Workbook
Name CNCodes_ListKey: Parameters_CNCodes!$D$4:$D$572
Name CNCodes_ListNames: Parameters_CNCodes!$C$4:$C$572
Name CNCodes_ListNumbering: Parameters_CNCodes!$F$4:$F$572
Name CNTR_CBAMPeriod: Parameters_Constants!$B$1
Name CNTR_HasEntriesA: A_InstData!$K$124
Name CNTR_IOProcAndPrec: InputOutput!$D$71:$D$100
Name CNTR_IOSupplyChain: InputOutput!$AR$71:$BU$100
Name CNTR_List_ExistGoodTypes: A_InstData!$S$62:$S$71
Name CNTR_List_ExistGoodTypesInclDir: A_InstData!$S$61:$S$71
Name CNTR_List_ExistProdProc: A_InstData!$S$83:$S$92
Name CNTR_List_ExistProdProcNames: A_InstData!$T$83:$T$92
Name CNTR_List_ExistPurchPrec: A_InstData!$S$102:$S$121
Name CNTR_List_ExistPurchPrecNames: A_InstData!$T$102:$T$121
Name CNTR_ListCountriesCode: c_CodeLists!$F$11:$F$277
Name CNTR_ListCountriesName: c_CodeLists!$G$11:$G$277
Name CNTR_ListCurrenciesCode: c_CodeLists!$K$11:$K$177
Name CNTR_ListCurrenciesName: c_CodeLists!$L$11:$L$177
Name CNTR_ListProdProcID: A_InstData!$D$83:$D$92
Name CNTR_ListProdProcNames: A_InstData!$L$83:$L$92
Name CNTR_ListPurchPrecID: A_InstData!$D$102:$D$121
Name CNTR_Matrix_Inv: InputOutput!$E$71:$AH$100
Name CNTR_MatrixPurchPrecRoutes: A_InstData!$X$102:$AB$121
Name CONST_AllProdRoutes: Parameters_Constants!$B$63
Name CONST_CarbonPriceType: Parameters_Constants!$C$45:$I$45
Name CONST_CEMSType: Parameters_Constants!$B$55:$C$55
Name CONST_CNTR_ElecEFMethod: Parameters_Constants!$B$10
Name CONST_CNTR_EmbedEmDir: Parameters_Constants!$B$2
Name CONST_CNTR_EmbedEmInDir: Parameters_Constants!$B$11
Name CONST_CNTR_ListGoodsForCN: Parameters_Constants!$B$133:$S$133
Name CONST_CNTR_PrecNumbering: Parameters_Constants!$BL$89:$BL$106
Name CONST_CNTR_SUM_CO2: Parameters_Constants!$B$3
Name CONST_CNTR_SUM_N2O: Parameters_Constants!$B$5
Name CONST_CNTR_SUM_PFC: Parameters_Constants!$B$4
Name CONST_CNTR_TotProd: Parameters_Constants!$B$12
Name CONST_DataQuality: Parameters_Constants!$B$42:$F$42
Name CONST_DataQualityJustification: Parameters_Constants!$B$44:$D$44
Name CONST_DataVerification: Parameters_Constants!$B$43:$E$43
Name CONST_EFNatGas: Parameters_Constants!$B$13
Name CONST_ElecConsumption: Parameters_Constants!$B$14
Name CONST_ElecSource: Parameters_Constants!$B$15:$H$15
Name CONST_EmDir: Parameters_Constants!$B$7
Name CONST_EmDirHeat: Parameters_Constants!$B$8
Name CONST_EmDirWasteGases: Parameters_Constants!$B$9
Name CONST_ERR_Duplicate: Parameters_Constants!$B$67
Name CONST_ERR_Incomplete: Parameters_Constants!$B$65
Name CONST_ERR_Inconsistent: Parameters_Constants!$B$66
Name CONST_ErrorOrMissing: Parameters_Constants!$B$16
Name CONST_GJ: Parameters_Constants!$B$25
Name CONST_GJpkNm3: Parameters_Constants!$B$36
Name CONST_GJpt: Parameters_Constants!$B$28
Name CONST_GoodToMarket: Parameters_Constants!$B$17
Name CONST_gpNm3: Parameters_Constants!$B$52
Name CONST_GWh: Parameters_Constants!$B$29
Name CONST_GWP_C2F6: Parameters_Constants!$B$78
Name CONST_GWP_CF4: Parameters_Constants!$B$77
Name CONST_GWP_N2O: Parameters_Constants!$B$76
Name CONST_hpa: Parameters_Constants!$B$50
Name CONST_kNm3: Parameters_Constants!$B$27
Name CONST_kNm3pa: Parameters_Constants!$B$53
Name CONST_LinkFromGuidance: Parameters_Constants!$B$73

Sheet 0_Versions
A1: ausblenden | P1: ausblenden | Q1: ausblenden | R1: ausblenden | S1: ausblenden | T1: ausblenden | U1: ausblenden
B2: =Translations!$B$5 | E2: =Translations!$B$11 | G2: =HYPERLINK("#"&ADDRESS(2,3,,,a_Contents!$U$2),a_Contents!$B$2) | I2: =HYPERLINK("#"&ADDRESS(2,3,,,G_FurtherGuidance!$U$2),G_FurtherGuidance!$B$2) | K2: =HYPERLINK("#"&ADDRESS(2,3,,,Summary_Processes!$Y$2),Summary_Processes!$Y$2) | M2: =HYPERLINK("#"&ADDRESS(2,3,,,Summary_Products!$BF$2),Summary_Products!$BF$2) | R2: Print area: | S2: =ADDRESS(ROW($B$6),COLUMN($B$6)) & ":" & ADDRESS(MATCH("PRINT",$P:$P,0),COLUMN($O$6)) | T2: Name of this sheet | U2: =IF(ISERROR(CELL("filename",V2)),"0_Versions",MID(CELL("filename",V2),FIND("]",CELL("filename",V2))+1,1024))
C6: =Translations!$B$6
E8: =Translations!$B$7 | F8: =Translations!$B$8 | G8: =Translations!$B$9
E9: 0.1 | F9: 45159 | G9: =Translations!$B$1889
E10: 1.0 | F10: 45222 | G10: =Translations!$B$1890
G11: =Translations!$B$1891
G12: =Translations!$B$1892
G13: =Translations!$B$1893
G14: =Translations!$B$1894
G15: =Translations!$B$1895
E16: 1.1 | F16: 45237 | G16: =Translations!$B$1896
E17: 2.0 | F17: 45370 | G17: =Translations!$B$1897
G18: =Translations!$B$1898
G19: =Translations!$B$1899
G20: =Translations!$B$1900
G21: =Translations!$B$1901
G22: =Translations!$B$1902
G23: =Translations!$B$1903
G24: =Translations!$B$1904
G25: =Translations!$B$1905
G26: =Translations!$B$1906
G27: =Translations!$B$1907
G28: =Translations!$B$1908
G29: =Translations!$B$1909
G30: =Translations!$B$1910
G31: =Translations!$B$1911
G32: =Translations!$B$1912
G33: =Translations!$B$1913
G34: =Translations!$B$1914
E35: 2.0.1 | F35: 45390 | G35: =Translations!$B$2104
E36: 2.1 | F36: 45448 | G36: =Translations!$B$2116
G37: =Translations!$B$2118
A53: ausblenden | P53: PRINT

Sheet a_Contents
A1: ausblenden | P1: ausblenden | Q1: ausblenden | R1: ausblenden | S1: ausblenden | T1: ausblenden | U1: ausblenden
B2: =Translations!$B$10 | E2: =Translations!$B$11 | G2: =HYPERLINK("#"&ADDRESS(2,3,,,a_Contents!$U$2),a_Contents!$B$2) | I2: =HYPERLINK("#"&ADDRESS(2,3,,,G_FurtherGuidance!$U$2),G_FurtherGuidance!$B$2) | K2: =HYPERLINK("#"&ADDRESS(2,3,,,Summary_Processes!$Y$2),Summary_Processes!$Y$2) | M2: =HYPERLINK("#"&ADDRESS(2,3,,,Summary_Products!$BF$2),Summary_Products!$BF$2) | R2: Print area: | S2: =ADDRESS(ROW($B$6),COLUMN($B$6)) & ":" & ADDRESS(MATCH("PRINT",$P:$P,0),COLUMN($O$6)) | T2: Name of this sheet | U2: =IF(ISERROR(CELL("filename",V2)),"a_Contents",MID(CELL("filename",V2),FIND("]",CELL("filename",V2))+1,1024))
C6: =Translations!$B$12
C8: 0. | D8: =HYPERLINK("#"&S8,INDIRECT(S8)) | S8: =ADDRESS(6,3,,,T8) | T8: ='0_Versions'!$U$2
C10: a. | D10: =HYPERLINK("#"&S10,INDIRECT(S10)) | S10: =ADDRESS(6,3,,,T10) | T10: =$U$2
C12: b. | D12: =HYPERLINK("#"&S12,INDIRECT(S12)) | S12: =ADDRESS(6,3,,,T12) | T12: ='b_Guidelines&Conditions'!$U$2
C14: c. | D14: =HYPERLINK("#"&S14,INDIRECT(S14)) | S14: =ADDRESS(6,3,,,T14) | T14: =c_CodeLists!$U$2
C16: A. | D16: =HYPERLINK("#"&S16,INDIRECT(S16)) | S16: =ADDRESS(6,5,,,T16) | T16: =A_InstData!$U$2
D17: 1 | E17: =HYPERLINK("#"&S17,INDIRECT(S17)) | S17: =ADDRESS(MATCH(D17,INDIRECT("'"& T17 & "'!A:A")),4,,,T17) | T17: =T16
D18: 2 | E18: =HYPERLINK("#"&S18,INDIRECT(S18)) | S18: =ADDRESS(MATCH(D18,INDIRECT("'"& T18 & "'!A:A")),4,,,T18) | T18: =T17
D19: 3 | E19: =HYPERLINK("#"&S19,INDIRECT(S19)) | S19: =ADDRESS(MATCH(D19,INDIRECT("'"& T19 & "'!A:A")),4,,,T19) | T19: =T18
D20: 4 | E20: =HYPERLINK("#"&S20,INDIRECT(S20)) | S20: =ADDRESS(MATCH(D20,INDIRECT("'"& T20 & "'!A:A")),4,,,T20) | T20: =T19
D21: 5 | E21: =HYPERLINK("#"&S21,INDIRECT(S21)) | S21: =ADDRESS(MATCH(D21,INDIRECT("'"& T21 & "'!A:A")),4,,,T21) | T21: =T20
C23: B. | D23: =HYPERLINK("#"&S23,INDIRECT(S23)) | S23: =ADDRESS(6,4,,,T23) | T23: =B_EmInst!$BD$2
D24: 1 | E24: =HYPERLINK("#"&S24,INDIRECT(S24)) | S24: =ADDRESS(MATCH(D24,INDIRECT("'"& T24 & "'!A:A")),4,,,T24) | T24: =T23
D25: 2 | E25: =HYPERLINK("#"&S25,INDIRECT(S25)) | S25: =ADDRESS(MATCH(D25,INDIRECT("'"& T25 & "'!A:A")),4,,,T25) | T25: =T24
D26: 3 | E26: =HYPERLINK("#"&S26,INDIRECT(S26)) | S26: =ADDRESS(MATCH(D26,INDIRECT("'"& T26 & "'!A:A")),4,,,T26) | T26: =T25
C28: C. | D28: =HYPERLINK("#"&S28,INDIRECT(S28)) | S28: =ADDRESS(6,5,,,T28) | T28: ='C_Emissions&Energy'!$U$2
D29: 1 | E29: =HYPERLINK("#"&S29,INDIRECT(S29)) | S29: =ADDRESS(MATCH(D29,INDIRECT("'"& T29 & "'!A:A")),4,,,T29) | T29: =T28
D30: 2 | E30: =HYPERLINK("#"&S30,INDIRECT(S30)) | S30: =ADDRESS(MATCH(D30,INDIRECT("'"& T30 & "'!A:A")),4,,,T30) | T30: =T29
C32: D. | D32: =HYPERLINK("#"&S32,INDIRECT(S32)) | S32: =ADDRESS(7,5,,,T32) | T32: =D_Processes!$U$2
D33: 1 | E33: =HYPERLINK("#"&S33,INDIRECT(S33)) | S33: =ADDRESS(MATCH(D33,INDIRECT("'"& T33 & "'!A:A")),4,,,T33) | T33: =T32
C35: E. | D35: =HYPERLINK("#"&S35,INDIRECT(S35)) | S35: =ADDRESS(8,5,,,T35) | T35: =E_PurchPrec!$U$2
D36: 1 | E36: =HYPERLINK("#"&S36,INDIRECT(S36)) | S36: =ADDRESS(MATCH(D36,INDIRECT("'"& T36 & "'!A:A")),4,,,T36) | T36: =T35
C38: F. | D38: =HYPERLINK("#"&S38,INDIRECT(S38)) | S38: =ADDRESS(6,5,,,T38) | T38: =F_Tools!$U$2
D39: 1 | E39: =HYPERLINK("#"&S39,INDIRECT(S39)) | S39: =ADDRESS(MATCH(D39,INDIRECT("'"& T39 & "'!A:A")),4,,,T39) | T39: =T38
D40: 2 | E40: =HYPERLINK("#"&S40,INDIRECT(S40)) | S40: =ADDRESS(MATCH(D40,INDIRECT("'"& T40 & "'!A:A")),4,,,T40) | T40: =T39
C42: G. | D42: =HYPERLINK("#"&S42,INDIRECT(S42)) | S42: =ADDRESS(6,5,,,T42) | T42: =G_FurtherGuidance!$U$2
D43: 1 | E43: =HYPERLINK("#"&S43,INDIRECT(S43)) | S43: =ADDRESS(MATCH(D43,INDIRECT("'"& T43 & "'!A:A")),4,,,T43) | T43: =T42
D44: 2 | E44: =HYPERLINK("#"&S44,INDIRECT(S44)) | S44: =ADDRESS(MATCH(D44,INDIRECT("'"& T44 & "'!A:A")),4,,,T44) | T44: =T43
D45: 3 | E45: =HYPERLINK("#"&S45,INDIRECT(S45)) | S45: =ADDRESS(MATCH(D45,INDIRECT("'"& T45 & "'!A:A")),4,,,T45) | T45: =T44
D46: 4 | E46: =HYPERLINK("#"&S46,INDIRECT(S46)) | S46: =ADDRESS(MATCH(D46,INDIRECT("'"& T46 & "'!A:A")),4,,,T46) | T46: =T45
D47: 5 | E47: =HYPERLINK("#"&S47,INDIRECT(S47)) | S47: =ADDRESS(MATCH(D47,INDIRECT("'"& T47 & "'!A:A")),4,,,T47) | T47: =T46
D50: =Translations!$B$13
D51: =HYPERLINK("#"&S51,INDIRECT(S51)) | S51: =ADDRESS(2,2,,,T51) | T51: =Summary_Processes!$Y$2
D52: =HYPERLINK("#"&S52,INDIRECT(S52)) | S52: =ADDRESS(2,2,,,T52) | T52: =Summary_Products!$BF$2
D54: =Translations!$B$14
D55: =HYPERLINK("#"&S55,INDIRECT(S55)) | S55: =ADDRESS(2,2,,,T55) | T55: =Summary_Communication!$BE$2
D59: =Translations!$B$15 | H59: =INDEX(Translations!$C$4:$M$4,Translations!A3-2)
D60: =Translations!$B$16 | H60: =VersionDocumentation!C3
D62: =Translations!$B$17
D63: =Translations!$B$18 | H63: =IF(A_InstData!I20="","",A_InstData!I20)
D64: =Translations!$B$19 | H64: =Translations!$B$20 | I64: =IF(A_InstData!I9="","",A_InstData!I9) | J64: =Translations!$B$21 | K64: =IF(A_InstData!L9="","",A_InstData!L9)
A66: ausblenden | P66: PRINT
A67: ausblenden
A68: ausblenden
A69: ausblenden

Sheet b_Guidelines&Conditions
A1: ausblenden | P1: ausblenden | Q1: ausblenden | R1: ausblenden | S1: ausblenden | T1: ausblenden | U1: ausblenden
B2: =Translations!$B$22 | E2: =Translations!$B$11 | G2: =HYPERLINK("#"&ADDRESS(2,3,,,a_Contents!$U$2),a_Contents!$B$2) | I2: =HYPERLINK("#"&ADDRESS(2,3,,,G_FurtherGuidance!$U$2),G_FurtherGuidance!$B$2) | K2: =HYPERLINK("#"&ADDRESS(2,3,,,Summary_Processes!$Y$2),Summary_Processes!$Y$2) | M2: =HYPERLINK("#"&ADDRESS(2,3,,,Summary_Products!$BF$2),Summary_Products!$BF$2) | R2: Print area: | S2: =ADDRESS(ROW($B$6),COLUMN($B$6)) & ":" & ADDRESS(MATCH("PRINT",$P:$P,0),COLUMN($O$6)) | T2: Name of this sheet | U2: =IF(ISERROR(CELL("filename",V2)),"b_Guidelines&Conditions",MID(CELL("filename",V2),FIND("]",CELL("filename",V2))+1,1024))
G3: =IFERROR(HYPERLINK("#"&ADDRESS(ROW($A$1)+MATCH(R3,$A:$A,0)-1,COLUMN($A$1)),INDEX($R:$R,MATCH(R3,$A:$A,0))),"") | I3: =IFERROR(HYPERLINK("#"&ADDRESS(ROW($A$1)+MATCH(T3,$A:$A,0)-1,COLUMN($A$1)),INDEX($R:$R,MATCH(T3,$A:$A,0))),"") | R3: 1 | T3: 2
C6: =Translations!$B$23
A8: 1 | C8: =Translations!$B$24 | R8: General information
B10: 1 | C10: =Translations!$B$26
C11: =HYPERLINK(Translations!$B$27,Translations!$B$27)
B12: 2 | C12: =Translations!$B$1915
C13: =HYPERLINK(Translations!$B$1916,Translations!$B$1916)
B14: 3 | C14: =Translations!$B$30
B15: 4 | C15: =Translations!$B$31
C16: =Translations!$B$32
B17: 5 | C17: =Translations!$B$1917
A19: 2 | C19: =Translations!$B$34 | R19: =C19
B21: 6 | C21: =Translations!$B$35
C22: =Translations!$B$36
B23: 7 | C23: =Translations!$B$1918
B24: 8 | C24: =Translations!$B$38
B25: 9 | C25: =Translations!$B$39
C26: =Translations!$B$1919
B28: 10 | C28: =Translations!$B$41
D29: =Translations!$B$42 | F29: =Translations!$B$43
D30: =Translations!$B$44 | F30: =Translations!$B$45
F31: =Translations!$B$46
F32: =Translations!$B$47
F33: =Translations!$B$48
D34: =CONST_NA | F34: =Translations!$B$1920
F35: =Translations!$B$50
D37: =Translations!$B$1921
E38: =Translations!$B$52
E39: =Translations!$B$53
E40: =Translations!$B$54
B42: 11 | C42: =Translations!$B$55
B43: 12 | C43: =Translations!$B$56
B44: 13 | C44: =Translations!$B$57
B46: 14 | C46: =Translations!$B$58
C48: =Translations!$B$59
C49: =Translations!$B$60 | F49: =HYPERLINK(Translations!$B$61,Translations!$B$61)
C50: =Translations!$B$62 | F50: =HYPERLINK(Translations!$B$63,Translations!$B$63)
A52: ausblenden | P52: PRINT

Sheet c_CodeLists
A1: ausblenden | P1: ausblenden | Q1: ausblenden | R1: ausblenden | S1: ausblenden | T1: ausblenden | U1: ausblenden | V1: ausblenden | W1: ausblenden | X1: ausblenden
B2: =Translations!$B$1438 | E2: =Translations!$B$11 | G2: =HYPERLINK("#"&ADDRESS(2,3,,,a_Contents!$U$2),a_Contents!$B$2) | I2: =HYPERLINK("#"&ADDRESS(2,3,,,G_FurtherGuidance!$U$2),G_FurtherGuidance!$B$2) | K2: =HYPERLINK("#"&ADDRESS(2,3,,,Summary_Processes!$Y$2),Summary_Processes!$Y$2) | M2: =HYPERLINK("#"&ADDRESS(2,3,,,Summary_Products!$BF$2),Summary_Products!$BF$2) | R2: Print area: | S2: =ADDRESS(ROW($B$2),COLUMN(B2)) & ":" & ADDRESS(MATCH("PRINT",$P:$P,0),COLUMN(O4)) | T2: Name of this sheet | U2: =IF(ISERROR(CELL("filename",V2)),"c_CodeLists",MID(CELL("filename",V2),FIND("]",CELL("filename",V2))+1,1024))
G3: =IFERROR(HYPERLINK("#"&ADDRESS(ROW($A$1)+MATCH(R3,$A:$A,0)-1,3),INDEX($R:$R,MATCH(R3,$A:$A,0))),"") | I3: =IFERROR(HYPERLINK("#"&ADDRESS(ROW($A$1)+MATCH(T3,$A:$A,0)-1,3),INDEX($R:$R,MATCH(T3,$A:$A,0))),"") | R3: 1 | T3: 2
C6: =Translations!$B$1439 | R6: Marker | S6: EmbedEm | V6: Errors | X6: Cond. form.
A8: =C8 | C8: 1 | D8: =Translations!$B$1440 | R8: =D8 | S8: =C8
F10: =Translations!$B$1441 | G10: =Translations!$B$1442 | K10: =Translations!$B$1441 | L10: =Translations!$B$1443 | S10: CNTR_ListCountriesCode | T10: CNTR_ListCountriesName | U10: CNTR_ListCurrenciesCode | V10: CNTR_ListCurrenciesName
E11: 1 | F11: AD | G11: =Translations!$B$1444 | J11: 1 | K11: AED | L11: =Translations!$B$1445
E12: 2 | F12: AE | G12: =Translations!$B$1446 | J12: 2 | K12: AFN | L12: =Translations!$B$1447
E13: 3 | F13: AF | G13: =Translations!$B$1448 | J13: 3 | K13: ALL | L13: =Translations!$B$1449
E14: 4 | F14: AG | G14: =Translations!$B$1450 | J14: 4 | K14: AMD | L14: =Translations!$B$1451
E15: 5 | F15: AI | G15: =Translations!$B$1452 | J15: 5 | K15: ANG | L15: =Translations!$B$1453
E16: 6 | F16: AL | G16: =Translations!$B$1454 | J16: 6 | K16: AOA | L16: =Translations!$B$1455
E17: 7 | F17: AM | G17: =Translations!$B$1456 | J17: 7 | K17: ARS | L17: =Translations!$B$1457
E18: 8 | F18: AN | G18: =Translations!$B$1458 | J18: 8 | K18: AUD | L18: =Translations!$B$1459
E19: 9 | F19: AO | G19: =Translations!$B$1460 | J19: 9 | K19: AWG | L19: =Translations!$B$1461
E20: 10 | F20: AQ | G20: =Translations!$B$1461 | J20: 10 | K20: AZN | L20: =Translations!$B$1463
E21: 11 | F21: AR | G21: =Translations!$B$1464 | J21: 11 | K21: BAM | L21: =Translations!$B$1465
E22: 12 | F22: AS | G22: =Translations!$B$1466 | J22: 12 | K22: BBD | L22: =Translations!$B$1467
E23: 13 | F23: AT | G23: =Translations!$B$1922 | J23: 13 | K23: BDT | L23: =Translations!$B$1468
E24: 14 | F24: AU | G24: =Translations!$B$1469 | J24: 14 | K24: BGN | L24: =Translations!$B$1470
E25: 15 | F25: AW | G25: =Translations!$B$1471 | J25: 15 | K25: BHD | L25: =Translations!$B$1472
E26: 16 | F26: AX | G26: =Translations!$B$1473 | J26: 16 | K26: BIF | L26: =Translations!$B$1474
E27: 17 | F27: AZ | G27: =Translations!$B$1475 | J27: 17 | K27: BMD | L27: =Translations!$B$1476
E28: 18 | F28: BA | G28: =Translations!$B$1477 | J28: 18 | K28: BND | L28: =Translations!$B$1478
E29: 19 | F29: BB | G29: =Translations!$B$1479 | J29: 19 | K29: BOB | L29: =Translations!$B$1480
E30: 20 | F30: BD | G30: =Translations!$B$1481 | J30: 20 | K30: BOV | L30: =Translations!$B$1482
E31: 21 | F31: BE | G31: =Translations!$B$1923 | J31: 21 | K31: BRL | L31: =Translations!$B$1483
E32: 22 | F32: BF | G32: =Translations!$B$1484 | J32: 22 | K32: BSD | L32: =Translations!$B$1485
E33: 23 | F33: BG | G33: =Translations!$B$1924 | J33: 23 | K33: BTN | L33: =Translations!$B$1486
E34: 24 | F34: BH | G34: =Translations!$B$1487 | J34: 24 | K34: BWP | L34: =Translations!$B$1488
E35: 25 | F35: BI | G35: =Translations!$B$1489 | J35: 25 | K35: BYN | L35: =Translations!$B$1490
E36: 26 | F36: BJ | G36: =Translations!$B$1491 | J36: 26 | K36: BZD | L36: =Translations!$B$1492
E37: 27 | F37: BL | G37: =Translations!$B$1493 | J37: 27 | K37: CAD | L37: =Translations!$B$1494
E38: 28 | F38: BM | G38: =Translations!$B$1495 | J38: 28 | K38: CDF | L38: =Translations!$B$1496
E39: 29 | F39: BN | G39: =Translations!$B$1497 | J39: 29 | K39: CHE | L39: =Translations!$B$1498
E40: 30 | F40: BO | G40: =Translations!$B$1499 | J40: 30 | K40: CHF | L40: =Translations!$B$1500
E41: 31 | F41: BQ | G41: =Translations!$B$1501 | J41: 31 | K41: CHW | L41: =Translations!$B$1502
E42: 32 | F42: BR | G42: =Translations!$B$1503 | J42: 32 | K42: CLF | L42: =Translations!$B$1504
E43: 33 | F43: BS | G43: =Translations!$B$1505 | J43: 33 | K43: CLP | L43: =Translations!$B$1506
E44: 34 | F44: BT | G44: =Translations!$B$1507 | J44: 34 | K44: CNY | L44: =Translations!$B$1508
E45: 35 | F45: BV | G45: =Translations!$B$1509 | J45: 35 | K45: COP | L45: =Translations!$B$1510
E46: 36 | F46: BW | G46: =Translations!$B$1511 | J46: 36 | K46: COU | L46: =Translations!$B$1512
E47: 37 | F47: BY | G47: =Translations!$B$1513 | J47: 37 | K47: CRC | L47: =Translations!$B$1514
E48: 38 | F48: BZ | G48: =Translations!$B$1515 | J48: 38 | K48: CUC | L48: =Translations!$B$1516
E49: 39 | F49: CA | G49: =Translations!$B$1517 | J49: 39 | K49: CUP | L49: =Translations!$B$1518
E50: 40 | F50: CC | G50: =Translations!$B$1519 | J50: 40 | K50: CVE | L50: =Translations!$B$1520
E51: 41 | F51: CD | G51: =Translations!$B$1521 | J51: 41 | K51: CZK | L51: =Translations!$B$1522
E52: 42 | F52: CF | G52: =Translations!$B$1523 | J52: 42 | K52: DJF | L52: =Translations!$B$1524
E53: 43 | F53: CG | G53: =Translations!$B$1525 | J53: 43 | K53: DKK | L53: =Translations!$B$1526
E54: 44 | F54: CH | G54: =Translations!$B$1527 | J54: 44 | K54: DOP | L54: =Translations!$B$1528
E55: 45 | F55: CI | G55: =Translations!$B$1529 | J55: 45 | K55: DZD | L55: =Translations!$B$1530
E56: 46 | F56: CK | G56: =Translations!$B$1531 | J56: 46 | K56: EGP | L56: =Translations!$B$1532
E57: 47 | F57: CL | G57: =Translations!$B$1533 | J57: 47 | K57: ERN | L57: =Translations!$B$1534
E58: 48 | F58: CM | G58: =Translations!$B$1535 | J58: 48 | K58: ETB | L58: =Translations!$B$1536
E59: 49 | F59: CN | G59: =Translations!$B$1537 | J59: 49 | K59: EUR | L59: =Translations!$B$1538
E60: 50 | F60: CO | G60: =Translations!$B$1539 | J60: 50 | K60: FJD | L60: =Translations!$B$1540
E61: 51 | F61: CR | G61: =Translations!$B$1541 | J61: 51 | K61: FKP | L61: =Translations!$B$1542
E62: 52 | F62: CU | G62: =Translations!$B$1545 | J62: 52 | K62: GBP | L62: =Translations!$B$1544
E63: 53 | F63: CV | G63: =Translations!$B$1547 | J63: 53 | K63: GEL | L63: =Translations!$B$1546
E64: 54 | F64: CW | G64: =Translations!$B$1549 | J64: 54 | K64: GHS | L64: =Translations!$B$1548
E65: 55 | F65: CX | G65: =Translations!$B$1551 | J65: 55 | K65: GIP | L65: =Translations!$B$1550
E66: 56 | F66: CY | G66: =Translations!$B$1925 | J66: 56 | K66: GMD | L66: =Translations!$B$1552
E67: 57 | F67: CZ | G67: =Translations!$B$1554 | J67: 57 | K67: GNF | L67: =Translations!$B$1553
E68: 58 | F68: DE | G68: =Translations!$B$1926 | J68: 58 | K68: GTQ | L68: =Translations!$B$1555
E69: 59 | F69: DJ | G69: =Translations!$B$1557 | J69: 59 | K69: GYD | L69: =Translations!$B$1556
E70: 60 | F70: DK | G70: =Translations!$B$1927 | J70: 60 | K70: HKD | L70: =Translations!$B$1558
E71: 61 | F71: DM | G71: =Translations!$B$1560 | J71: 61 | K71: HNL | L71: =Translations!$B$1559
E72: 62 | F72: DO | G72: =Translations!$B$1562 | J72: 62 | K72: HTG | L72: =Translations!$B$1561
E73: 63 | F73: DZ | G73: =Translations!$B$1564 | J73: 63 | K73: HUF | L73: =Translations!$B$1563
E74: 64 | F74: EC | G74: =Translations!$B$1566 | J74: 64 | K74: IDR | L74: =Translations!$B$1565
E75: 65 | F75: EE | G75: =Translations!$B$1928 | J75: 65 | K75: ILS | L75: =Translations!$B$1567
E76: 66 | F76: EG | G76: =Translations!$B$1569 | J76: 66 | K76: INR | L76: =Translations!$B$1568
E77: 67 | F77: EH | G77: =Translations!$B$1571 | J77: 67 | K77: IQD | L77: =Translations!$B$1570
E78: 68 | F78: ER | G78: =Translations!$B$1573 | J78: 68 | K78: IRR | L78: =Translations!$B$1572
E79: 69 | F79: ES | G79: =Translations!$B$1929 | J79: 69 | K79: ISK | L79: =Translations!$B$1574
E80: 70 | F80: ET | G80: =Translations!$B$1576 | J80: 70 | K80: JMD | L80: =Translations!$B$1575
E81: 71 | F81: EU | G81: =Translations!$B$1578 | J81: 71 | K81: JOD | L81: =Translations!$B$1577
E82: 72 | F82: FI | G82: =Translations!$B$1930 | J82: 72 | K82: JPY | L82: =Translations!$B$1579
E83: 73 | F83: FJ | G83: =Translations!$B$1581 | J83: 73 | K83: KES | L83: =Translations!$B$1580
E84: 74 | F84: FK | G84: =Translations!$B$1583 | J84: 74 | K84: KGS | L84: =Translations!$B$1582
E85: 75 | F85: FM | G85: =Translations!$B$1585 | J85: 75 | K85: KHR | L85: =Translations!$B$1584
E86: 76 | F86: FO | G86: =Translations!$B$1587 | J86: 76 | K86: KMF | L86: =Translations!$B$1586
E87: 77 | F87: FR | G87: =Translations!$B$1931 | J87: 77 | K87: KPW | L87: =Translations!$B$1588
E88: 78 | F88: GA | G88: =Translations!$B$1590 | J88: 78 | K88: KRW | L88: =Translations!$B$1589
E89: 79 | F89: GB | G89: =Translations!$B$1932 | J89: 79 | K89: KWD | L89: =Translations!$B$1591
E90: 80 | F90: GD | G90: =Translations!$B$1593 | J90: 80 | K90: KYD | L90: =Translations!$B$1592
E91: 81 | F91: GE | G91: =Translations!$B$1595 | J91: 81 | K91: KZT | L91: =Translations!$B$1594
E92: 82 | F92: GF | G92: =Translations!$B$1597 | J92: 82 | K92: LAK | L92: =Translations!$B$1596
E93: 83 | F93: GG | G93: =Translations!$B$1599 | J93: 83 | K93: LBP | L93: =Translations!$B$1598
E94: 84 | F94: GH | G94: =Translations!$B$1601 | J94: 84 | K94: LKR | L94: =Translations!$B$1600
E95: 85 | F95: GI | G95: =Translations!$B$1603 | J95: 85 | K95: LRD | L95: =Translations!$B$1602
E96: 86 | F96: GL | G96: =Translations!$B$1605 | J96: 86 | K96: LSL | L96: =Translations!$B$1604
E97: 87 | F97: GM | G97: =Translations!$B$1607 | J97: 87 | K97: LYD | L97: =Translations!$B$1606
E98: 88 | F98: GN | G98: =Translations!$B$1609 | J98: 88 | K98: MAD | L98: =Translations!$B$1608
E99: 89 | F99: GP | G99: =Translations!$B$1611 | J99: 89 | K99: MDL | L99: =Translations!$B$1610
E100: 90 | F100: GQ | G100: =Translations!$B$1613 | J100: 90 | K100: MGA | L100: =Translations!$B$1612
E101: 91 | F101: GR | G101: =Translations!$B$1933 | J101: 91 | K101: MKD | L101: =Translations!$B$1614
E102: 92 | F102: GS | G102: =Translations!$B$1616 | J102: 92 | K102: MMK | L102: =Translations!$B$1615
E103: 93 | F103: GT | G103: =Translations!$B$1618 | J103: 93 | K103: MNT | L103: =Translations!$B$1617
E104: 94 | F104: GU | G104: =Translations!$B$1620 | J104: 94 | K104: MOP | L104: =Translations!$B$1619
...

Sheet A_InstData
A1: ausblenden | P1: ausblenden | Q1: ausblenden | R1: ausblenden | S1: ausblenden | T1: ausblenden | U1: ausblenden | V1: ausblenden | W1: ausblenden | X1: ausblenden | Y1: ausblenden | Z1: ausblenden | AA1: ausblenden | AB1: ausblenden | AC1: ausblenden | AD1: ausblenden | AE1: ausblenden | AF1: ausblenden | AG1: ausblenden | AH1: ausblenden | AI1: ausblenden
B2: =Translations!$B$64 | E2: =Translations!$B$11 | G2: =HYPERLINK("#"&ADDRESS(2,3,,,a_Contents!$U$2),a_Contents!$B$2) | I2: =HYPERLINK("#"&ADDRESS(2,3,,,G_FurtherGuidance!$U$2),G_FurtherGuidance!$B$2) | K2: =HYPERLINK("#"&ADDRESS(2,3,,,Summary_Processes!$Y$2),Summary_Processes!$Y$2) | M2: =HYPERLINK("#"&ADDRESS(2,3,,,Summary_Products!$BF$2),Summary_Products!$BF$2) | R2: Print area: | S2: =ADDRESS(ROW($B$6),COLUMN($B$55)) & ":" & ADDRESS(MATCH("PRINT",$P:$P,0),COLUMN($O$55)) | T2: Name of this sheet | U2: =IF(ISERROR(CELL("filename",V2)),"A_InstData",MID(CELL("filename",V2),FIND("]",CELL("filename",V2))+1,1024))
G3: =IFERROR(HYPERLINK("#"&ADDRESS(ROW($A$1)+MATCH(R3,$A:$A,0)-1,3),INDEX($R:$R,MATCH(R3,$A:$A,0))),"") | I3: =IFERROR(HYPERLINK("#"&ADDRESS(ROW($A$1)+MATCH(T3,$A:$A,0)-1,3),INDEX($R:$R,MATCH(T3,$A:$A,0))),"") | K3: =IFERROR(HYPERLINK("#"&ADDRESS(ROW($A$1)+MATCH(V3,$A:$A,0)-1,3),INDEX($R:$R,MATCH(V3,$A:$A,0))),"") | M3: =IFERROR(HYPERLINK("#"&ADDRESS(ROW($A$1)+MATCH(X3,$A:$A,0)-1,3),INDEX($R:$R,MATCH(X3,$A:$A,0))),"") | R3: 1 | T3: 2 | V3: 3 | X3: 4
G4: =IFERROR(HYPERLINK("#"&ADDRESS(ROW($A$1)+MATCH(R4,$A:$A,0)-1,3),INDEX($R:$R,MATCH(R4,$A:$A,0))),"") | R4: 5
C6: A. | E6: =Translations!$B$65 | R6: Marker | AG6: Errors | AI6: Cond. form.
A9: =C9 | C9: 1 | D9: =Translations!$B$67 | H9: =Translations!$B$68 | I9: 44562 | K9: =Translations!$B$69 | L9: 44926 | R9: =D9 | AG9: =IF(AND(CNTR_HasEntriesA,COUNTA(I9,L9)<2),CONST_ErrorOrMissing&A9,CONST_NA)
E13: =Translations!$B$1952
E14: =Translations!$B$71
A17: =C17 | C17: 2 | D17: =Translations!$B$72 | R17: =D17
D19: i. | E19: =Translations!$B$73 | I19: Ulsan Steel Plant 22
D20: ii. | E20: =Translations!$B$74 | I20: Ulsan Steel Plant 22 | AG20: =IF(AND(CNTR_HasEntriesA,I20=""),CONST_ErrorOrMissing&A17,CONST_NA)
D21: iii. | E21: =Translations!$B$75 | I21: Steel Way, 20
D22: iv. | E22: =Translations!$B$76 | I22: Blast furnace operation
D23: v. | E23: =Translations!$B$77 | I23: 305293
D24: vi. | E24: =Translations!$B$78 | I24: ROC
D25: vii. | E25: =Translations!$B$79 | I25: Ulsan
D26: viii. | E26: =Translations!$B$80 | I26: South Korea | S26: =IF(I26="","",INDEX(CNTR_ListCountriesCode,MATCH(I26,CNTR_ListCountriesName,0))) | AG26: =IF(AND(CNTR_HasEntriesA,I26=""),CONST_ErrorOrMissing&A17,CONST_NA)
D27: ix. | E27: =Translations!$B$81 | I27: KRRIV
D28: x. | E28: =Translations!$B$82 | I28: -24.1625416°
D29: xi. | E29: =Translations!$B$83 | I29: 163.199359°
D30: xii. | E30: =Translations!$B$84 | I30: Maria Tanaka
D31: xiii. | E31: =Translations!$B$85 | I31: maria.tanaka@example-steel.com
D32: xiv. | E32: =Translations!$B$86 | I32: +2 865617976
A34: =C34 | C34: 3 | D34: =Translations!$B$87 | R34: Verifier
D36: (a) | E36: =Translations!$B$89
D37: i. | E37: =Translations!$B$90
D38: ii. | E38: =Translations!$B$75
D39: iii. | E39: =Translations!$B$79
D40: iv. | E40: =Translations!$B$91
D41: v. | E41: =Translations!$B$80
D43: (b) | E43: =Translations!$B$92
E44: =Translations!$B$93
D45: i. | E45: =Translations!$B$94
D46: ii. | E46: =Translations!$B$95
D47: iii. | E47: =Translations!$B$96
D48: iv. | E48: =Translations!$B$97
D50: (c) | E50: =Translations!$B$98
D51: i. | E51: =Translations!$B$99
D52: ii. | E52: =Translations!$B$100
D53: iii. | E53: =Translations!$B$101
A55: =C55 | C55: 4 | D55: =Translations!$B$102 | R55: Goods & precursors
D57: (a) | E57: =Translations!$B$104
E58: =Translations!$B$105
E59: =Translations!$B$106
D61: ID | E61: =Translations!$B$107 | G61: =Translations!$B$108 | I61: =Translations!$B$109 | J61: =Translations!$B$110 | K61: =Translations!$B$111 | L61: =Translations!$B$112 | M61: =Translations!$B$113 | N61: =Translations!$B$114 | R61: CNTR_List_ExistGoodTypesInclDir | S61: =CONST_OnlyDirProd | W61: GoodID | X61: RouteID 1 | Y61: RouteID 2 | Z61: RouteID 3 | AA61: RouteID 4 | AB61: RouteID 5 | AC61: RouteID 6 | AE61: Incomplete? | AH61: PFC emissions relevant?
D62: G1 | E62: Sintered Ore | G62: =IF(E62="","",IF(COUNTIF(INDEX(CONST_MATRIX_ProductionRoute,MATCH(E62,CONST_LIST_Goods,0),),CONST_NA)=9,CONST_AllProdRoutes,CONST_PleaseSelect)) | R62: CNTR_List_ExistGoodTypes | S62: =IF(E62="",CONST_NA,E62) | T62: =IF(E62="","",INDEX(CONST_LIST_GoodsProdRouteAdd,MATCH(E62,CONST_LIST_Goods,0))) | V62: =D62 | W62: =IF(E62="","",MATCH(E62,CONST_LIST_Goods,0)) | X62: =IF(I62="","",$W62&"_"&MATCH(I62,INDEX(CONST_MATRIX_ProductionRoute,$W62,),0)) | Y62: =IF(J62="","",$W62&"_"&MATCH(J62,INDEX(CONST_MATRIX_ProductionRoute,$W62,),0)) | Z62: =IF(K62="","",$W62&"_"&MATCH(K62,INDEX(CONST_MATRIX_ProductionRoute,$W62,),0)) | AA62: =IF(L62="","",$W62&"_"&MATCH(L62,INDEX(CONST_MATRIX_ProductionRoute,$W62,),0)) | AB62: =IF(M62="","",$W62&"_"&MATCH(M62,INDEX(CONST_MATRIX_ProductionRoute,$W62,),0)) | AC62: =IF(N62="","",$W62&"_"&MATCH(N62,INDEX(CONST_MATRIX_ProductionRoute,$W62,),0)) | AE62: =IF(E62="","",COUNTIF($E$83:$K$92,E62)=0) | AG62: =IF(AND(CNTR_HasEntriesA,COUNTA(E62:F71)=0),CONST_ErrorOrMissing&A55,CONST_NA) | AH62: =IF(E62="","",INDEX(Parameters_Constants!$BN$89:$BN$106,MATCH(E62,CONST_LIST_Goods,0))) | AI62: =OR(AND(CNTR_HasEntriesA,E62=""),AND(E62<>"",G62=CONST_AllProdRoutes))
D63: G1 | E63: Pig iron | G63: =IF(E63="","",IF(COUNTIF(INDEX(CONST_MATRIX_ProductionRoute,MATCH(E63,CONST_LIST_Goods,0),),CONST_NA)=9,CONST_AllProdRoutes,CONST_PleaseSelect)) | I63: Blast furnace route | S63: =IF(E63="",CONST_NA,E63) | T63: =IF(E63="","",INDEX(CONST_LIST_GoodsProdRouteAdd,MATCH(E63,CONST_LIST_Goods,0))) | V63: =D63 | W63: =IF(E63="","",MATCH(E63,CONST_LIST_Goods,0)) | X63: =IF(I63="","",$W63&"_"&MATCH(I63,INDEX(CONST_MATRIX_ProductionRoute,$W63,),0)) | Y63: =IF(J63="","",$W63&"_"&MATCH(J63,INDEX(CONST_MATRIX_ProductionRoute,$W63,),0)) | Z63: =IF(K63="","",$W63&"_"&MATCH(K63,INDEX(CONST_MATRIX_ProductionRoute,$W63,),0)) | AA63: =IF(L63="","",$W63&"_"&MATCH(L63,INDEX(CONST_MATRIX_ProductionRoute,$W63,),0)) | AB63: =IF(M63="","",$W63&"_"&MATCH(M63,INDEX(CONST_MATRIX_ProductionRoute,$W63,),0)) | AC63: =IF(N63="","",$W63&"_"&MATCH(N63,INDEX(CONST_MATRIX_ProductionRoute,$W63,),0)) | AE63: =IF(E63="","",COUNTIF($E$83:$K$92,E63)=0) | AH63: =IF(E63="","",INDEX(Parameters_Constants!$BN$89:$BN$106,MATCH(E63,CONST_LIST_Goods,0))) | AI63: =OR(AND(CNTR_HasEntriesA,E63=""),AND(E63<>"",G63=CONST_AllProdRoutes))
D64: G3 | E64: Crude steel | G64: =IF(E64="","",IF(COUNTIF(INDEX(CONST_MATRIX_ProductionRoute,MATCH(E64,CONST_LIST_Goods,0),),CONST_NA)=9,CONST_AllProdRoutes,CONST_PleaseSelect)) | I64: Basic oxygen steelmaking | S64: =IF(E64="",CONST_NA,E64) | T64: =IF(E64="","",INDEX(CONST_LIST_GoodsProdRouteAdd,MATCH(E64,CONST_LIST_Goods,0))) | V64: =D64 | W64: =IF(E64="","",MATCH(E64,CONST_LIST_Goods,0)) | X64: =IF(I64="","",$W64&"_"&MATCH(I64,INDEX(CONST_MATRIX_ProductionRoute,$W64,),0)) | Y64: =IF(J64="","",$W64&"_"&MATCH(J64,INDEX(CONST_MATRIX_ProductionRoute,$W64,),0)) | Z64: =IF(K64="","",$W64&"_"&MATCH(K64,INDEX(CONST_MATRIX_ProductionRoute,$W64,),0)) | AA64: =IF(L64="","",$W64&"_"&MATCH(L64,INDEX(CONST_MATRIX_ProductionRoute,$W64,),0)) | AB64: =IF(M64="","",$W64&"_"&MATCH(M64,INDEX(CONST_MATRIX_ProductionRoute,$W64,),0)) | AC64: =IF(N64="","",$W64&"_"&MATCH(N64,INDEX(CONST_MATRIX_ProductionRoute,$W64,),0)) | AE64: =IF(E64="","",COUNTIF($E$83:$K$92,E64)=0) | AH64: =IF(E64="","",INDEX(Parameters_Constants!$BN$89:$BN$106,MATCH(E64,CONST_LIST_Goods,0))) | AI64: =OR(AND(CNTR_HasEntriesA,E64=""),AND(E64<>"",G64=CONST_AllProdRoutes))
D65: G4 | E65: Iron or steel products | G65: =IF(E65="","",IF(COUNTIF(INDEX(CONST_MATRIX_ProductionRoute,MATCH(E65,CONST_LIST_Goods,0),),CONST_NA)=9,CONST_AllProdRoutes,CONST_PleaseSelect)) | S65: =IF(E65="",CONST_NA,E65) | T65: =IF(E65="","",INDEX(CONST_LIST_GoodsProdRouteAdd,MATCH(E65,CONST_LIST_Goods,0))) | V65: =D65 | W65: =IF(E65="","",MATCH(E65,CONST_LIST_Goods,0)) | X65: =IF(I65="","",$W65&"_"&MATCH(I65,INDEX(CONST_MATRIX_ProductionRoute,$W65,),0)) | Y65: =IF(J65="","",$W65&"_"&MATCH(J65,INDEX(CONST_MATRIX_ProductionRoute,$W65,),0)) | Z65: =IF(K65="","",$W65&"_"&MATCH(K65,INDEX(CONST_MATRIX_ProductionRoute,$W65,),0)) | AA65: =IF(L65="","",$W65&"_"&MATCH(L65,INDEX(CONST_MATRIX_ProductionRoute,$W65,),0)) | AB65: =IF(M65="","",$W65&"_"&MATCH(M65,INDEX(CONST_MATRIX_ProductionRoute,$W65,),0)) | AC65: =IF(N65="","",$W65&"_"&MATCH(N65,INDEX(CONST_MATRIX_ProductionRoute,$W65,),0)) | AE65: =IF(E65="","",COUNTIF($E$83:$K$92,E65)=0) | AH65: =IF(E65="","",INDEX(Parameters_Constants!$BN$89:$BN$106,MATCH(E65,CONST_LIST_Goods,0))) | AI65: =OR(AND(CNTR_HasEntriesA,E65=""),AND(E65<>"",G65=CONST_AllProdRoutes))
D66: G5 | G66: =IF(E66="","",IF(COUNTIF(INDEX(CONST_MATRIX_ProductionRoute,MATCH(E66,CONST_LIST_Goods,0),),CONST_NA)=9,CONST_AllProdRoutes,CONST_PleaseSelect)) | S66: =IF(E66="",CONST_NA,E66) | T66: =IF(E66="","",INDEX(CONST_LIST_GoodsProdRouteAdd,MATCH(E66,CONST_LIST_Goods,0))) | V66: =D66 | W66: =IF(E66="","",MATCH(E66,CONST_LIST_Goods,0)) | X66: =IF(I66="","",$W66&"_"&MATCH(I66,INDEX(CONST_MATRIX_ProductionRoute,$W66,),0)) | Y66: =IF(J66="","",$W66&"_"&MATCH(J66,INDEX(CONST_MATRIX_ProductionRoute,$W66,),0)) | Z66: =IF(K66="","",$W66&"_"&MATCH(K66,INDEX(CONST_MATRIX_ProductionRoute,$W66,),0)) | AA66: =IF(L66="","",$W66&"_"&MATCH(L66,INDEX(CONST_MATRIX_ProductionRoute,$W66,),0)) | AB66: =IF(M66="","",$W66&"_"&MATCH(M66,INDEX(CONST_MATRIX_ProductionRoute,$W66,),0)) | AC66: =IF(N66="","",$W66&"_"&MATCH(N66,INDEX(CONST_MATRIX_ProductionRoute,$W66,),0)) | AE66: =IF(E66="","",COUNTIF($E$83:$K$92,E66)=0) | AH66: =IF(E66="","",INDEX(Parameters_Constants!$BN$89:$BN$106,MATCH(E66,CONST_LIST_Goods,0))) | AI66: =OR(AND(CNTR_HasEntriesA,E66=""),AND(E66<>"",G66=CONST_AllProdRoutes))
D67: G6 | G67: =IF(E67="","",IF(COUNTIF(INDEX(CONST_MATRIX_ProductionRoute,MATCH(E67,CONST_LIST_Goods,0),),CONST_NA)=9,CONST_AllProdRoutes,CONST_PleaseSelect)) | S67: =IF(E67="",CONST_NA,E67) | T67: =IF(E67="","",INDEX(CONST_LIST_GoodsProdRouteAdd,MATCH(E67,CONST_LIST_Goods,0))) | V67: =D67 | W67: =IF(E67="","",MATCH(E67,CONST_LIST_Goods,0)) | X67: =IF(I67="","",$W67&"_"&MATCH(I67,INDEX(CONST_MATRIX_ProductionRoute,$W67,),0)) | Y67: =IF(J67="","",$W67&"_"&MATCH(J67,INDEX(CONST_MATRIX_ProductionRoute,$W67,),0)) | Z67: =IF(K67="","",$W67&"_"&MATCH(K67,INDEX(CONST_MATRIX_ProductionRoute,$W67,),0)) | AA67: =IF(L67="","",$W67&"_"&MATCH(L67,INDEX(CONST_MATRIX_ProductionRoute,$W67,),0)) | AB67: =IF(M67="","",$W67&"_"&MATCH(M67,INDEX(CONST_MATRIX_ProductionRoute,$W67,),0)) | AC67: =IF(N67="","",$W67&"_"&MATCH(N67,INDEX(CONST_MATRIX_ProductionRoute,$W67,),0)) | AE67: =IF(E67="","",COUNTIF($E$83:$K$92,E67)=0) | AH67: =IF(E67="","",INDEX(Parameters_Constants!$BN$89:$BN$106,MATCH(E67,CONST_LIST_Goods,0))) | AI67: =OR(AND(CNTR_HasEntriesA,E67=""),AND(E67<>"",G67=CONST_AllProdRoutes))
D68: G7 | G68: =IF(E68="","",IF(COUNTIF(INDEX(CONST_MATRIX_ProductionRoute,MATCH(E68,CONST_LIST_Goods,0),),CONST_NA)=9,CONST_AllProdRoutes,CONST_PleaseSelect)) | S68: =IF(E68="",CONST_NA,E68) | T68: =IF(E68="","",INDEX(CONST_LIST_GoodsProdRouteAdd,MATCH(E68,CONST_LIST_Goods,0))) | V68: =D68 | W68: =IF(E68="","",MATCH(E68,CONST_LIST_Goods,0)) | X68: =IF(I68="","",$W68&"_"&MATCH(I68,INDEX(CONST_MATRIX_ProductionRoute,$W68,),0)) | Y68: =IF(J68="","",$W68&"_"&MATCH(J68,INDEX(CONST_MATRIX_ProductionRoute,$W68,),0)) | Z68: =IF(K68="","",$W68&"_"&MATCH(K68,INDEX(CONST_MATRIX_ProductionRoute,$W68,),0)) | AA68: =IF(L68="","",$W68&"_"&MATCH(L68,INDEX(CONST_MATRIX_ProductionRoute,$W68,),0)) | AB68: =IF(M68="","",$W68&"_"&MATCH(M68,INDEX(CONST_MATRIX_ProductionRoute,$W68,),0)) | AC68: =IF(N68="","",$W68&"_"&MATCH(N68,INDEX(CONST_MATRIX_ProductionRoute,$W68,),0)) | AE68: =IF(E68="","",COUNTIF($E$83:$K$92,E68)=0) | AH68: =IF(E68="","",INDEX(Parameters_Constants!$BN$89:$BN$106,MATCH(E68,CONST_LIST_Goods,0))) | AI68: =OR(AND(CNTR_HasEntriesA,E68=""),AND(E68<>"",G68=CONST_AllProdRoutes))
D69: G8 | G69: =IF(E69="","",IF(COUNTIF(INDEX(CONST_MATRIX_ProductionRoute,MATCH(E69,CONST_LIST_Goods,0),),CONST_NA)=9,CONST_AllProdRoutes,CONST_PleaseSelect)) | S69: =IF(E69="",CONST_NA,E69) | T69: =IF(E69="","",INDEX(CONST_LIST_GoodsProdRouteAdd,MATCH(E69,CONST_LIST_Goods,0))) | V69: =D69 | W69: =IF(E69="","",MATCH(E69,CONST_LIST_Goods,0)) | X69: =IF(I69="","",$W69&"_"&MATCH(I69,INDEX(CONST_MATRIX_ProductionRoute,$W69,),0)) | Y69: =IF(J69="","",$W69&"_"&MATCH(J69,INDEX(CONST_MATRIX_ProductionRoute,$W69,),0)) | Z69: =IF(K69="","",$W69&"_"&MATCH(K69,INDEX(CONST_MATRIX_ProductionRoute,$W69,),0)) | AA69: =IF(L69="","",$W69&"_"&MATCH(L69,INDEX(CONST_MATRIX_ProductionRoute,$W69,),0)) | AB69: =IF(M69="","",$W69&"_"&MATCH(M69,INDEX(CONST_MATRIX_ProductionRoute,$W69,),0)) | AC69: =IF(N69="","",$W69&"_"&MATCH(N69,INDEX(CONST_MATRIX_ProductionRoute,$W69,),0)) | AE69: =IF(E69="","",COUNTIF($E$83:$K$92,E69)=0) | AH69: =IF(E69="","",INDEX(Parameters_Constants!$BN$89:$BN$106,MATCH(E69,CONST_LIST_Goods,0))) | AI69: =OR(AND(CNTR_HasEntriesA,E69=""),AND(E69<>"",G69=CONST_AllProdRoutes))
D70: G9 | G70: =IF(E70="","",IF(COUNTIF(INDEX(CONST_MATRIX_ProductionRoute,MATCH(E70,CONST_LIST_Goods,0),),CONST_NA)=9,CONST_AllProdRoutes,CONST_PleaseSelect)) | S70: =IF(E70="",CONST_NA,E70) | T70: =IF(E70="","",INDEX(CONST_LIST_GoodsProdRouteAdd,MATCH(E70,CONST_LIST_Goods,0))) | V70: =D70 | W70: =IF(E70="","",MATCH(E70,CONST_LIST_Goods,0)) | X70: =IF(I70="","",$W70&"_"&MATCH(I70,INDEX(CONST_MATRIX_ProductionRoute,$W70,),0)) | Y70: =IF(J70="","",$W70&"_"&MATCH(J70,INDEX(CONST_MATRIX_ProductionRoute,$W70,),0)) | Z70: =IF(K70="","",$W70&"_"&MATCH(K70,INDEX(CONST_MATRIX_ProductionRoute,$W70,),0)) | AA70: =IF(L70="","",$W70&"_"&MATCH(L70,INDEX(CONST_MATRIX_ProductionRoute,$W70,),0)) | AB70: =IF(M70="","",$W70&"_"&MATCH(M70,INDEX(CONST_MATRIX_ProductionRoute,$W70,),0)) | AC70: =IF(N70="","",$W70&"_"&MATCH(N70,INDEX(CONST_MATRIX_ProductionRoute,$W70,),0)) | AE70: =IF(E70="","",COUNTIF($E$83:$K$92,E70)=0) | AH70: =IF(E70="","",INDEX(Parameters_Constants!$BN$89:$BN$106,MATCH(E70,CONST_LIST_Goods,0))) | AI70: =OR(AND(CNTR_HasEntriesA,E70=""),AND(E70<>"",G70=CONST_AllProdRoutes))
D71: G10 | G71: =IF(E71="","",IF(COUNTIF(INDEX(CONST_MATRIX_ProductionRoute,MATCH(E71,CONST_LIST_Goods,0),),CONST_NA)=9,CONST_AllProdRoutes,CONST_PleaseSelect)) | S71: =IF(E71="",CONST_NA,E71) | T71: =IF(E71="","",INDEX(CONST_LIST_GoodsProdRouteAdd,MATCH(E71,CONST_LIST_Goods,0))) | V71: =D71 | W71: =IF(E71="","",MATCH(E71,CONST_LIST_Goods,0)) | X71: =IF(I71="","",$W71&"_"&MATCH(I71,INDEX(CONST_MATRIX_ProductionRoute,$W71,),0)) | Y71: =IF(J71="","",$W71&"_"&MATCH(J71,INDEX(CONST_MATRIX_ProductionRoute,$W71,),0)) | Z71: =IF(K71="","",$W71&"_"&MATCH(K71,INDEX(CONST_MATRIX_ProductionRoute,$W71,),0)) | AA71: =IF(L71="","",$W71&"_"&MATCH(L71,INDEX(CONST_MATRIX_ProductionRoute,$W71,),0)) | AB71: =IF(M71="","",$W71&"_"&MATCH(M71,INDEX(CONST_MATRIX_ProductionRoute,$W71,),0)) | AC71: =IF(N71="","",$W71&"_"&MATCH(N71,INDEX(CONST_MATRIX_ProductionRoute,$W71,),0)) | AE71: =IF(E71="","",COUNTIF($E$83:$K$92,E71)=0) | AH71: =IF(E71="","",INDEX(Parameters_Constants!$BN$89:$BN$106,MATCH(E71,CONST_LIST_Goods,0))) | AI71: =OR(AND(CNTR_HasEntriesA,E71=""),AND(E71<>"",G71=CONST_AllProdRoutes))
E73: =Translations!$B$1953
E74: =Translations!$B$116 | G74: =IF(COUNTIF(CONST_CNTR_PrecNumbering,COLUMNS($G74:G74))=0,"",INDEX(CONST_LIST_Goods,MATCH(COLUMNS($G74:G74),CONST_CNTR_PrecNumbering,0))) | H74: =IF(COUNTIF(CONST_CNTR_PrecNumbering,COLUMNS($G74:H74))=0,"",INDEX(CONST_LIST_Goods,MATCH(COLUMNS($G74:H74),CONST_CNTR_PrecNumbering,0))) | I74: =IF(COUNTIF(CONST_CNTR_PrecNumbering,COLUMNS($G74:I74))=0,"",INDEX(CONST_LIST_Goods,MATCH(COLUMNS($G74:I74),CONST_CNTR_PrecNumbering,0))) | J74: =IF(COUNTIF(CONST_CNTR_PrecNumbering,COLUMNS($G74:J74))=0,"",INDEX(CONST_LIST_Goods,MATCH(COLUMNS($G74:J74),CONST_CNTR_PrecNumbering,0))) | K74: =IF(COUNTIF(CONST_CNTR_PrecNumbering,COLUMNS($G74:K74))=0,"",INDEX(CONST_LIST_Goods,MATCH(COLUMNS($G74:K74),CONST_CNTR_PrecNumbering,0))) | L74: =IF(COUNTIF(CONST_CNTR_PrecNumbering,COLUMNS($G74:L74))=0,"",INDEX(CONST_LIST_Goods,MATCH(COLUMNS($G74:L74),CONST_CNTR_PrecNumbering,0))) | M74: =IF(COUNTIF(CONST_CNTR_PrecNumbering,COLUMNS($G74:M74))=0,"",INDEX(CONST_LIST_Goods,MATCH(COLUMNS($G74:M74),CONST_CNTR_PrecNumbering,0))) | N74: =IF(COUNTIF(CONST_CNTR_PrecNumbering,COLUMNS($G74:N74))=0,"",INDEX(CONST_LIST_Goods,MATCH(COLUMNS($G74:N74),CONST_CNTR_PrecNumbering,0)))
G75: =IF(COUNTIF(CONST_CNTR_PrecNumbering,COLUMNS($G75:G75)+8)=0,"",INDEX(CONST_LIST_Goods,MATCH(COLUMNS($G75:G75)+8,CONST_CNTR_PrecNumbering,0))) | H75: =IF(COUNTIF(CONST_CNTR_PrecNumbering,COLUMNS($G75:H75)+8)=0,"",INDEX(CONST_LIST_Goods,MATCH(COLUMNS($G75:H75)+8,CONST_CNTR_PrecNumbering,0))) | I75: =IF(COUNTIF(CONST_CNTR_PrecNumbering,COLUMNS($G75:I75)+8)=0,"",INDEX(CONST_LIST_Goods,MATCH(COLUMNS($G75:I75)+8,CONST_CNTR_PrecNumbering,0))) | J75: =IF(COUNTIF(CONST_CNTR_PrecNumbering,COLUMNS($G75:J75)+8)=0,"",INDEX(CONST_LIST_Goods,MATCH(COLUMNS($G75:J75)+8,CONST_CNTR_PrecNumbering,0))) | K75: =IF(COUNTIF(CONST_CNTR_PrecNumbering,COLUMNS($G75:K75)+8)=0,"",INDEX(CONST_LIST_Goods,MATCH(COLUMNS($G75:K75)+8,CONST_CNTR_PrecNumbering,0))) | L75: =IF(COUNTIF(CONST_CNTR_PrecNumbering,COLUMNS($G75:L75)+8)=0,"",INDEX(CONST_LIST_Goods,MATCH(COLUMNS($G75:L75)+8,CONST_CNTR_PrecNumbering,0))) | M75: =IF(COUNTIF(CONST_CNTR_PrecNumbering,COLUMNS($G75:M75)+8)=0,"",INDEX(CONST_LIST_Goods,MATCH(COLUMNS($G75:M75)+8,CONST_CNTR_PrecNumbering,0))) | N75: =IF(COUNTIF(CONST_CNTR_PrecNumbering,COLUMNS($G75:N75)+8)=0,"",INDEX(CONST_LIST_Goods,MATCH(COLUMNS($G75:N75)+8,CONST_CNTR_PrecNumbering,0)))
D77: (b) | E77: =Translations!$B$117
E78: =Translations!$B$1954
E79: =Translations!$B$1955
D81: ID | E81: =Translations!$B$107 | F81: =Translations!$B$121 | L81: =Translations!$B$122 | N81: =Translations!$B$123
F82: 1 | G82: 2 | H82: 3 | I82: 4 | J82: 5 | K82: 6 | S82: CNTR_List_ExistProdProc | T82: CNTR_List_ExistProdProcNames | W82: GoodID | X82: PrecID 1 | Y82: PrecID 2 | Z82: PrecID 3 | AA82: PrecID 4 | AB82: PrecID 5 | AC82: PrecID 6 | AD82: ProdRoute
D83: P1 | E83: Iron or steel products | F83: Sintered Ore | L83: Bubble approach | N83: =IF(E83="","",IF(OR(L83="",AND(AF83=FALSE(),COUNTA(F83:K83)=0)),CONST_ERR_Incomplete,IF(COUNTIF(L$83:M83,L83)>1,CONST_ERR_Duplicate,IF(COUNTIF(X83:AC83,NA())>0,CONST_ERR_Inconsistent,"")))) | S83: =IF(E83="",CONST_NA,E83) | T83: =IF(E83="",CONST_NA,IF(L83="",D83 & " - " & E83,L83)) | V83: =D83 | W83: =IF(E83="","",MATCH(E83,CONST_LIST_Goods,0)) | X83: =IF(F83="","",$W83&"_"&IF(F83=$S$61,0,MATCH(F83,INDEX(Parameters_Constants!$AC$89:$AM$106,$W83,),0))) | Y83: =IF(G83="","",$W83&"_"&IF(G83=$S$61,0,MATCH(G83,INDEX(Parameters_Constants!$AC$89:$AM$106,$W83,),0))) | Z83: =IF(H83="","",$W83&"_"&IF(H83=$S$61,0,MATCH(H83,INDEX(Parameters_Constants!$AC$89:$AM$106,$W83,),0))) | AA83: =IF(I83="","",$W83&"_"&IF(I83=$S$61,0,MATCH(I83,INDEX(Parameters_Constants!$AC$89:$AM$106,$W83,),0))) | AB83: =IF(J83="","",$W83&"_"&IF(J83=$S$61,0,MATCH(J83,INDEX(Parameters_Constants!$AC$89:$AM$106,$W83,),0))) | AC83: =IF(K83="","",$W83&"_"&IF(K83=$S$61,0,MATCH(K83,INDEX(Parameters_Constants!$AC$89:$AM$106,$W83,),0))) | AD83: =IF(E83="","",IF(COUNTIF(INDEX(CONST_MATRIX_ProductionRoute,MATCH(E83,CONST_LIST_Goods,0),),CONST_NA)=9,CONST_AllProdRoutes,CONST_NA)) | AG83: =IF(AND(CNTR_HasEntriesA,N83<>""),CONST_ErrorOrMissing&$A$55,CONST_NA) | AI83: =AND(CNTR_HasEntriesA,E83="")
D84: P2 | E84: Pig iron | F84: Sintered Ore | L84: Other process | N84: =IF(E84="","",IF(OR(L84="",AND(AF84=FALSE(),COUNTA(F84:K84)=0)),CONST_ERR_Incomplete,IF(COUNTIF(L$83:M84,L84)>1,CONST_ERR_Duplicate,IF(COUNTIF(X84:AC84,NA())>0,CONST_ERR_Inconsistent,"")))) | S84: =IF(E84="",CONST_NA,E84) | T84: =IF(E84="",CONST_NA,IF(L84="",D84 & " - " & E84,L84)) | V84: =D84 | W84: =IF(E84="","",MATCH(E84,CONST_LIST_Goods,0)) | X84: =IF(F84="","",$W84&"_"&IF(F84=$S$61,0,MATCH(F84,INDEX(Parameters_Constants!$AC$89:$AM$106,$W84,),0))) | Y84: =IF(G84="","",$W84&"_"&IF(G84=$S$61,0,MATCH(G84,INDEX(Parameters_Constants!$AC$89:$AM$106,$W84,),0))) | Z84: =IF(H84="","",$W84&"_"&IF(H84=$S$61,0,MATCH(H84,INDEX(Parameters_Constants!$AC$89:$AM$106,$W84,),0))) | AA84: =IF(I84="","",$W84&"_"&IF(I84=$S$61,0,MATCH(I84,INDEX(Parameters_Constants!$AC$89:$AM$106,$W84,),0))) | AB84: =IF(J84="","",$W84&"_"&IF(J84=$S$61,0,MATCH(J84,INDEX(Parameters_Constants!$AC$89:$AM$106,$W84,),0))) | AC84: =IF(K84="","",$W84&"_"&IF(K84=$S$61,0,MATCH(K84,INDEX(Parameters_Constants!$AC$89:$AM$106,$W84,),0))) | AD84: =IF(E84="","",IF(COUNTIF(INDEX(CONST_MATRIX_ProductionRoute,MATCH(E84,CONST_LIST_Goods,0),),CONST_NA)=9,CONST_AllProdRoutes,CONST_NA)) | AG84: =IF(AND(CNTR_HasEntriesA,N84<>""),CONST_ErrorOrMissing&$A$55,CONST_NA) | AI84: =AND(CNTR_HasEntriesA,E84="")
D85: P3 | N85: =IF(E85="","",IF(OR(L85="",AND(AF85=FALSE(),COUNTA(F85:K85)=0)),CONST_ERR_Incomplete,IF(COUNTIF(L$83:M85,L85)>1,CONST_ERR_Duplicate,IF(COUNTIF(X85:AC85,NA())>0,CONST_ERR_Inconsistent,"")))) | S85: =IF(E85="",CONST_NA,E85) | T85: =IF(E85="",CONST_NA,IF(L85="",D85 & " - " & E85,L85)) | V85: =D85 | W85: =IF(E85="","",MATCH(E85,CONST_LIST_Goods,0)) | X85: =IF(F85="","",$W85&"_"&IF(F85=$S$61,0,MATCH(F85,INDEX(Parameters_Constants!$AC$89:$AM$106,$W85,),0))) | Y85: =IF(G85="","",$W85&"_"&IF(G85=$S$61,0,MATCH(G85,INDEX(Parameters_Constants!$AC$89:$AM$106,$W85,),0))) | Z85: =IF(H85="","",$W85&"_"&IF(H85=$S$61,0,MATCH(H85,INDEX(Parameters_Constants!$AC$89:$AM$106,$W85,),0))) | AA85: =IF(I85="","",$W85&"_"&IF(I85=$S$61,0,MATCH(I85,INDEX(Parameters_Constants!$AC$89:$AM$106,$W85,),0))) | AB85: =IF(J85="","",$W85&"_"&IF(J85=$S$61,0,MATCH(J85,INDEX(Parameters_Constants!$AC$89:$AM$106,$W85,),0))) | AC85: =IF(K85="","",$W85&"_"&IF(K85=$S$61,0,MATCH(K85,INDEX(Parameters_Constants!$AC$89:$AM$106,$W85,),0))) | AD85: =IF(E85="","",IF(COUNTIF(INDEX(CONST_MATRIX_ProductionRoute,MATCH(E85,CONST_LIST_Goods,0),),CONST_NA)=9,CONST_AllProdRoutes,CONST_NA)) | AG85: =IF(AND(CNTR_HasEntriesA,N85<>""),CONST_ErrorOrMissing&$A$55,CONST_NA) | AI85: =AND(CNTR_HasEntriesA,E85="")
D86: P4 | N86: =IF(E86="","",IF(OR(L86="",AND(AF86=FALSE(),COUNTA(F86:K86)=0)),CONST_ERR_Incomplete,IF(COUNTIF(L$83:M86,L86)>1,CONST_ERR_Duplicate,IF(COUNTIF(X86:AC86,NA())>0,CONST_ERR_Inconsistent,"")))) | S86: =IF(E86="",CONST_NA,E86) | T86: =IF(E86="",CONST_NA,IF(L86="",D86 & " - " & E86,L86)) | V86: =D86 | W86: =IF(E86="","",MATCH(E86,CONST_LIST_Goods,0)) | X86: =IF(F86="","",$W86&"_"&IF(F86=$S$61,0,MATCH(F86,INDEX(Parameters_Constants!$AC$89:$AM$106,$W86,),0))) | Y86: =IF(G86="","",$W86&"_"&IF(G86=$S$61,0,MATCH(G86,INDEX(Parameters_Constants!$AC$89:$AM$106,$W86,),0))) | Z86: =IF(H86="","",$W86&"_"&IF(H86=$S$61,0,MATCH(H86,INDEX(Parameters_Constants!$AC$89:$AM$106,$W86,),0))) | AA86: =IF(I86="","",$W86&"_"&IF(I86=$S$61,0,MATCH(I86,INDEX(Parameters_Constants!$AC$89:$AM$106,$W86,),0))) | AB86: =IF(J86="","",$W86&"_"&IF(J86=$S$61,0,MATCH(J86,INDEX(Parameters_Constants!$AC$89:$AM$106,$W86,),0))) | AC86: =IF(K86="","",$W86&"_"&IF(K86=$S$61,0,MATCH(K86,INDEX(Parameters_Constants!$AC$89:$AM$106,$W86,),0))) | AD86: =IF(E86="","",IF(COUNTIF(INDEX(CONST_MATRIX_ProductionRoute,MATCH(E86,CONST_LIST_Goods,0),),CONST_NA)=9,CONST_AllProdRoutes,CONST_NA)) | AG86: =IF(AND(CNTR_HasEntriesA,N86<>""),CONST_ErrorOrMissing&$A$55,CONST_NA) | AI86: =AND(CNTR_HasEntriesA,E86="")
D87: P5 | N87: =IF(E87="","",IF(OR(L87="",AND(AF87=FALSE(),COUNTA(F87:K87)=0)),CONST_ERR_Incomplete,IF(COUNTIF(L$83:M87,L87)>1,CONST_ERR_Duplicate,IF(COUNTIF(X87:AC87,NA())>0,CONST_ERR_Inconsistent,"")))) | S87: =IF(E87="",CONST_NA,E87) | T87: =IF(E87="",CONST_NA,IF(L87="",D87 & " - " & E87,L87)) | V87: =D87 | W87: =IF(E87="","",MATCH(E87,CONST_LIST_Goods,0)) | X87: =IF(F87="","",$W87&"_"&IF(F87=$S$61,0,MATCH(F87,INDEX(Parameters_Constants!$AC$89:$AM$106,$W87,),0))) | Y87: =IF(G87="","",$W87&"_"&IF(G87=$S$61,0,MATCH(G87,INDEX(Parameters_Constants!$AC$89:$AM$106,$W87,),0))) | Z87: =IF(H87="","",$W87&"_"&IF(H87=$S$61,0,MATCH(H87,INDEX(Parameters_Constants!$AC$89:$AM$106,$W87,),0))) | AA87: =IF(I87="","",$W87&"_"&IF(I87=$S$61,0,MATCH(I87,INDEX(Parameters_Constants!$AC$89:$AM$106,$W87,),0))) | AB87: =IF(J87="","",$W87&"_"&IF(J87=$S$61,0,MATCH(J87,INDEX(Parameters_Constants!$AC$89:$AM$106,$W87,),0))) | AC87: =IF(K87="","",$W87&"_"&IF(K87=$S$61,0,MATCH(K87,INDEX(Parameters_Constants!$AC$89:$AM$106,$W87,),0))) | AD87: =IF(E87="","",IF(COUNTIF(INDEX(CONST_MATRIX_ProductionRoute,MATCH(E87,CONST_LIST_Goods,0),),CONST_NA)=9,CONST_AllProdRoutes,CONST_NA)) | AG87: =IF(AND(CNTR_HasEntriesA,N87<>""),CONST_ErrorOrMissing&$A$55,CONST_NA) | AI87: =AND(CNTR_HasEntriesA,E87="")
D88: P6 | N88: =IF(E88="","",IF(OR(L88="",AND(AF88=FALSE(),COUNTA(F88:K88)=0)),CONST_ERR_Incomplete,IF(COUNTIF(L$83:M88,L88)>1,CONST_ERR_Duplicate,IF(COUNTIF(X88:AC88,NA())>0,CONST_ERR_Inconsistent,"")))) | S88: =IF(E88="",CONST_NA,E88) | T88: =IF(E88="",CONST_NA,IF(L88="",D88 & " - " & E88,L88)) | V88: =D88 | W88: =IF(E88="","",MATCH(E88,CONST_LIST_Goods,0)) | X88: =IF(F88="","",$W88&"_"&IF(F88=$S$61,0,MATCH(F88,INDEX(Parameters_Constants!$AC$89:$AM$106,$W88,),0))) | Y88: =IF(G88="","",$W88&"_"&IF(G88=$S$61,0,MATCH(G88,INDEX(Parameters_Constants!$AC$89:$AM$106,$W88,),0))) | Z88: =IF(H88="","",$W88&"_"&IF(H88=$S$61,0,MATCH(H88,INDEX(Parameters_Constants!$AC$89:$AM$106,$W88,),0))) | AA88: =IF(I88="","",$W88&"_"&IF(I88=$S$61,0,MATCH(I88,INDEX(Parameters_Constants!$AC$89:$AM$106,$W88,),0))) | AB88: =IF(J88="","",$W88&"_"&IF(J88=$S$61,0,MATCH(J88,INDEX(Parameters_Constants!$AC$89:$AM$106,$W88,),0))) | AC88: =IF(K88="","",$W88&"_"&IF(K88=$S$61,0,MATCH(K88,INDEX(Parameters_Constants!$AC$89:$AM$106,$W88,),0))) | AD88: =IF(E88="","",IF(COUNTIF(INDEX(CONST_MATRIX_ProductionRoute,MATCH(E88,CONST_LIST_Goods,0),),CONST_NA)=9,CONST_AllProdRoutes,CONST_NA)) | AG88: =IF(AND(CNTR_HasEntriesA,N88<>""),CONST_ErrorOrMissing&$A$55,CONST_NA) | AI88: =AND(CNTR_HasEntriesA,E88="")
D89: P7 | N89: =IF(E89="","",IF(OR(L89="",AND(AF89=FALSE(),COUNTA(F89:K89)=0)),CONST_ERR_Incomplete,IF(COUNTIF(L$83:M89,L89)>1,CONST_ERR_Duplicate,IF(COUNTIF(X89:AC89,NA())>0,CONST_ERR_Inconsistent,"")))) | S89: =IF(E89="",CONST_NA,E89) | T89: =IF(E89="",CONST_NA,IF(L89="",D89 & " - " & E89,L89)) | V89: =D89 | W89: =IF(E89="","",MATCH(E89,CONST_LIST_Goods,0)) | X89: =IF(F89="","",$W89&"_"&IF(F89=$S$61,0,MATCH(F89,INDEX(Parameters_Constants!$AC$89:$AM$106,$W89,),0))) | Y89: =IF(G89="","",$W89&"_"&IF(G89=$S$61,0,MATCH(G89,INDEX(Parameters_Constants!$AC$89:$AM$106,$W89,),0))) | Z89: =IF(H89="","",$W89&"_"&IF(H89=$S$61,0,MATCH(H89,INDEX(Parameters_Constants!$AC$89:$AM$106,$W89,),0))) | AA89: =IF(I89="","",$W89&"_"&IF(I89=$S$61,0,MATCH(I89,INDEX(Parameters_Constants!$AC$89:$AM$106,$W89,),0))) | AB89: =IF(J89="","",$W89&"_"&IF(J89=$S$61,0,MATCH(J89,INDEX(Parameters_Constants!$AC$89:$AM$106,$W89,),0))) | AC89: =IF(K89="","",$W89&"_"&IF(K89=$S$61,0,MATCH(K89,INDEX(Parameters_Constants!$AC$89:$AM$106,$W89,),0))) | AD89: =IF(E89="","",IF(COUNTIF(INDEX(CONST_MATRIX_ProductionRoute,MATCH(E89,CONST_LIST_Goods,0),),CONST_NA)=9,CONST_AllProdRoutes,CONST_NA)) | AG89: =IF(AND(CNTR_HasEntriesA,N89<>""),CONST_ErrorOrMissing&$A$55,CONST_NA) | AI89: =AND(CNTR_HasEntriesA,E89="")
D90: P8 | N90: =IF(E90="","",IF(OR(L90="",AND(AF90=FALSE(),COUNTA(F90:K90)=0)),CONST_ERR_Incomplete,IF(COUNTIF(L$83:M90,L90)>1,CONST_ERR_Duplicate,IF(COUNTIF(X90:AC90,NA())>0,CONST_ERR_Inconsistent,"")))) | S90: =IF(E90="",CONST_NA,E90) | T90: =IF(E90="",CONST_NA,IF(L90="",D90 & " - " & E90,L90)) | V90: =D90 | W90: =IF(E90="","",MATCH(E90,CONST_LIST_Goods,0)) | X90: =IF(F90="","",$W90&"_"&IF(F90=$S$61,0,MATCH(F90,INDEX(Parameters_Constants!$AC$89:$AM$106,$W90,),0))) | Y90: =IF(G90="","",$W90&"_"&IF(G90=$S$61,0,MATCH(G90,INDEX(Parameters_Constants!$AC$89:$AM$106,$W90,),0))) | Z90: =IF(H90="","",$W90&"_"&IF(H90=$S$61,0,MATCH(H90,INDEX(Parameters_Constants!$AC$89:$AM$106,$W90,),0))) | AA90: =IF(I90="","",$W90&"_"&IF(I90=$S$61,0,MATCH(I90,INDEX(Parameters_Constants!$AC$89:$AM$106,$W90,),0))) | AB90: =IF(J90="","",$W90&"_"&IF(J90=$S$61,0,MATCH(J90,INDEX(Parameters_Constants!$AC$89:$AM$106,$W90,),0))) | AC90: =IF(K90="","",$W90&"_"&IF(K90=$S$61,0,MATCH(K90,INDEX(Parameters_Constants!$AC$89:$AM$106,$W90,),0))) | AD90: =IF(E90="","",IF(COUNTIF(INDEX(CONST_MATRIX_ProductionRoute,MATCH(E90,CONST_LIST_Goods,0),),CONST_NA)=9,CONST_AllProdRoutes,CONST_NA)) | AG90: =IF(AND(CNTR_HasEntriesA,N90<>""),CONST_ErrorOrMissing&$A$55,CONST_NA) | AI90: =AND(CNTR_HasEntriesA,E90="")
D91: P9 | N91: =IF(E91="","",IF(OR(L91="",AND(AF91=FALSE(),COUNTA(F91:K91)=0)),CONST_ERR_Incomplete,IF(COUNTIF(L$83:M91,L91)>1,CONST_ERR_Duplicate,IF(COUNTIF(X91:AC91,NA())>0,CONST_ERR_Inconsistent,"")))) | S91: =IF(E91="",CONST_NA,E91) | T91: =IF(E91="",CONST_NA,IF(L91="",D91 & " - " & E91,L91)) | V91: =D91 | W91: =IF(E91="","",MATCH(E91,CONST_LIST_Goods,0)) | X91: =IF(F91="","",$W91&"_"&IF(F91=$S$61,0,MATCH(F91,INDEX(Parameters_Constants!$AC$89:$AM$106,$W91,),0))) | Y91: =IF(G91="","",$W91&"_"&IF(G91=$S$61,0,MATCH(G91,INDEX(Parameters_Constants!$AC$89:$AM$106,$W91,),0))) | Z91: =IF(H91="","",$W91&"_"&IF(H91=$S$61,0,MATCH(H91,INDEX(Parameters_Constants!$AC$89:$AM$106,$W91,),0))) | AA91: =IF(I91="","",$W91&"_"&IF(I91=$S$61,0,MATCH(I91,INDEX(Parameters_Constants!$AC$89:$AM$106,$W91,),0))) | AB91: =IF(J91="","",$W91&"_"&IF(J91=$S$61,0,MATCH(J91,INDEX(Parameters_Constants!$AC$89:$AM$106,$W91,),0))) | AC91: =IF(K91="","",$W91&"_"&IF(K91=$S$61,0,MATCH(K91,INDEX(Parameters_Constants!$AC$89:$AM$106,$W91,),0))) | AD91: =IF(E91="","",IF(COUNTIF(INDEX(CONST_MATRIX_ProductionRoute,MATCH(E91,CONST_LIST_Goods,0),),CONST_NA)=9,CONST_AllProdRoutes,CONST_NA)) | AG91: =IF(AND(CNTR_HasEntriesA,N91<>""),CONST_ErrorOrMissing&$A$55,CONST_NA) | AI91: =AND(CNTR_HasEntriesA,E91="")
D92: P10 | N92: =IF(E92="","",IF(OR(L92="",AND(AF92=FALSE(),COUNTA(F92:K92)=0)),CONST_ERR_Incomplete,IF(COUNTIF(L$83:M92,L92)>1,CONST_ERR_Duplicate,IF(COUNTIF(X92:AC92,NA())>0,CONST_ERR_Inconsistent,"")))) | S92: =IF(E92="",CONST_NA,E92) | T92: =IF(E92="",CONST_NA,IF(L92="",D92 & " - " & E92,L92)) | V92: =D92 | W92: =IF(E92="","",MATCH(E92,CONST_LIST_Goods,0)) | X92: =IF(F92="","",$W92&"_"&IF(F92=$S$61,0,MATCH(F92,INDEX(Parameters_Constants!$AC$89:$AM$106,$W92,),0))) | Y92: =IF(G92="","",$W92&"_"&IF(G92=$S$61,0,MATCH(G92,INDEX(Parameters_Constants!$AC$89:$AM$106,$W92,),0))) | Z92: =IF(H92="","",$W92&"_"&IF(H92=$S$61,0,MATCH(H92,INDEX(Parameters_Constants!$AC$89:$AM$106,$W92,),0))) | AA92: =IF(I92="","",$W92&"_"&IF(I92=$S$61,0,MATCH(I92,INDEX(Parameters_Constants!$AC$89:$AM$106,$W92,),0))) | AB92: =IF(J92="","",$W92&"_"&IF(J92=$S$61,0,MATCH(J92,INDEX(Parameters_Constants!$AC$89:$AM$106,$W92,),0))) | AC92: =IF(K92="","",$W92&"_"&IF(K92=$S$61,0,MATCH(K92,INDEX(Parameters_Constants!$AC$89:$AM$106,$W92,),0))) | AD92: =IF(E92="","",IF(COUNTIF(INDEX(CONST_MATRIX_ProductionRoute,MATCH(E92,CONST_LIST_Goods,0),),CONST_NA)=9,CONST_AllProdRoutes,CONST_NA)) | AG92: =IF(AND(CNTR_HasEntriesA,N92<>""),CONST_ErrorOrMissing&$A$55,CONST_NA) | AI92: =AND(CNTR_HasEntriesA,E92="")
G94: =Translations!$B$1956 | H94: =IF(COUNTIF(AE62:AE71,TRUE())>0,CONST_MsgMissingProdProc,"") | AG94: =IF(AND(CNTR_HasEntriesA,H94<>""),CONST_ErrorOrMissing&A55,CONST_NA)
A96: =C96 | C96: 5 | D96: =Translations!$B$124 | R96: =D96
E98: =Translations!$B$125
E99: =Translations!$B$126 | U99: For drop-Down | X99: CNTR_MatrixPurchPrecRoutes
D101: ID | E101: =Translations!$B$120 | F101: =Translations!$B$1957 | G101: =Translations!$B$109 | H101: =Translations!$B$110 | I101: =Translations!$B$111 | J101: =Translations!$B$112 | K101: =Translations!$B$113 | L101: =Translations!$B$122 | N101: =Translations!$B$123 | S101: CNTR_List_ExistPurchPrec | T101: CNTR_List_ExistPurchPrecNames | W101: GoodID | X101: RouteID 1 | Y101: RouteID 2 | Z101: RouteID 3 | AA101: RouteID 4 | AB101: RouteID 5 | AH101: ProdRoute All?
D102: PP1 | N102: =IF(E102="","",IF(COUNTIF(X102:AB102,NA())>0,CONST_ERR_Inconsistent,IF(OR(F102="",L102="",AND(AH102=FALSE(),COUNTA(G102:K102)=0)),CONST_ERR_Incomplete,""))) | S102: =IF(E102="",CONST_NA,E102) | T102: =IF(E102="",CONST_NA,IF(L102="",D102 & " - " & E102,L102)) | U102: =IF(E102="","",INDEX(CONST_LIST_GoodsProdRouteAdd,MATCH(E102,CONST_LIST_Goods,0))) | V102: =D102 | W102: =IF(E102="","",MATCH(E102,CONST_LIST_Goods,0)) | X102: =IF(G102="","",MATCH(G102,INDEX(CONST_MATRIX_ProductionRoute,$W102,),0)) | Y102: =IF(H102="","",MATCH(H102,INDEX(CONST_MATRIX_ProductionRoute,$W102,),0)) | Z102: =IF(I102="","",MATCH(I102,INDEX(CONST_MATRIX_ProductionRoute,$W102,),0)) | AA102: =IF(J102="","",MATCH(J102,INDEX(CONST_MATRIX_ProductionRoute,$W102,),0)) | AB102: =IF(K102="","",MATCH(K102,INDEX(CONST_MATRIX_ProductionRoute,$W102,),0)) | AG102: =IF(AND(CNTR_HasEntriesA,N102<>""),CONST_ErrorOrMissing&$A$96,CONST_NA) | AH102: =IF(OR(CNTR_HasEntriesA=FALSE(),E102=""),"",COUNTIF(INDEX(CONST_MATRIX_ProductionRoute,MATCH(E102,CONST_LIST_Goods,0),),CONST_NA)=9) | AI102: =AND(CNTR_HasEntriesA,E102="")
D103: PP2 | N103: =IF(E103="","",IF(COUNTIF(X103:AB103,NA())>0,CONST_ERR_Inconsistent,IF(OR(F103="",L103="",AND(AH103=FALSE(),COUNTA(G103:K103)=0)),CONST_ERR_Incomplete,""))) | S103: =IF(E103="",CONST_NA,E103) | T103: =IF(E103="",CONST_NA,IF(L103="",D103 & " - " & E103,L103)) | U103: =IF(E103="","",INDEX(CONST_LIST_GoodsProdRouteAdd,MATCH(E103,CONST_LIST_Goods,0))) | V103: =D103 | W103: =IF(E103="","",MATCH(E103,CONST_LIST_Goods,0)) | X103: =IF(G103="","",MATCH(G103,INDEX(CONST_MATRIX_ProductionRoute,$W103,),0)) | Y103: =IF(H103="","",MATCH(H103,INDEX(CONST_MATRIX_ProductionRoute,$W103,),0)) | Z103: =IF(I103="","",MATCH(I103,INDEX(CONST_MATRIX_ProductionRoute,$W103,),0)) | AA103: =IF(J103="","",MATCH(J103,INDEX(CONST_MATRIX_ProductionRoute,$W103,),0)) | AB103: =IF(K103="","",MATCH(K103,INDEX(CONST_MATRIX_ProductionRoute,$W103,),0)) | AG103: =IF(AND(CNTR_HasEntriesA,N103<>""),CONST_ErrorOrMissing&$A$96,CONST_NA) | AH103: =IF(OR(CNTR_HasEntriesA=FALSE(),E103=""),"",COUNTIF(INDEX(CONST_MATRIX_ProductionRoute,MATCH(E103,CONST_LIST_Goods,0),),CONST_NA)=9) | AI103: =AND(CNTR_HasEntriesA,E103="")
D104: PP3 | N104: =IF(E104="","",IF(COUNTIF(X104:AB104,NA())>0,CONST_ERR_Inconsistent,IF(OR(F104="",L104="",AND(AH104=FALSE(),COUNTA(G104:K104)=0)),CONST_ERR_Incomplete,""))) | S104: =IF(E104="",CONST_NA,E104) | T104: =IF(E104="",CONST_NA,IF(L104="",D104 & " - " & E104,L104)) | U104: =IF(E104="","",INDEX(CONST_LIST_GoodsProdRouteAdd,MATCH(E104,CONST_LIST_Goods,0))) | V104: =D104 | W104: =IF(E104="","",MATCH(E104,CONST_LIST_Goods,0)) | X104: =IF(G104="","",MATCH(G104,INDEX(CONST_MATRIX_ProductionRoute,$W104,),0)) | Y104: =IF(H104="","",MATCH(H104,INDEX(CONST_MATRIX_ProductionRoute,$W104,),0)) | Z104: =IF(I104="","",MATCH(I104,INDEX(CONST_MATRIX_ProductionRoute,$W104,),0)) | AA104: =IF(J104="","",MATCH(J104,INDEX(CONST_MATRIX_ProductionRoute,$W104,),0)) | AB104: =IF(K104="","",MATCH(K104,INDEX(CONST_MATRIX_ProductionRoute,$W104,),0)) | AG104: =IF(AND(CNTR_HasEntriesA,N104<>""),CONST_ErrorOrMissing&$A$96,CONST_NA) | AH104: =IF(OR(CNTR_HasEntriesA=FALSE(),E104=""),"",COUNTIF(INDEX(CONST_MATRIX_ProductionRoute,MATCH(E104,CONST_LIST_Goods,0),),CONST_NA)=9) | AI104: =AND(CNTR_HasEntriesA,E104="")
D105: PP4 | N105: =IF(E105="","",IF(COUNTIF(X105:AB105,NA())>0,CONST_ERR_Inconsistent,IF(OR(F105="",L105="",AND(AH105=FALSE(),COUNTA(G105:K105)=0)),CONST_ERR_Incomplete,""))) | S105: =IF(E105="",CONST_NA,E105) | T105: =IF(E105="",CONST_NA,IF(L105="",D105 & " - " & E105,L105)) | U105: =IF(E105="","",INDEX(CONST_LIST_GoodsProdRouteAdd,MATCH(E105,CONST_LIST_Goods,0))) | V105: =D105 | W105: =IF(E105="","",MATCH(E105,CONST_LIST_Goods,0)) | X105: =IF(G105="","",MATCH(G105,INDEX(CONST_MATRIX_ProductionRoute,$W105,),0)) | Y105: =IF(H105="","",MATCH(H105,INDEX(CONST_MATRIX_ProductionRoute,$W105,),0)) | Z105: =IF(I105="","",MATCH(I105,INDEX(CONST_MATRIX_ProductionRoute,$W105,),0)) | AA105: =IF(J105="","",MATCH(J105,INDEX(CONST_MATRIX_ProductionRoute,$W105,),0)) | AB105: =IF(K105="","",MATCH(K105,INDEX(CONST_MATRIX_ProductionRoute,$W105,),0)) | AG105: =IF(AND(CNTR_HasEntriesA,N105<>""),CONST_ErrorOrMissing&$A$96,CONST_NA) | AH105: =IF(OR(CNTR_HasEntriesA=FALSE(),E105=""),"",COUNTIF(INDEX(CONST_MATRIX_ProductionRoute,MATCH(E105,CONST_LIST_Goods,0),),CONST_NA)=9) | AI105: =AND(CNTR_HasEntriesA,E105="")
D106: PP5 | N106: =IF(E106="","",IF(COUNTIF(X106:AB106,NA())>0,CONST_ERR_Inconsistent,IF(OR(F106="",L106="",AND(AH106=FALSE(),COUNTA(G106:K106)=0)),CONST_ERR_Incomplete,""))) | S106: =IF(E106="",CONST_NA,E106) | T106: =IF(E106="",CONST_NA,IF(L106="",D106 & " - " & E106,L106)) | U106: =IF(E106="","",INDEX(CONST_LIST_GoodsProdRouteAdd,MATCH(E106,CONST_LIST_Goods,0))) | V106: =D106 | W106: =IF(E106="","",MATCH(E106,CONST_LIST_Goods,0)) | X106: =IF(G106="","",MATCH(G106,INDEX(CONST_MATRIX_ProductionRoute,$W106,),0)) | Y106: =IF(H106="","",MATCH(H106,INDEX(CONST_MATRIX_ProductionRoute,$W106,),0)) | Z106: =IF(I106="","",MATCH(I106,INDEX(CONST_MATRIX_ProductionRoute,$W106,),0)) | AA106: =IF(J106="","",MATCH(J106,INDEX(CONST_MATRIX_ProductionRoute,$W106,),0)) | AB106: =IF(K106="","",MATCH(K106,INDEX(CONST_MATRIX_ProductionRoute,$W106,),0)) | AG106: =IF(AND(CNTR_HasEntriesA,N106<>""),CONST_ErrorOrMissing&$A$96,CONST_NA) | AH106: =IF(OR(CNTR_HasEntriesA=FALSE(),E106=""),"",COUNTIF(INDEX(CONST_MATRIX_ProductionRoute,MATCH(E106,CONST_LIST_Goods,0),),CONST_NA)=9) | AI106: =AND(CNTR_HasEntriesA,E106="")
D107: PP6 | N107: =IF(E107="","",IF(COUNTIF(X107:AB107,NA())>0,CONST_ERR_Inconsistent,IF(OR(F107="",L107="",AND(AH107=FALSE(),COUNTA(G107:K107)=0)),CONST_ERR_Incomplete,""))) | S107: =IF(E107="",CONST_NA,E107) | T107: =IF(E107="",CONST_NA,IF(L107="",D107 & " - " & E107,L107)) | U107: =IF(E107="","",INDEX(CONST_LIST_GoodsProdRouteAdd,MATCH(E107,CONST_LIST_Goods,0))) | V107: =D107 | W107: =IF(E107="","",MATCH(E107,CONST_LIST_Goods,0)) | X107: =IF(G107="","",MATCH(G107,INDEX(CONST_MATRIX_ProductionRoute,$W107,),0)) | Y107: =IF(H107="","",MATCH(H107,INDEX(CONST_MATRIX_ProductionRoute,$W107,),0)) | Z107: =IF(I107="","",MATCH(I107,INDEX(CONST_MATRIX_ProductionRoute,$W107,),0)) | AA107: =IF(J107="","",MATCH(J107,INDEX(CONST_MATRIX_ProductionRoute,$W107,),0)) | AB107: =IF(K107="","",MATCH(K107,INDEX(CONST_MATRIX_ProductionRoute,$W107,),0)) | AG107: =IF(AND(CNTR_HasEntriesA,N107<>""),CONST_ErrorOrMissing&$A$96,CONST_NA) | AH107: =IF(OR(CNTR_HasEntriesA=FALSE(),E107=""),"",COUNTIF(INDEX(CONST_MATRIX_ProductionRoute,MATCH(E107,CONST_LIST_Goods,0),),CONST_NA)=9) | AI107: =AND(CNTR_HasEntriesA,E107="")
D108: PP7 | N108: =IF(E108="","",IF(COUNTIF(X108:AB108,NA())>0,CONST_ERR_Inconsistent,IF(OR(F108="",L108="",AND(AH108=FALSE(),COUNTA(G108:K108)=0)),CONST_ERR_Incomplete,""))) | S108: =IF(E108="",CONST_NA,E108) | T108: =IF(E108="",CONST_NA,IF(L108="",D108 & " - " & E108,L108)) | U108: =IF(E108="","",INDEX(CONST_LIST_GoodsProdRouteAdd,MATCH(E108,CONST_LIST_Goods,0))) | V108: =D108 | W108: =IF(E108="","",MATCH(E108,CONST_LIST_Goods,0)) | X108: =IF(G108="","",MATCH(G108,INDEX(CONST_MATRIX_ProductionRoute,$W108,),0)) | Y108: =IF(H108="","",MATCH(H108,INDEX(CONST_MATRIX_ProductionRoute,$W108,),0)) | Z108: =IF(I108="","",MATCH(I108,INDEX(CONST_MATRIX_ProductionRoute,$W108,),0)) | AA108: =IF(J108="","",MATCH(J108,INDEX(CONST_MATRIX_ProductionRoute,$W108,),0)) | AB108: =IF(K108="","",MATCH(K108,INDEX(CONST_MATRIX_ProductionRoute,$W108,),0)) | AG108: =IF(AND(CNTR_HasEntriesA,N108<>""),CONST_ErrorOrMissing&$A$96,CONST_NA) | AH108: =IF(OR(CNTR_HasEntriesA=FALSE(),E108=""),"",COUNTIF(INDEX(CONST_MATRIX_ProductionRoute,MATCH(E108,CONST_LIST_Goods,0),),CONST_NA)=9) | AI108: =AND(CNTR_HasEntriesA,E108="")
D109: PP8 | N109: =IF(E109="","",IF(COUNTIF(X109:AB109,NA())>0,CONST_ERR_Inconsistent,IF(OR(F109="",L109="",AND(AH109=FALSE(),COUNTA(G109:K109)=0)),CONST_ERR_Incomplete,""))) | S109: =IF(E109="",CONST_NA,E109) | T109: =IF(E109="",CONST_NA,IF(L109="",D109 & " - " & E109,L109)) | U109: =IF(E109="","",INDEX(CONST_LIST_GoodsProdRouteAdd,MATCH(E109,CONST_LIST_Goods,0))) | V109: =D109 | W109: =IF(E109="","",MATCH(E109,CONST_LIST_Goods,0)) | X109: =IF(G109="","",MATCH(G109,INDEX(CONST_MATRIX_ProductionRoute,$W109,),0)) | Y109: =IF(H109="","",MATCH(H109,INDEX(CONST_MATRIX_ProductionRoute,$W109,),0)) | Z109: =IF(I109="","",MATCH(I109,INDEX(CONST_MATRIX_ProductionRoute,$W109,),0)) | AA109: =IF(J109="","",MATCH(J109,INDEX(CONST_MATRIX_ProductionRoute,$W109,),0)) | AB109: =IF(K109="","",MATCH(K109,INDEX(CONST_MATRIX_ProductionRoute,$W109,),0)) | AG109: =IF(AND(CNTR_HasEntriesA,N109<>""),CONST_ErrorOrMissing&$A$96,CONST_NA) | AH109: =IF(OR(CNTR_HasEntriesA=FALSE(),E109=""),"",COUNTIF(INDEX(CONST_MATRIX_ProductionRoute,MATCH(E109,CONST_LIST_Goods,0),),CONST_NA)=9) | AI109: =AND(CNTR_HasEntriesA,E109="")
D110: PP9 | N110: =IF(E110="","",IF(COUNTIF(X110:AB110,NA())>0,CONST_ERR_Inconsistent,IF(OR(F110="",L110="",AND(AH110=FALSE(),COUNTA(G110:K110)=0)),CONST_ERR_Incomplete,""))) | S110: =IF(E110="",CONST_NA,E110) | T110: =IF(E110="",CONST_NA,IF(L110="",D110 & " - " & E110,L110)) | U110: =IF(E110="","",INDEX(CONST_LIST_GoodsProdRouteAdd,MATCH(E110,CONST_LIST_Goods,0))) | V110: =D110 | W110: =IF(E110="","",MATCH(E110,CONST_LIST_Goods,0)) | X110: =IF(G110="","",MATCH(G110,INDEX(CONST_MATRIX_ProductionRoute,$W110,),0)) | Y110: =IF(H110="","",MATCH(H110,INDEX(CONST_MATRIX_ProductionRoute,$W110,),0)) | Z110: =IF(I110="","",MATCH(I110,INDEX(CONST_MATRIX_ProductionRoute,$W110,),0)) | AA110: =IF(J110="","",MATCH(J110,INDEX(CONST_MATRIX_ProductionRoute,$W110,),0)) | AB110: =IF(K110="","",MATCH(K110,INDEX(CONST_MATRIX_ProductionRoute,$W110,),0)) | AG110: =IF(AND(CNTR_HasEntriesA,N110<>""),CONST_ErrorOrMissing&$A$96,CONST_NA) | AH110: =IF(OR(CNTR_HasEntriesA=FALSE(),E110=""),"",COUNTIF(INDEX(CONST_MATRIX_ProductionRoute,MATCH(E110,CONST_LIST_Goods,0),),CONST_NA)=9) | AI110: =AND(CNTR_HasEntriesA,E110="")
D111: PP10 | N111: =IF(E111="","",IF(COUNTIF(X111:AB111,NA())>0,CONST_ERR_Inconsistent,IF(OR(F111="",L111="",AND(AH111=FALSE(),COUNTA(G111:K111)=0)),CONST_ERR_Incomplete,""))) | S111: =IF(E111="",CONST_NA,E111) | T111: =IF(E111="",CONST_NA,IF(L111="",D111 & " - " & E111,L111)) | U111: =IF(E111="","",INDEX(CONST_LIST_GoodsProdRouteAdd,MATCH(E111,CONST_LIST_Goods,0))) | V111: =D111 | W111: =IF(E111="","",MATCH(E111,CONST_LIST_Goods,0)) | X111: =IF(G111="","",MATCH(G111,INDEX(CONST_MATRIX_ProductionRoute,$W111,),0)) | Y111: =IF(H111="","",MATCH(H111,INDEX(CONST_MATRIX_ProductionRoute,$W111,),0)) | Z111: =IF(I111="","",MATCH(I111,INDEX(CONST_MATRIX_ProductionRoute,$W111,),0)) | AA111: =IF(J111="","",MATCH(J111,INDEX(CONST_MATRIX_ProductionRoute,$W111,),0)) | AB111: =IF(K111="","",MATCH(K111,INDEX(CONST_MATRIX_ProductionRoute,$W111,),0)) | AG111: =IF(AND(CNTR_HasEntriesA,N111<>""),CONST_ErrorOrMissing&$A$96,CONST_NA) | AH111: =IF(OR(CNTR_HasEntriesA=FALSE(),E111=""),"",COUNTIF(INDEX(CONST_MATRIX_ProductionRoute,MATCH(E111,CONST_LIST_Goods,0),),CONST_NA)=9) | AI111: =AND(CNTR_HasEntriesA,E111="")
D112: PP11 | N112: =IF(E112="","",IF(COUNTIF(X112:AB112,NA())>0,CONST_ERR_Inconsistent,IF(OR(F112="",L112="",AND(AH112=FALSE(),COUNTA(G112:K112)=0)),CONST_ERR_Incomplete,""))) | S112: =IF(E112="",CONST_NA,E112) | T112: =IF(E112="",CONST_NA,IF(L112="",D112 & " - " & E112,L112)) | U112: =IF(E112="","",INDEX(CONST_LIST_GoodsProdRouteAdd,MATCH(E112,CONST_LIST_Goods,0))) | V112: =D112 | W112: =IF(E112="","",MATCH(E112,CONST_LIST_Goods,0)) | X112: =IF(G112="","",MATCH(G112,INDEX(CONST_MATRIX_ProductionRoute,$W112,),0)) | Y112: =IF(H112="","",MATCH(H112,INDEX(CONST_MATRIX_ProductionRoute,$W112,),0)) | Z112: =IF(I112="","",MATCH(I112,INDEX(CONST_MATRIX_ProductionRoute,$W112,),0)) | AA112: =IF(J112="","",MATCH(J112,INDEX(CONST_MATRIX_ProductionRoute,$W112,),0)) | AB112: =IF(K112="","",MATCH(K112,INDEX(CONST_MATRIX_ProductionRoute,$W112,),0)) | AG112: =IF(AND(CNTR_HasEntriesA,N112<>""),CONST_ErrorOrMissing&$A$96,CONST_NA) | AH112: =IF(OR(CNTR_HasEntriesA=FALSE(),E112=""),"",COUNTIF(INDEX(CONST_MATRIX_ProductionRoute,MATCH(E112,CONST_LIST_Goods,0),),CONST_NA)=9) | AI112: =AND(CNTR_HasEntriesA,E112="")
D113: PP12 | N113: =IF(E113="","",IF(COUNTIF(X113:AB113,NA())>0,CONST_ERR_Inconsistent,IF(OR(F113="",L113="",AND(AH113=FALSE(),COUNTA(G113:K113)=0)),CONST_ERR_Incomplete,""))) | S113: =IF(E113="",CONST_NA,E113) | T113: =IF(E113="",CONST_NA,IF(L113="",D113 & " - " & E113,L113)) | U113: =IF(E113="","",INDEX(CONST_LIST_GoodsProdRouteAdd,MATCH(E113,CONST_LIST_Goods,0))) | V113: =D113 | W113: =IF(E113="","",MATCH(E113,CONST_LIST_Goods,0)) | X113: =IF(G113="","",MATCH(G113,INDEX(CONST_MATRIX_ProductionRoute,$W113,),0)) | Y113: =IF(H113="","",MATCH(H113,INDEX(CONST_MATRIX_ProductionRoute,$W113,),0)) | Z113: =IF(I113="","",MATCH(I113,INDEX(CONST_MATRIX_ProductionRoute,$W113,),0)) | AA113: =IF(J113="","",MATCH(J113,INDEX(CONST_MATRIX_ProductionRoute,$W113,),0)) | AB113: =IF(K113="","",MATCH(K113,INDEX(CONST_MATRIX_ProductionRoute,$W113,),0)) | AG113: =IF(AND(CNTR_HasEntriesA,N113<>""),CONST_ErrorOrMissing&$A$96,CONST_NA) | AH113: =IF(OR(CNTR_HasEntriesA=FALSE(),E113=""),"",COUNTIF(INDEX(CONST_MATRIX_ProductionRoute,MATCH(E113,CONST_LIST_Goods,0),),CONST_NA)=9) | AI113: =AND(CNTR_HasEntriesA,E113="")
... D121: PP20 | N121: =IF(E121="","",IF(COUNTIF(X121:AB121,NA())>0,CONST_ERR_Inconsistent,IF(OR(F121="",L121="",AND(AH121=FALSE(),COUNTA(G121:K121)=0)),CONST_ERR_Incomplete,""))) | S121: =IF(E121="",CONST_NA,E121) | T121: =IF(E121="",CONST_NA,IF(L121="",D121 & " - " & E121,L121)) | U121: =IF(E121="","",INDEX(CONST_LIST_GoodsProdRouteAdd,MATCH(E121,CONST_LIST_Goods,0))) | V121: =D121 | W121: =IF(E121="","",MATCH(E121,CONST_LIST_Goods,0)) | X121: =IF(G121="","",MATCH(G121,INDEX(CONST_MATRIX_ProductionRoute,$W121,),0)) | Y121: =IF(H121="","",MATCH(H121,INDEX(CONST_MATRIX_ProductionRoute,$W121,),0)) | Z121: =IF(I121="","",MATCH(I121,INDEX(CONST_MATRIX_ProductionRoute,$W121,),0)) | AA121: =IF(J121="","",MATCH(J121,INDEX(CONST_MATRIX_ProductionRoute,$W121,),0)) | AB121: =IF(K121="","",MATCH(K121,INDEX(CONST_MATRIX_ProductionRoute,$W121,),0)) | AG121: =IF(AND(CNTR_HasEntriesA,N121<>""),CONST_ErrorOrMissing&$A$96,CONST_NA) | AH121: =IF(OR(CNTR_HasEntriesA=FALSE(),E121=""),"",COUNTIF(INDEX(CONST_MATRIX_ProductionRoute,MATCH(E121,CONST_LIST_Goods,0),),CONST_NA)=9) | AI121: =AND(CNTR_HasEntriesA,E121="")
A123: ausblenden | P123: PRINT
A124: ausblenden | J124: CNTR_HasEntriesA | K124: =COUNTA(I9,L9,I19:N32,E62:F71,E102:E121)>0
A125: ausblenden

Sheet B_EmInst
A1: ausblenden | T1: ausblenden | U1: ausblenden | AB1: ausblenden | AC1: ausblenden | AW1: ausblenden | AZ1: ausblenden | BA1: ausblenden | BB1: ausblenden | BC1: ausblenden | BD1: ausblenden | BE1: ausblenden | BF1: ausblenden | BG1: ausblenden | BH1: ausblenden | BI1: ausblenden | BJ1: ausblenden | BK1: ausblenden | BL1: ausblenden | BM1: ausblenden | BN1: ausblenden | BO1: ausblenden | BP1: ausblenden | BQ1: ausblenden | BR1: ausblenden | BS1: ausblenden | BT1: ausblenden | BU1: ausblenden | BV1: ausblenden | BW1: ausblenden
B2: =Translations!$B$127 | E2: =Translations!$B$11 | G2: =HYPERLINK("#"&ADDRESS(2,3,,,a_Contents!$U$2),a_Contents!$B$2) | I2: =HYPERLINK("#"&ADDRESS(2,3,,,G_FurtherGuidance!$U$2),G_FurtherGuidance!$B$2) | K2: =HYPERLINK("#"&ADDRESS(2,3,,,Summary_Processes!$Y$2),Summary_Processes!$Y$2) | M2: =HYPERLINK("#"&ADDRESS(2,3,,,Summary_Products!$BF$2),Summary_Products!$BF$2) | BA2: Print area: | BB2: =ADDRESS(ROW($B$8),COLUMN($B$8)) & ":" & ADDRESS(MATCH("PRINT",$AZ:$AZ,0),COLUMN($AZ$8)) | BC2: Name of this sheet | BD2: =IF(ISERROR(CELL("filename",BE2)),"B_EmInst",MID(CELL("filename",BE2),FIND("]",CELL("filename",BE2))+1,1024))
G3: =IFERROR(HYPERLINK("#"&ADDRESS(ROW($A$1)+MATCH(BA3,$A:$A,0)-1,3),INDEX($BA:$BA,MATCH(BA3,$A:$A,0))),"") | I3: =IFERROR(HYPERLINK("#"&ADDRESS(ROW($A$1)+MATCH(BC3,$A:$A,0)-1,3),INDEX($BA:$BA,MATCH(BC3,$A:$A,0))),"") | K3: =IFERROR(HYPERLINK("#"&ADDRESS(ROW($A$1)+MATCH(BE3,$A:$A,0)-1,3),INDEX($BA:$BA,MATCH(BE3,$A:$A,0))),"") | BA3: 1 | BC3: 2 | BE3: 3
C6: B. | D6: =Translations!$B$128
C8: 1 | D8: =Translations!$B$129
D10: =HYPERLINK("#"&ADDRESS(MATCH($BB10,G_FurtherGuidance!$S:$S,0),3,,,G_FurtherGuidance!$U$2),CONST_LinkToGuidanceSheet) | BA10: Link to guidance: | BB10: 2
A12: 1 | C12: (a) | D12: =Translations!$B$1958 | T12: Delete | U12: Delete | AB12: Delete | AC12: Delete | AW12: Delete | BA12: Source streams | BD12: fossil | BH12: biomass | BL12: Cond. Formats --> True = white | BP12: True = light yellow | BR12: Error of FALSE | BW12: Cond. Formats
C13: =Translations!$B$131 | D13: =Translations!$B$132 | E13: =Translations!$B$133 | F13: =Translations!$B$134 | G13: =Translations!$B$135 | H13: =Translations!$B$136 | I13: =Translations!$B$137 | J13: =Translations!$B$138 | K13: =Translations!$B$139 | L13: =Translations!$B$140 | M13: =Translations!$B$141 | N13: =Translations!$B$142 | O13: =Translations!$B$143 | P13: =Translations!$B$144 | Q13: =Translations!$B$145 | R13: =Translations!$B$146 | S13: =Translations!$B$147 | T13: non-sust. BioC | U13: non-sust. BioC Unit | V13: =Translations!$B$150 | W13: =Translations!$B$151 | X13: =Translations!$B$152 | Y13: =Translations!$B$153 | Z13: =Translations!$B$1959 | AA13: =Translations!$B$1960 | AB13: Flue gas (total) | AC13: Flue gas (total), Unit | AD13: =Translations!$B$158 | AE13: =Translations!$B$159 | AF13: =Translations!$B$1961 | AG13: =Translations!$B$161 | AH13: =Translations!$B$162 | AI13: =Translations!$B$163 | AJ13: =Translations!$B$164 | AK13: =Translations!$B$165 | AL13: =Translations!$B$166 | AM13: =Translations!$B$167 | AN13: =Translations!$B$168 | AO13: =Translations!$B$169 | AP13: =Translations!$B$170 | AQ13: =Translations!$B$171 | AR13: =Translations!$B$172 | AS13: =Translations!$B$173 | AT13: =Translations!$B$174 | AU13: =Translations!$B$175 | AV13: =Translations!$B$176 | AW13: CO2e non-sust. bio (t) | AX13: =Translations!$B$178 | AY13: =Translations!$B$179 | BD13: Combustion | BE13: Process | BF13: Mass Balance | BH13: Combustion | BI13: Process | BJ13: Mass Balance | BL13: Emission factor (EF) | BM13: CC | BN13: OxF | BO13: ConvF | BP13: NCV | BR13: AD+EF Units consistent? | BS13: Complete-ness? Combustion | BT13: Complete-ness? Process | BU13: Complete-ness? Mass balance
C14: =Translations!$B$180 | D14: =Translations!$B$181 | E14: =Translations!$B$182 | F14: 252000 | G14: t | H14: 45 | I14: =IF(E14="","",IF(G14="","", IF(G14=CONST_kNm3,CONST_GJpkNm3,CONST_GJpt))) | J14: 73 | K14: =Translations!$B$184 | M14: =IF(D14<>INDEX(CONST_MonitoringApproach,3),"", IF(G14="","", CONST_tC&"/"&IF(G14="",CONST_t,G14))) | N14: 100 | O14: % | Q14: % | R14: 0 | S14: % | U14: % | AU14: =IF($D14="","",IF(BR14=FALSE(),CONST_ERR_Inconsistent,IF(COUNTIF(BS14:BU14,FALSE())>0,CONST_ERR_Incomplete,SUM(BD14:BF14)))) | AV14: =IF(ISNUMBER(AU14),SUM(BH14:BJ14),"") | AX14: =IF($D14="","",$F14*$H14/1000*(1-$R14/100)) | AY14: =IF($D14="","",$F14*$H14/1000*($R14/100)) | BD14: =IF($D14<>INDEX(CONST_MonitoringApproach,1),"",$F14*IF($K14=CONST_tCO2pTJ,$H14/1000,1)*$J14*IF($N14="",1,$N14/100)*(1-$R14/100)) | BE14: =IF($D14<>INDEX(CONST_MonitoringApproach,2),"",$F14*IF($K14=CONST_tCO2pTJ,$H14/1000,1)*$J14*IF($P14="",1,$P14/100)*(1-$R14/100)) | BF14: =IF($D14<>INDEX(CONST_MonitoringApproach,3),"",$F14*$L14*3.664*(1-$R14/100)) | BH14: =IF($D14<>INDEX(CONST_MonitoringApproach,1),"",$F14*IF($K14=CONST_tCO2pTJ,$H14/1000,1)*$J14*IF($N14="",1,$N14/100)*($R14/100)) | BI14: =IF($D14<>INDEX(CONST_MonitoringApproach,2),"",$F14*IF($K14=CONST_tCO2pTJ,$H14/1000,1)*$J14*IF($P14="",1,$P14/100)*($R14/100)) | BJ14: =IF($D14<>INDEX(CONST_MonitoringApproach,3),"",$F14*$L14*3.664*($R14/100)) | BR14: =IF($D14="","",OR(AND($G14 = INDEX(CONST_torkNm3,1), $K14=INDEX(CONST_tCO2pTJOrtCO2pt,2)),AND($G14 = INDEX(CONST_torkNm3,2),$K14=INDEX(CONST_tCO2pTJOrtCO2pt,3)),$K14=INDEX(CONST_tCO2pTJOrtCO2pt,1),$D14=INDEX(CONST_MonitoringApproach,3))) | BS14: =IF($D14<>INDEX(CONST_MonitoringApproach,1),"", AND(COUNTA($E14,$G14,$K14)=3,COUNT($F14,$J14)=2,IF($K14=CONST_tCO2pTJ,ISNUMBER($H14),TRUE()))) | BT14: =IF($D14<>INDEX(CONST_MonitoringApproach,2),"", AND(COUNTA($E14,$G14,$K14)=3,COUNT($F14,$J14)=2,IF($K14=CONST_tCO2pTJ,ISNUMBER($H14),TRUE()))) | BU14: =IF($D14<>INDEX(CONST_MonitoringApproach,3),"",AND(COUNTA($E14,$G14)=2,COUNT($F14,$L14)=2))
C15: =Translations!$B$185 | D15: =Translations!$B$186 | E15: =Translations!$B$187 | F15: 121000 | G15: t | I15: =IF(E15="","",IF(G15="","", IF(G15=CONST_kNm3,CONST_GJpkNm3,CONST_GJpt))) | J15: 0.08794 | K15: =Translations!$B$188 | M15: =IF(D15<>INDEX(CONST_MonitoringApproach,3),"", IF(G15="","", CONST_tC&"/"&IF(G15="",CONST_t,G15))) | O15: % | P15: 100 | Q15: % | R15: 0 | S15: % | U15: % | AU15: =IF($D15="","",IF(BR15=FALSE(),CONST_ERR_Inconsistent,IF(COUNTIF(BS15:BU15,FALSE())>0,CONST_ERR_Incomplete,SUM(BD15:BF15)))) | AV15: =IF(ISNUMBER(AU15),SUM(BH15:BJ15),"") | AX15: =IF($D15="","",$F15*$H15/1000*(1-$R15/100)) | AY15: =IF($D15="","",$F15*$H15/1000*($R15/100)) | BD15: =IF($D15<>INDEX(CONST_MonitoringApproach,1),"",$F15*IF($K15=CONST_tCO2pTJ,$H15/1000,1)*$J15*IF($N15="",1,$N15/100)*(1-$R15/100)) | BE15: =IF($D15<>INDEX(CONST_MonitoringApproach,2),"",$F15*IF($K15=CONST_tCO2pTJ,$H15/1000,1)*$J15*IF($P15="",1,$P15/100)*(1-$R15/100)) | BF15: =IF($D15<>INDEX(CONST_MonitoringApproach,3),"",$F15*$L15*3.664*(1-$R15/100)) | BH15: =IF($D15<>INDEX(CONST_MonitoringApproach,1),"",$F15*IF($K15=CONST_tCO2pTJ,$H15/1000,1)*$J15*IF($N15="",1,$N15/100)*($R15/100)) | BI15: =IF($D15<>INDEX(CONST_MonitoringApproach,2),"",$F15*IF($K15=CONST_tCO2pTJ,$H15/1000,1)*$J15*IF($P15="",1,$P15/100)*($R15/100)) | BJ15: =IF($D15<>INDEX(CONST_MonitoringApproach,3),"",$F15*$L15*3.664*($R15/100)) | BR15: =IF($D15="","",OR(AND($G15 = INDEX(CONST_torkNm3,1), $K15=INDEX(CONST_tCO2pTJOrtCO2pt,2)),AND($G15 = INDEX(CONST_torkNm3,2),$K15=INDEX(CONST_tCO2pTJOrtCO2pt,3)),$K15=INDEX(CONST_tCO2pTJOrtCO2pt,1),$D15=INDEX(CONST_MonitoringApproach,3))) | BS15: =IF($D15<>INDEX(CONST_MonitoringApproach,1),"", AND(COUNTA($E15,$G15,$K15)=3,COUNT($F15,$J15)=2,IF($K15=CONST_tCO2pTJ,ISNUMBER($H15),TRUE()))) | BT15: =IF($D15<>INDEX(CONST_MonitoringApproach,2),"", AND(COUNTA($E15,$G15,$K15)=3,COUNT($F15,$J15)=2,IF($K15=CONST_tCO2pTJ,ISNUMBER($H15),TRUE()))) | BU15: =IF($D15<>INDEX(CONST_MonitoringApproach,3),"",AND(COUNTA($E15,$G15)=2,COUNT($F15,$L15)=2))
C16: =Translations!$B$189 | D16: =Translations!$B$190 | E16: =Translations!$B$191 | F16: -1808226 | G16: t | I16: =IF(E16="","",IF(G16="","", IF(G16=CONST_kNm3,CONST_GJpkNm3,CONST_GJpt))) | L16: 0.003878 | M16: =IF(D16<>INDEX(CONST_MonitoringApproach,3),"", IF(G16="","", CONST_tC&"/"&IF(G16="",CONST_t,G16))) | O16: % | Q16: % | R16: 0 | S16: % | U16: % | AU16: =IF($D16="","",IF(BR16=FALSE(),CONST_ERR_Inconsistent,IF(COUNTIF(BS16:BU16,FALSE())>0,CONST_ERR_Incomplete,SUM(BD16:BF16)))) | AV16: =IF(ISNUMBER(AU16),SUM(BH16:BJ16),"") | AX16: =IF($D16="","",$F16*$H16/1000*(1-$R16/100)) | AY16: =IF($D16="","",$F16*$H16/1000*($R16/100)) | BD16: =IF($D16<>INDEX(CONST_MonitoringApproach,1),"",$F16*IF($K16=CONST_tCO2pTJ,$H16/1000,1)*$J16*IF($N16="",1,$N16/100)*(1-$R16/100)) | BE16: =IF($D16<>INDEX(CONST_MonitoringApproach,2),"",$F16*IF($K16=CONST_tCO2pTJ,$H16/1000,1)*$J16*IF($P16="",1,$P16/100)*(1-$R16/100)) | BF16: =IF($D16<>INDEX(CONST_MonitoringApproach,3),"",$F16*$L16*3.664*(1-$R16/100)) | BH16: =IF($D16<>INDEX(CONST_MonitoringApproach,1),"",$F16*IF($K16=CONST_tCO2pTJ,$H16/1000,1)*$J16*IF($N16="",1,$N16/100)*($R16/100)) | BI16: =IF($D16<>INDEX(CONST_MonitoringApproach,2),"",$F16*IF($K16=CONST_tCO2pTJ,$H16/1000,1)*$J16*IF($P16="",1,$P16/100)*($R16/100)) | BJ16: =IF($D16<>INDEX(CONST_MonitoringApproach,3),"",$F16*$L16*3.664*($R16/100)) | BR16: =IF($D16="","",OR(AND($G16 = INDEX(CONST_torkNm3,1), $K16=INDEX(CONST_tCO2pTJOrtCO2pt,2)),AND($G16 = INDEX(CONST_torkNm3,2),$K16=INDEX(CONST_tCO2pTJOrtCO2pt,3)),$K16=INDEX(CONST_tCO2pTJOrtCO2pt,1),$D16=INDEX(CONST_MonitoringApproach,3))) | BS16: =IF($D16<>INDEX(CONST_MonitoringApproach,1),"", AND(COUNTA($E16,$G16,$K16)=3,COUNT($F16,$J16)=2,IF($K16=CONST_tCO2pTJ,ISNUMBER($H16),TRUE()))) | BT16: =IF($D16<>INDEX(CONST_MonitoringApproach,2),"", AND(COUNTA($E16,$G16,$K16)=3,COUNT($F16,$J16)=2,IF($K16=CONST_tCO2pTJ,ISNUMBER($H16),TRUE()))) | BU16: =IF($D16<>INDEX(CONST_MonitoringApproach,3),"",AND(COUNTA($E16,$G16)=2,COUNT($F16,$L16)=2))
C17: 1 | D17: Mass Balance | E17: Coke fines | F17: 50000 | G17: t | H17: 28.2 | I17: =IF(E17="","",IF(G17="","", IF(G17=CONST_kNm3,CONST_GJpkNm3,CONST_GJpt))) | L17: 0.88 | M17: =IF(D17<>INDEX(CONST_MonitoringApproach,3),"", IF(G17="","", CONST_tC&"/"&IF(G17="",CONST_t,G17))) | O17: % | Q17: % | S17: % | U17: % | AU17: =IF($D17="","",IF(BR17=FALSE(),CONST_ERR_Inconsistent,IF(COUNTIF(BS17:BU17,FALSE())>0,CONST_ERR_Incomplete,SUM(BD17:BF17)))) | AV17: =IF(ISNUMBER(AU17),SUM(BH17:BJ17),"") | AX17: =IF($D17="","",$F17*$H17/1000*(1-$R17/100)) | AY17: =IF($D17="","",$F17*$H17/1000*($R17/100)) | BA17: =CONST_CNTR_SUM_CO2 | BD17: =IF($D17<>INDEX(CONST_MonitoringApproach,1),"",$F17*IF($K17=CONST_tCO2pTJ,$H17/1000,1)*$J17*IF($N17="",1,$N17/100)*(1-$R17/100)) | BE17: =IF($D17<>INDEX(CONST_MonitoringApproach,2),"",$F17*IF($K17=CONST_tCO2pTJ,$H17/1000,1)*$J17*IF($P17="",1,$P17/100)*(1-$R17/100)) | BF17: =IF($D17<>INDEX(CONST_MonitoringApproach,3),"",$F17*$L17*3.664*(1-$R17/100)) | BH17: =IF($D17<>INDEX(CONST_MonitoringApproach,1),"",$F17*IF($K17=CONST_tCO2pTJ,$H17/1000,1)*$J17*IF($N17="",1,$N17/100)*($R17/100)) | BI17: =IF($D17<>INDEX(CONST_MonitoringApproach,2),"",$F17*IF($K17=CONST_tCO2pTJ,$H17/1000,1)*$J17*IF($P17="",1,$P17/100)*($R17/100)) | BJ17: =IF($D17<>INDEX(CONST_MonitoringApproach,3),"",$F17*$L17*3.664*($R17/100)) | BL17: =IF($D17="","",MATCH($D17,CONST_MonitoringApproach,0)=3) | BM17: =IF($D17="","",MATCH($D17,CONST_MonitoringApproach,0)<>3) | BN17: =IF($D17="","",MATCH($D17,CONST_MonitoringApproach,0)<>1) | BO17: =IF($D17="","",MATCH($D17,CONST_MonitoringApproach,0)<>2) | BP17: =OR($K17<>CONST_tCO2pTJ,$D17=INDEX(CONST_MonitoringApproach,3)) | BR17: =IF($D17="","",OR(AND($G17 = INDEX(CONST_torkNm3,1), $K17=INDEX(CONST_tCO2pTJOrtCO2pt,2)),AND($G17 = INDEX(CONST_torkNm3,2),$K17=INDEX(CONST_tCO2pTJOrtCO2pt,3)),$K17=INDEX(CONST_tCO2pTJOrtCO2pt,1),$D17=INDEX(CONST_MonitoringApproach,3))) | BS17: =IF($D17<>INDEX(CONST_MonitoringApproach,1),"", AND(COUNTA($E17,$G17,$K17)=3,COUNT($F17,$J17)=2,IF($K17=CONST_tCO2pTJ,ISNUMBER($H17),TRUE()))) | BT17: =IF($D17<>INDEX(CONST_MonitoringApproach,2),"", AND(COUNTA($E17,$G17,$K17)=3,COUNT($F17,$J17)=2,IF($K17=CONST_tCO2pTJ,ISNUMBER($H17),TRUE()))) | BU17: =IF($D17<>INDEX(CONST_MonitoringApproach,3),"",AND(COUNTA($E17,$G17)=2,COUNT($F17,$L17)=2)) | BW17: =AND(CNTR_HasEntriesA,D17="")
C18: 2 | D18: Mass Balance | E18: Iron ores | F18: 5600000 | G18: t | I18: =IF(E18="","",IF(G18="","", IF(G18=CONST_kNm3,CONST_GJpkNm3,CONST_GJpt))) | L18: 0.00023 | M18: =IF(D18<>INDEX(CONST_MonitoringApproach,3),"", IF(G18="","", CONST_tC&"/"&IF(G18="",CONST_t,G18))) | O18: % | Q18: % | S18: % | U18: % | AU18: =IF($D18="","",IF(BR18=FALSE(),CONST_ERR_Inconsistent,IF(COUNTIF(BS18:BU18,FALSE())>0,CONST_ERR_Incomplete,SUM(BD18:BF18)))) | AV18: =IF(ISNUMBER(AU18),SUM(BH18:BJ18),"") | AX18: =IF($D18="","",$F18*$H18/1000*(1-$R18/100)) | AY18: =IF($D18="","",$F18*$H18/1000*($R18/100)) | BA18: =CONST_CNTR_SUM_CO2 | BD18: =IF($D18<>INDEX(CONST_MonitoringApproach,1),"",$F18*IF($K18=CONST_tCO2pTJ,$H18/1000,1)*$J18*IF($N18="",1,$N18/100)*(1-$R18/100)) | BE18: =IF($D18<>INDEX(CONST_MonitoringApproach,2),"",$F18*IF($K18=CONST_tCO2pTJ,$H18/1000,1)*$J18*IF($P18="",1,$P18/100)*(1-$R18/100)) | BF18: =IF($D18<>INDEX(CONST_MonitoringApproach,3),"",$F18*$L18*3.664*(1-$R18/100)) | BH18: =IF($D18<>INDEX(CONST_MonitoringApproach,1),"",$F18*IF($K18=CONST_tCO2pTJ,$H18/1000,1)*$J18*IF($N18="",1,$N18/100)*($R18/100)) | BI18: =IF($D18<>INDEX(CONST_MonitoringApproach,2),"",$F18*IF($K18=CONST_tCO2pTJ,$H18/1000,1)*$J18*IF($P18="",1,$P18/100)*($R18/100)) | BJ18: =IF($D18<>INDEX(CONST_MonitoringApproach,3),"",$F18*$L18*3.664*($R18/100)) | BL18: =IF($D18="","",MATCH($D18,CONST_MonitoringApproach,0)=3) | BM18: =IF($D18="","",MATCH($D18,CONST_MonitoringApproach,0)<>3) | BN18: =IF($D18="","",MATCH($D18,CONST_MonitoringApproach,0)<>1) | BO18: =IF($D18="","",MATCH($D18,CONST_MonitoringApproach,0)<>2) | BP18: =OR($K18<>CONST_tCO2pTJ,$D18=INDEX(CONST_MonitoringApproach,3)) | BR18: =IF($D18="","",OR(AND($G18 = INDEX(CONST_torkNm3,1), $K18=INDEX(CONST_tCO2pTJOrtCO2pt,2)),AND($G18 = INDEX(CONST_torkNm3,2),$K18=INDEX(CONST_tCO2pTJOrtCO2pt,3)),$K18=INDEX(CONST_tCO2pTJOrtCO2pt,1),$D18=INDEX(CONST_MonitoringApproach,3))) | BS18: =IF($D18<>INDEX(CONST_MonitoringApproach,1),"", AND(COUNTA($E18,$G18,$K18)=3,COUNT($F18,$J18)=2,IF($K18=CONST_tCO2pTJ,ISNUMBER($H18),TRUE()))) | BT18: =IF($D18<>INDEX(CONST_MonitoringApproach,2),"", AND(COUNTA($E18,$G18,$K18)=3,COUNT($F18,$J18)=2,IF($K18=CONST_tCO2pTJ,ISNUMBER($H18),TRUE()))) | BU18: =IF($D18<>INDEX(CONST_MonitoringApproach,3),"",AND(COUNTA($E18,$G18)=2,COUNT($F18,$L18)=2)) | BW18: =AND(CNTR_HasEntriesA,D18="")
C19: 3 | D19: Mass Balance | E19: Coke | F19: 2200000 | G19: t | H19: 28.2 | I19: =IF(E19="","",IF(G19="","", IF(G19=CONST_kNm3,CONST_GJpkNm3,CONST_GJpt))) | L19: 0.88 | M19: =IF(D19<>INDEX(CONST_MonitoringApproach,3),"", IF(G19="","", CONST_tC&"/"&IF(G19="",CONST_t,G19))) | O19: % | Q19: % | S19: % | U19: % | AU19: =IF($D19="","",IF(BR19=FALSE(),CONST_ERR_Inconsistent,IF(COUNTIF(BS19:BU19,FALSE())>0,CONST_ERR_Incomplete,SUM(BD19:BF19)))) | AV19: =IF(ISNUMBER(AU19),SUM(BH19:BJ19),"") | AX19: =IF($D19="","",$F19*$H19/1000*(1-$R19/100)) | AY19: =IF($D19="","",$F19*$H19/1000*($R19/100)) | BA19: =CONST_CNTR_SUM_CO2 | BD19: =IF($D19<>INDEX(CONST_MonitoringApproach,1),"",$F19*IF($K19=CONST_tCO2pTJ,$H19/1000,1)*$J19*IF($N19="",1,$N19/100)*(1-$R19/100)) | BE19: =IF($D19<>INDEX(CONST_MonitoringApproach,2),"",$F19*IF($K19=CONST_tCO2pTJ,$H19/1000,1)*$J19*IF($P19="",1,$P19/100)*(1-$R19/100)) | BF19: =IF($D19<>INDEX(CONST_MonitoringApproach,3),"",$F19*$L19*3.664*(1-$R19/100)) | BH19: =IF($D19<>INDEX(CONST_MonitoringApproach,1),"",$F19*IF($K19=CONST_tCO2pTJ,$H19/1000,1)*$J19*IF($N19="",1,$N19/100)*($R19/100)) | BI19: =IF($D19<>INDEX(CONST_MonitoringApproach,2),"",$F19*IF($K19=CONST_tCO2pTJ,$H19/1000,1)*$J19*IF($P19="",1,$P19/100)*($R19/100)) | BJ19: =IF($D19<>INDEX(CONST_MonitoringApproach,3),"",$F19*$L19*3.664*($R19/100)) | BL19: =IF($D19="","",MATCH($D19,CONST_MonitoringApproach,0)=3) | BM19: =IF($D19="","",MATCH($D19,CONST_MonitoringApproach,0)<>3) | BN19: =IF($D19="","",MATCH($D19,CONST_MonitoringApproach,0)<>1) | BO19: =IF($D19="","",MATCH($D19,CONST_MonitoringApproach,0)<>2) | BP19: =OR($K19<>CONST_tCO2pTJ,$D19=INDEX(CONST_MonitoringApproach,3)) | BR19: =IF($D19="","",OR(AND($G19 = INDEX(CONST_torkNm3,1), $K19=INDEX(CONST_tCO2pTJOrtCO2pt,2)),AND($G19 = INDEX(CONST_torkNm3,2),$K19=INDEX(CONST_tCO2pTJOrtCO2pt,3)),$K19=INDEX(CONST_tCO2pTJOrtCO2pt,1),$D19=INDEX(CONST_MonitoringApproach,3))) | BS19: =IF($D19<>INDEX(CONST_MonitoringApproach,1),"", AND(COUNTA($E19,$G19,$K19)=3,COUNT($F19,$J19)=2,IF($K19=CONST_tCO2pTJ,ISNUMBER($H19),TRUE()))) | BT19: =IF($D19<>INDEX(CONST_MonitoringApproach,2),"", AND(COUNTA($E19,$G19,$K19)=3,COUNT($F19,$J19)=2,IF($K19=CONST_tCO2pTJ,ISNUMBER($H19),TRUE()))) | BU19: =IF($D19<>INDEX(CONST_MonitoringApproach,3),"",AND(COUNTA($E19,$G19)=2,COUNT($F19,$L19)=2)) | BW19: =AND(CNTR_HasEntriesA,D19="")
C20: 4 | D20: Mass Balance | E20: Plastic wastes | F20: 70000 | G20: t | H20: 38 | I20: =IF(E20="","",IF(G20="","", IF(G20=CONST_kNm3,CONST_GJpkNm3,CONST_GJpt))) | L20: 0.68357153 | M20: =IF(D20<>INDEX(CONST_MonitoringApproach,3),"", IF(G20="","", CONST_tC&"/"&IF(G20="",CONST_t,G20))) | O20: % | Q20: % | R20: 16 | S20: % | U20: % | AU20: =IF($D20="","",IF(BR20=FALSE(),CONST_ERR_Inconsistent,IF(COUNTIF(BS20:BU20,FALSE())>0,CONST_ERR_Incomplete,SUM(BD20:BF20)))) | AV20: =IF(ISNUMBER(AU20),SUM(BH20:BJ20),"") | AX20: =IF($D20="","",$F20*$H20/1000*(1-$R20/100)) | AY20: =IF($D20="","",$F20*$H20/1000*($R20/100)) | BA20: =CONST_CNTR_SUM_CO2 | BD20: =IF($D20<>INDEX(CONST_MonitoringApproach,1),"",$F20*IF($K20=CONST_tCO2pTJ,$H20/1000,1)*$J20*IF($N20="",1,$N20/100)*(1-$R20/100)) | BE20: =IF($D20<>INDEX(CONST_MonitoringApproach,2),"",$F20*IF($K20=CONST_tCO2pTJ,$H20/1000,1)*$J20*IF($P20="",1,$P20/100)*(1-$R20/100)) | BF20: =IF($D20<>INDEX(CONST_MonitoringApproach,3),"",$F20*$L20*3.664*(1-$R20/100)) | BH20: =IF($D20<>INDEX(CONST_MonitoringApproach,1),"",$F20*IF($K20=CONST_tCO2pTJ,$H20/1000,1)*$J20*IF($N20="",1,$N20/100)*($R20/100)) | BI20: =IF($D20<>INDEX(CONST_MonitoringApproach,2),"",$F20*IF($K20=CONST_tCO2pTJ,$H20/1000,1)*$J20*IF($P20="",1,$P20/100)*($R20/100)) | BJ20: =IF($D20<>INDEX(CONST_MonitoringApproach,3),"",$F20*$L20*3.664*($R20/100)) | BL20: =IF($D20="","",MATCH($D20,CONST_MonitoringApproach,0)=3) | BM20: =IF($D20="","",MATCH($D20,CONST_MonitoringApproach,0)<>3) | BN20: =IF($D20="","",MATCH($D20,CONST_MonitoringApproach,0)<>1) | BO20: =IF($D20="","",MATCH($D20,CONST_MonitoringApproach,0)<>2) | BP20: =OR($K20<>CONST_tCO2pTJ,$D20=INDEX(CONST_MonitoringApproach,3)) | BR20: =IF($D20="","",OR(AND($G20 = INDEX(CONST_torkNm3,1), $K20=INDEX(CONST_tCO2pTJOrtCO2pt,2)),AND($G20 = INDEX(CONST_torkNm3,2),$K20=INDEX(CONST_tCO2pTJOrtCO2pt,3)),$K20=INDEX(CONST_tCO2pTJOrtCO2pt,1),$D20=INDEX(CONST_MonitoringApproach,3))) | BS20: =IF($D20<>INDEX(CONST_MonitoringApproach,1),"", AND(COUNTA($E20,$G20,$K20)=3,COUNT($F20,$J20)=2,IF($K20=CONST_tCO2pTJ,ISNUMBER($H20),TRUE()))) | BT20: =IF($D20<>INDEX(CONST_MonitoringApproach,2),"", AND(COUNTA($E20,$G20,$K20)=3,COUNT($F20,$J20)=2,IF($K20=CONST_tCO2pTJ,ISNUMBER($H20),TRUE()))) | BU20: =IF($D20<>INDEX(CONST_MonitoringApproach,3),"",AND(COUNTA($E20,$G20)=2,COUNT($F20,$L20)=2)) | BW20: =AND(CNTR_HasEntriesA,D20="")
C21: 5 | D21: Mass Balance | E21: Scrap (external) | F21: 800000 | G21: t | I21: =IF(E21="","",IF(G21="","", IF(G21=CONST_kNm3,CONST_GJpkNm3,CONST_GJpt))) | L21: 0.0021 | M21: =IF(D21<>INDEX(CONST_MonitoringApproach,3),"", IF(G21="","", CONST_tC&"/"&IF(G21="",CONST_t,G21))) | O21: % | Q21: % | S21: % | U21: % | AU21: =IF($D21="","",IF(BR21=FALSE(),CONST_ERR_Inconsistent,IF(COUNTIF(BS21:BU21,FALSE())>0,CONST_ERR_Incomplete,SUM(BD21:BF21)))) | AV21: =IF(ISNUMBER(AU21),SUM(BH21:BJ21),"") | AX21: =IF($D21="","",$F21*$H21/1000*(1-$R21/100)) | AY21: =IF($D21="","",$F21*$H21/1000*($R21/100)) | BA21: =CONST_CNTR_SUM_CO2 | BD21: =IF($D21<>INDEX(CONST_MonitoringApproach,1),"",$F21*IF($K21=CONST_tCO2pTJ,$H21/1000,1)*$J21*IF($N21="",1,$N21/100)*(1-$R21/100)) | BE21: =IF($D21<>INDEX(CONST_MonitoringApproach,2),"",$F21*IF($K21=CONST_tCO2pTJ,$H21/1000,1)*$J21*IF($P21="",1,$P21/100)*(1-$R21/100)) | BF21: =IF($D21<>INDEX(CONST_MonitoringApproach,3),"",$F21*$L21*3.664*(1-$R21/100)) | BH21: =IF($D21<>INDEX(CONST_MonitoringApproach,1),"",$F21*IF($K21=CONST_tCO2pTJ,$H21/1000,1)*$J21*IF($N21="",1,$N21/100)*($R21/100)) | BI21: =IF($D21<>INDEX(CONST_MonitoringApproach,2),"",$F21*IF($K21=CONST_tCO2pTJ,$H21/1000,1)*$J21*IF($P21="",1,$P21/100)*($R21/100)) | BJ21: =IF($D21<>INDEX(CONST_MonitoringApproach,3),"",$F21*$L21*3.664*($R21/100)) | BL21: =IF($D21="","",MATCH($D21,CONST_MonitoringApproach,0)=3) | BM21: =IF($D21="","",MATCH($D21,CONST_MonitoringApproach,0)<>3) | BN21: =IF($D21="","",MATCH($D21,CONST_MonitoringApproach,0)<>1) | BO21: =IF($D21="","",MATCH($D21,CONST_MonitoringApproach,0)<>2) | BP21: =OR($K21<>CONST_tCO2pTJ,$D21=INDEX(CONST_MonitoringApproach,3)) | BR21: =IF($D21="","",OR(AND($G21 = INDEX(CONST_torkNm3,1), $K21=INDEX(CONST_tCO2pTJOrtCO2pt,2)),AND($G21 = INDEX(CONST_torkNm3,2),$K21=INDEX(CONST_tCO2pTJOrtCO2pt,3)),$K21=INDEX(CONST_tCO2pTJOrtCO2pt,1),$D21=INDEX(CONST_MonitoringApproach,3))) | BS21: =IF($D21<>INDEX(CONST_MonitoringApproach,1),"", AND(COUNTA($E21,$G21,$K21)=3,COUNT($F21,$J21)=2,IF($K21=CONST_tCO2pTJ,ISNUMBER($H21),TRUE()))) | BT21: =IF($D21<>INDEX(CONST_MonitoringApproach,2),"", AND(COUNTA($E21,$G21,$K21)=3,COUNT($F21,$J21)=2,IF($K21=CONST_tCO2pTJ,ISNUMBER($H21),TRUE()))) | BU21: =IF($D21<>INDEX(CONST_MonitoringApproach,3),"",AND(COUNTA($E21,$G21)=2,COUNT($F21,$L21)=2)) | BW21: =AND(CNTR_HasEntriesA,D21="")
C22: 6 | D22: Mass Balance | E22: Scrap (internal) | F22: 200000 | G22: t | I22: =IF(E22="","",IF(G22="","", IF(G22=CONST_kNm3,CONST_GJpkNm3,CONST_GJpt))) | L22: 0.0018 | M22: =IF(D22<>INDEX(CONST_MonitoringApproach,3),"", IF(G22="","", CONST_tC&"/"&IF(G22="",CONST_t,G22))) | O22: % | Q22: % | S22: % | U22: % | AU22: =IF($D22="","",IF(BR22=FALSE(),CONST_ERR_Inconsistent,IF(COUNTIF(BS22:BU22,FALSE())>0,CONST_ERR_Incomplete,SUM(BD22:BF22)))) | AV22: =IF(ISNUMBER(AU22),SUM(BH22:BJ22),"") | AX22: =IF($D22="","",$F22*$H22/1000*(1-$R22/100)) | AY22: =IF($D22="","",$F22*$H22/1000*($R22/100)) | BA22: =CONST_CNTR_SUM_CO2 | BD22: =IF($D22<>INDEX(CONST_MonitoringApproach,1),"",$F22*IF($K22=CONST_tCO2pTJ,$H22/1000,1)*$J22*IF($N22="",1,$N22/100)*(1-$R22/100)) | BE22: =IF($D22<>INDEX(CONST_MonitoringApproach,2),"",$F22*IF($K22=CONST_tCO2pTJ,$H22/1000,1)*$J22*IF($P22="",1,$P22/100)*(1-$R22/100)) | BF22: =IF($D22<>INDEX(CONST_MonitoringApproach,3),"",$F22*$L22*3.664*(1-$R22/100)) | BH22: =IF($D22<>INDEX(CONST_MonitoringApproach,1),"",$F22*IF($K22=CONST_tCO2pTJ,$H22/1000,1)*$J22*IF($N22="",1,$N22/100)*($R22/100)) | BI22: =IF($D22<>INDEX(CONST_MonitoringApproach,2),"",$F22*IF($K22=CONST_tCO2pTJ,$H22/1000,1)*$J22*IF($P22="",1,$P22/100)*($R22/100)) | BJ22: =IF($D22<>INDEX(CONST_MonitoringApproach,3),"",$F22*$L22*3.664*($R22/100)) | BL22: =IF($D22="","",MATCH($D22,CONST_MonitoringApproach,0)=3) | BM22: =IF($D22="","",MATCH($D22,CONST_MonitoringApproach,0)<>3) | BN22: =IF($D22="","",MATCH($D22,CONST_MonitoringApproach,0)<>1) | BO22: =IF($D22="","",MATCH($D22,CONST_MonitoringApproach,0)<>2) | BP22: =OR($K22<>CONST_tCO2pTJ,$D22=INDEX(CONST_MonitoringApproach,3)) | BR22: =IF($D22="","",OR(AND($G22 = INDEX(CONST_torkNm3,1), $K22=INDEX(CONST_tCO2pTJOrtCO2pt,2)),AND($G22 = INDEX(CONST_torkNm3,2),$K22=INDEX(CONST_tCO2pTJOrtCO2pt,3)),$K22=INDEX(CONST_tCO2pTJOrtCO2pt,1),$D22=INDEX(CONST_MonitoringApproach,3))) | BS22: =IF($D22<>INDEX(CONST_MonitoringApproach,1),"", AND(COUNTA($E22,$G22,$K22)=3,COUNT($F22,$J22)=2,IF($K22=CONST_tCO2pTJ,ISNUMBER($H22),TRUE()))) | BT22: =IF($D22<>INDEX(CONST_MonitoringApproach,2),"", AND(COUNTA($E22,$G22,$K22)=3,COUNT($F22,$J22)=2,IF($K22=CONST_tCO2pTJ,ISNUMBER($H22),TRUE()))) | BU22: =IF($D22<>INDEX(CONST_MonitoringApproach,3),"",AND(COUNTA($E22,$G22)=2,COUNT($F22,$L22)=2)) | BW22: =AND(CNTR_HasEntriesA,D22="")
C23: 7 | D23: Mass Balance | E23: Lime calcined | F23: 280000 | G23: t | I23: =IF(E23="","",IF(G23="","", IF(G23=CONST_kNm3,CONST_GJpkNm3,CONST_GJpt))) | L23: 0.0027292576 | M23: =IF(D23<>INDEX(CONST_MonitoringApproach,3),"", IF(G23="","", CONST_tC&"/"&IF(G23="",CONST_t,G23))) | O23: % | Q23: % | S23: % | U23: % | AU23: =IF($D23="","",IF(BR23=FALSE(),CONST_ERR_Inconsistent,IF(COUNTIF(BS23:BU23,FALSE())>0,CONST_ERR_Incomplete,SUM(BD23:BF23)))) | AV23: =IF(ISNUMBER(AU23),SUM(BH23:BJ23),"") | AX23: =IF($D23="","",$F23*$H23/1000*(1-$R23/100)) | AY23: =IF($D23="","",$F23*$H23/1000*($R23/100)) | BA23: =CONST_CNTR_SUM_CO2 | BD23: =IF($D23<>INDEX(CONST_MonitoringApproach,1),"",$F23*IF($K23=CONST_tCO2pTJ,$H23/1000,1)*$J23*IF($N23="",1,$N23/100)*(1-$R23/100)) | BE23: =IF($D23<>INDEX(CONST_MonitoringApproach,2),"",$F23*IF($K23=CONST_tCO2pTJ,$H23/1000,1)*$J23*IF($P23="",1,$P23/100)*(1-$R23/100)) | BF23: =IF($D23<>INDEX(CONST_MonitoringApproach,3),"",$F23*$L23*3.664*(1-$R23/100)) | BH23: =IF($D23<>INDEX(CONST_MonitoringApproach,1),"",$F23*IF($K23=CONST_tCO2pTJ,$H23/1000,1)*$J23*IF($N23="",1,$N23/100)*($R23/100)) | BI23: =IF($D23<>INDEX(CONST_MonitoringApproach,2),"",$F23*IF($K23=CONST_tCO2pTJ,$H23/1000,1)*$J23*IF($P23="",1,$P23/100)*($R23/100)) | BJ23: =IF($D23<>INDEX(CONST_MonitoringApproach,3),"",$F23*$L23*3.664*($R23/100)) | BL23: =IF($D23="","",MATCH($D23,CONST_MonitoringApproach,0)=3) | BM23: =IF($D23="","",MATCH($D23,CONST_MonitoringApproach,0)<>3) | BN23: =IF($D23="","",MATCH($D23,CONST_MonitoringApproach,0)<>1) | BO23: =IF($D23="","",MATCH($D23,CONST_MonitoringApproach,0)<>2) | BP23: =OR($K23<>CONST_tCO2pTJ,$D23=INDEX(CONST_MonitoringApproach,3)) | BR23: =IF($D23="","",OR(AND($G23 = INDEX(CONST_torkNm3,1), $K23=INDEX(CONST_tCO2pTJOrtCO2pt,2)),AND($G23 = INDEX(CONST_torkNm3,2),$K23=INDEX(CONST_tCO2pTJOrtCO2pt,3)),$K23=INDEX(CONST_tCO2pTJOrtCO2pt,1),$D23=INDEX(CONST_MonitoringApproach,3))) | BS23: =IF($D23<>INDEX(CONST_MonitoringApproach,1),"", AND(COUNTA($E23,$G23,$K23)=3,COUNT($F23,$J23)=2,IF($K23=CONST_tCO2pTJ,ISNUMBER($H23),TRUE()))) | BT23: =IF($D23<>INDEX(CONST_MonitoringApproach,2),"", AND(COUNTA($E23,$G23,$K23)=3,COUNT($F23,$J23)=2,IF($K23=CONST_tCO2pTJ,ISNUMBER($H23),TRUE()))) | BU23: =IF($D23<>INDEX(CONST_MonitoringApproach,3),"",AND(COUNTA($E23,$G23)=2,COUNT($F23,$L23)=2)) | BW23: =AND(CNTR_HasEntriesA,D23="")
C24: 8 | D24: Mass Balance | E24: Natural gas | F24: 170000 | G24: t | H24: 48 | I24: =IF(E24="","",IF(G24="","", IF(G24=CONST_kNm3,CONST_GJpkNm3,CONST_GJpt))) | L24: 0.75 | M24: =IF(D24<>INDEX(CONST_MonitoringApproach,3),"", IF(G24="","", CONST_tC&"/"&IF(G24="",CONST_t,G24))) | O24: % | Q24: % | S24: % | U24: % | AU24: =IF($D24="","",IF(BR24=FALSE(),CONST_ERR_Inconsistent,IF(COUNTIF(BS24:BU24,FALSE())>0,CONST_ERR_Incomplete,SUM(BD24:BF24)))) | AV24: =IF(ISNUMBER(AU24),SUM(BH24:BJ24),"") | AX24: =IF($D24="","",$F24*$H24/1000*(1-$R24/100)) | AY24: =IF($D24="","",$F24*$H24/1000*($R24/100)) | BA24: =CONST_CNTR_SUM_CO2 | BD24: =IF($D24<>INDEX(CONST_MonitoringApproach,1),"",$F24*IF($K24=CONST_tCO2pTJ,$H24/1000,1)*$J24*IF($N24="",1,$N24/100)*(1-$R24/100)) | BE24: =IF($D24<>INDEX(CONST_MonitoringApproach,2),"",$F24*IF($K24=CONST_tCO2pTJ,$H24/1000,1)*$J24*IF($P24="",1,$P24/100)*(1-$R24/100)) | BF24: =IF($D24<>INDEX(CONST_MonitoringApproach,3),"",$F24*$L24*3.664*(1-$R24/100)) | BH24: =IF($D24<>INDEX(CONST_MonitoringApproach,1),"",$F24*IF($K24=CONST_tCO2pTJ,$H24/1000,1)*$J24*IF($N24="",1,$N24/100)*($R24/100)) | BI24: =IF($D24<>INDEX(CONST_MonitoringApproach,2),"",$F24*IF($K24=CONST_tCO2pTJ,$H24/1000,1)*$J24*IF($P24="",1,$P24/100)*($R24/100)) | BJ24: =IF($D24<>INDEX(CONST_MonitoringApproach,3),"",$F24*$L24*3.664*($R24/100)) | BL24: =IF($D24="","",MATCH($D24,CONST_MonitoringApproach,0)=3) | BM24: =IF($D24="","",MATCH($D24,CONST_MonitoringApproach,0)<>3) | BN24: =IF($D24="","",MATCH($D24,CONST_MonitoringApproach,0)<>1) | BO24: =IF($D24="","",MATCH($D24,CONST_MonitoringApproach,0)<>2) | BP24: =OR($K24<>CONST_tCO2pTJ,$D24=INDEX(CONST_MonitoringApproach,3)) | BR24: =IF($D24="","",OR(AND($G24 = INDEX(CONST_torkNm3,1), $K24=INDEX(CONST_tCO2pTJOrtCO2pt,2)),AND($G24 = INDEX(CONST_torkNm3,2),$K24=INDEX(CONST_tCO2pTJOrtCO2pt,3)),$K24=INDEX(CONST_tCO2pTJOrtCO2pt,1),$D24=INDEX(CONST_MonitoringApproach,3))) | BS24: =IF($D24<>INDEX(CONST_MonitoringApproach,1),"", AND(COUNTA($E24,$G24,$K24)=3,COUNT($F24,$J24)=2,IF($K24=CONST_tCO2pTJ,ISNUMBER($H24),TRUE()))) | BT24: =IF($D24<>INDEX(CONST_MonitoringApproach,2),"", AND(COUNTA($E24,$G24,$K24)=3,COUNT($F24,$J24)=2,IF($K24=CONST_tCO2pTJ,ISNUMBER($H24),TRUE()))) | BU24: =IF($D24<>INDEX(CONST_MonitoringApproach,3),"",AND(COUNTA($E24,$G24)=2,COUNT($F24,$L24)=2)) | BW24: =AND(CNTR_HasEntriesA,D24="")
C25: 9 | D25: Mass Balance | E25: Other inputs | F25: 40000 | G25: t | I25: =IF(E25="","",IF(G25="","", IF(G25=CONST_kNm3,CONST_GJpkNm3,CONST_GJpt))) | L25: 0.1 | M25: =IF(D25<>INDEX(CONST_MonitoringApproach,3),"", IF(G25="","", CONST_tC&"/"&IF(G25="",CONST_t,G25))) | O25: % | Q25: % | S25: % | U25: % | AU25: =IF($D25="","",IF(BR25=FALSE(),CONST_ERR_Inconsistent,IF(COUNTIF(BS25:BU25,FALSE())>0,CONST_ERR_Incomplete,SUM(BD25:BF25)))) | AV25: =IF(ISNUMBER(AU25),SUM(BH25:BJ25),"") | AX25: =IF($D25="","",$F25*$H25/1000*(1-$R25/100)) | AY25: =IF($D25="","",$F25*$H25/1000*($R25/100)) | BA25: =CONST_CNTR_SUM_CO2 | BD25: =IF($D25<>INDEX(CONST_MonitoringApproach,1),"",$F25*IF($K25=CONST_tCO2pTJ,$H25/1000,1)*$J25*IF($N25="",1,$N25/100)*(1-$R25/100)) | BE25: =IF($D25<>INDEX(CONST_MonitoringApproach,2),"",$F25*IF($K25=CONST_tCO2pTJ,$H25/1000,1)*$J25*IF($P25="",1,$P25/100)*(1-$R25/100)) | BF25: =IF($D25<>INDEX(CONST_MonitoringApproach,3),"",$F25*$L25*3.664*(1-$R25/100)) | BH25: =IF($D25<>INDEX(CONST_MonitoringApproach,1),"",$F25*IF($K25=CONST_tCO2pTJ,$H25/1000,1)*$J25*IF($N25="",1,$N25/100)*($R25/100)) | BI25: =IF($D25<>INDEX(CONST_MonitoringApproach,2),"",$F25*IF($K25=CONST_tCO2pTJ,$H25/1000,1)*$J25*IF($P25="",1,$P25/100)*($R25/100)) | BJ25: =IF($D25<>INDEX(CONST_MonitoringApproach,3),"",$F25*$L25*3.664*($R25/100)) | BL25: =IF($D25="","",MATCH($D25,CONST_MonitoringApproach,0)=3) | BM25: =IF($D25="","",MATCH($D25,CONST_MonitoringApproach,0)<>3) | BN25: =IF($D25="","",MATCH($D25,CONST_MonitoringApproach,0)<>1) | BO25: =IF($D25="","",MATCH($D25,CONST_MonitoringApproach,0)<>2) | BP25: =OR($K25<>CONST_tCO2pTJ,$D25=INDEX(CONST_MonitoringApproach,3)) | BR25: =IF($D25="","",OR(AND($G25 = INDEX(CONST_torkNm3,1), $K25=INDEX(CONST_tCO2pTJOrtCO2pt,2)),AND($G25 = INDEX(CONST_torkNm3,2),$K25=INDEX(CONST_tCO2pTJOrtCO2pt,3)),$K25=INDEX(CONST_tCO2pTJOrtCO2pt,1),$D25=INDEX(CONST_MonitoringApproach,3))) | BS25: =IF($D25<>INDEX(CONST_MonitoringApproach,1),"", AND(COUNTA($E25,$G25,$K25)=3,COUNT($F25,$J25)=2,IF($K25=CONST_tCO2pTJ,ISNUMBER($H25),TRUE()))) | BT25: =IF($D25<>INDEX(CONST_MonitoringApproach,2),"", AND(COUNTA($E25,$G25,$K25)=3,COUNT($F25,$J25)=2,IF($K25=CONST_tCO2pTJ,ISNUMBER($H25),TRUE()))) | BU25: =IF($D25<>INDEX(CONST_MonitoringApproach,3),"",AND(COUNTA($E25,$G25)=2,COUNT($F25,$L25)=2)) | BW25: =AND(CNTR_HasEntriesA,D25="")
C26: 10 | D26: Mass Balance | E26: Steel | F26: -4800000 | G26: t | I26: =IF(E26="","",IF(G26="","", IF(G26=CONST_kNm3,CONST_GJpkNm3,CONST_GJpt))) | L26: 0.0018 | M26: =IF(D26<>INDEX(CONST_MonitoringApproach,3),"", IF(G26="","", CONST_tC&"/"&IF(G26="",CONST_t,G26))) | O26: % | Q26: % | S26: % | U26: % | AU26: =IF($D26="","",IF(BR26=FALSE(),CONST_ERR_Inconsistent,IF(COUNTIF(BS26:BU26,FALSE())>0,CONST_ERR_Incomplete,SUM(BD26:BF26)))) | AV26: =IF(ISNUMBER(AU26),SUM(BH26:BJ26),"") | AX26: =IF($D26="","",$F26*$H26/1000*(1-$R26/100)) | AY26: =IF($D26="","",$F26*$H26/1000*($R26/100)) | BA26: =CONST_CNTR_SUM_CO2 | BD26: =IF($D26<>INDEX(CONST_MonitoringApproach,1),"",$F26*IF($K26=CONST_tCO2pTJ,$H26/1000,1)*$J26*IF($N26="",1,$N26/100)*(1-$R26/100)) | BE26: =IF($D26<>INDEX(CONST_MonitoringApproach,2),"",$F26*IF($K26=CONST_tCO2pTJ,$H26/1000,1)*$J26*IF($P26="",1,$P26/100)*(1-$R26/100)) | BF26: =IF($D26<>INDEX(CONST_MonitoringApproach,3),"",$F26*$L26*3.664*(1-$R26/100)) | BH26: =IF($D26<>INDEX(CONST_MonitoringApproach,1),"",$F26*IF($K26=CONST_tCO2pTJ,$H26/1000,1)*$J26*IF($N26="",1,$N26/100)*($R26/100)) | BI26: =IF($D26<>INDEX(CONST_MonitoringApproach,2),"",$F26*IF($K26=CONST_tCO2pTJ,$H26/1000,1)*$J26*IF($P26="",1,$P26/100)*($R26/100)) | BJ26: =IF($D26<>INDEX(CONST_MonitoringApproach,3),"",$F26*$L26*3.664*($R26/100)) | BL26: =IF($D26="","",MATCH($D26,CONST_MonitoringApproach,0)=3) | BM26: =IF($D26="","",MATCH($D26,CONST_MonitoringApproach,0)<>3) | BN26: =IF($D26="","",MATCH($D26,CONST_MonitoringApproach,0)<>1) | BO26: =IF($D26="","",MATCH($D26,CONST_MonitoringApproach,0)<>2) | BP26: =OR($K26<>CONST_tCO2pTJ,$D26=INDEX(CONST_MonitoringApproach,3)) | BR26: =IF($D26="","",OR(AND($G26 = INDEX(CONST_torkNm3,1), $K26=INDEX(CONST_tCO2pTJOrtCO2pt,2)),AND($G26 = INDEX(CONST_torkNm3,2),$K26=INDEX(CONST_tCO2pTJOrtCO2pt,3)),$K26=INDEX(CONST_tCO2pTJOrtCO2pt,1),$D26=INDEX(CONST_MonitoringApproach,3))) | BS26: =IF($D26<>INDEX(CONST_MonitoringApproach,1),"", AND(COUNTA($E26,$G26,$K26)=3,COUNT($F26,$J26)=2,IF($K26=CONST_tCO2pTJ,ISNUMBER($H26),TRUE()))) | BT26: =IF($D26<>INDEX(CONST_MonitoringApproach,2),"", AND(COUNTA($E26,$G26,$K26)=3,COUNT($F26,$J26)=2,IF($K26=CONST_tCO2pTJ,ISNUMBER($H26),TRUE()))) | BU26: =IF($D26<>INDEX(CONST_MonitoringApproach,3),"",AND(COUNTA($E26,$G26)=2,COUNT($F26,$L26)=2)) | BW26: =AND(CNTR_HasEntriesA,D26="")
C27: 11 | D27: Mass Balance | E27: Slags | F27: -1000000 | G27: t | I27: =IF(E27="","",IF(G27="","", IF(G27=CONST_kNm3,CONST_GJpkNm3,CONST_GJpt))) | L27: 0.0003 | M27: =IF(D27<>INDEX(CONST_MonitoringApproach,3),"", IF(G27="","", CONST_tC&"/"&IF(G27="",CONST_t,G27))) | O27: % | Q27: % | S27: % | U27: % | AU27: =IF($D27="","",IF(BR27=FALSE(),CONST_ERR_Inconsistent,IF(COUNTIF(BS27:BU27,FALSE())>0,CONST_ERR_Incomplete,SUM(BD27:BF27)))) | AV27: =IF(ISNUMBER(AU27),SUM(BH27:BJ27),"") | AX27: =IF($D27="","",$F27*$H27/1000*(1-$R27/100)) | AY27: =IF($D27="","",$F27*$H27/1000*($R27/100)) | BA27: =CONST_CNTR_SUM_CO2 | BD27: =IF($D27<>INDEX(CONST_MonitoringApproach,1),"",$F27*IF($K27=CONST_tCO2pTJ,$H27/1000,1)*$J27*IF($N27="",1,$N27/100)*(1-$R27/100)) | BE27: =IF($D27<>INDEX(CONST_MonitoringApproach,2),"",$F27*IF($K27=CONST_tCO2pTJ,$H27/1000,1)*$J27*IF($P27="",1,$P27/100)*(1-$R27/100)) | BF27: =IF($D27<>INDEX(CONST_MonitoringApproach,3),"",$F27*$L27*3.664*(1-$R27/100)) | BH27: =IF($D27<>INDEX(CONST_MonitoringApproach,1),"",$F27*IF($K27=CONST_tCO2pTJ,$H27/1000,1)*$J27*IF($N27="",1,$N27/100)*($R27/100)) | BI27: =IF($D27<>INDEX(CONST_MonitoringApproach,2),"",$F27*IF($K27=CONST_tCO2pTJ,$H27/1000,1)*$J27*IF($P27="",1,$P27/100)*($R27/100)) | BJ27: =IF($D27<>INDEX(CONST_MonitoringApproach,3),"",$F27*$L27*3.664*($R27/100)) | BL27: =IF($D27="","",MATCH($D27,CONST_MonitoringApproach,0)=3) | BM27: =IF($D27="","",MATCH($D27,CONST_MonitoringApproach,0)<>3) | BN27: =IF($D27="","",MATCH($D27,CONST_MonitoringApproach,0)<>1) | BO27: =IF($D27="","",MATCH($D27,CONST_MonitoringApproach,0)<>2) | BP27: =OR($K27<>CONST_tCO2pTJ,$D27=INDEX(CONST_MonitoringApproach,3)) | BR27: =IF($D27="","",OR(AND($G27 = INDEX(CONST_torkNm3,1), $K27=INDEX(CONST_tCO2pTJOrtCO2pt,2)),AND($G27 = INDEX(CONST_torkNm3,2),$K27=INDEX(CONST_tCO2pTJOrtCO2pt,3)),$K27=INDEX(CONST_tCO2pTJOrtCO2pt,1),$D27=INDEX(CONST_MonitoringApproach,3))) | BS27: =IF($D27<>INDEX(CONST_MonitoringApproach,1),"", AND(COUNTA($E27,$G27,$K27)=3,COUNT($F27,$J27)=2,IF($K27=CONST_tCO2pTJ,ISNUMBER($H27),TRUE()))) | BT27: =IF($D27<>INDEX(CONST_MonitoringApproach,2),"", AND(COUNTA($E27,$G27,$K27)=3,COUNT($F27,$J27)=2,IF($K27=CONST_tCO2pTJ,ISNUMBER($H27),TRUE()))) | BU27: =IF($D27<>INDEX(CONST_MonitoringApproach,3),"",AND(COUNTA($E27,$G27)=2,COUNT($F27,$L27)=2)) | BW27: =AND(CNTR_HasEntriesA,D27="")
C28: 12 | I28: =IF(E28="","",IF(G28="","", IF(G28=CONST_kNm3,CONST_GJpkNm3,CONST_GJpt))) | M28: =IF(D28<>INDEX(CONST_MonitoringApproach,3),"", IF(G28="","", CONST_tC&"/"&IF(G28="",CONST_t,G28))) | O28: % | Q28: % | S28: % | U28: % | AU28: =IF($D28="","",IF(BR28=FALSE(),CONST_ERR_Inconsistent,IF(COUNTIF(BS28:BU28,FALSE())>0,CONST_ERR_Incomplete,SUM(BD28:BF28)))) | AV28: =IF(ISNUMBER(AU28),SUM(BH28:BJ28),"") | AX28: =IF($D28="","",$F28*$H28/1000*(1-$R28/100)) | AY28: =IF($D28="","",$F28*$H28/1000*($R28/100)) | BA28: =CONST_CNTR_SUM_CO2 | BD28: =IF($D28<>INDEX(CONST_MonitoringApproach,1),"",$F28*IF($K28=CONST_tCO2pTJ,$H28/1000,1)*$J28*IF($N28="",1,$N28/100)*(1-$R28/100)) | BE28: =IF($D28<>INDEX(CONST_MonitoringApproach,2),"",$F28*IF($K28=CONST_tCO2pTJ,$H28/1000,1)*$J28*IF($P28="",1,$P28/100)*(1-$R28/100)) | BF28: =IF($D28<>INDEX(CONST_MonitoringApproach,3),"",$F28*$L28*3.664*(1-$R28/100)) | BH28: =IF($D28<>INDEX(CONST_MonitoringApproach,1),"",$F28*IF($K28=CONST_tCO2pTJ,$H28/1000,1)*$J28*IF($N28="",1,$N28/100)*($R28/100)) | BI28: =IF($D28<>INDEX(CONST_MonitoringApproach,2),"",$F28*IF($K28=CONST_tCO2pTJ,$H28/1000,1)*$J28*IF($P28="",1,$P28/100)*($R28/100)) | BJ28: =IF($D28<>INDEX(CONST_MonitoringApproach,3),"",$F28*$L28*3.664*($R28/100)) | BL28: =IF($D28="","",MATCH($D28,CONST_MonitoringApproach,0)=3) | BM28: =IF($D28="","",MATCH($D28,CONST_MonitoringApproach,0)<>3) | BN28: =IF($D28="","",MATCH($D28,CONST_MonitoringApproach,0)<>1) | BO28: =IF($D28="","",MATCH($D28,CONST_MonitoringApproach,0)<>2) | BP28: =OR($K28<>CONST_tCO2pTJ,$D28=INDEX(CONST_MonitoringApproach,3)) | BR28: =IF($D28="","",OR(AND($G28 = INDEX(CONST_torkNm3,1), $K28=INDEX(CONST_tCO2pTJOrtCO2pt,2)),AND($G28 = INDEX(CONST_torkNm3,2),$K28=INDEX(CONST_tCO2pTJOrtCO2pt,3)),$K28=INDEX(CONST_tCO2pTJOrtCO2pt,1),$D28=INDEX(CONST_MonitoringApproach,3))) | BS28: =IF($D28<>INDEX(CONST_MonitoringApproach,1),"", AND(COUNTA($E28,$G28,$K28)=3,COUNT($F28,$J28)=2,IF($K28=CONST_tCO2pTJ,ISNUMBER($H28),TRUE()))) | BT28: =IF($D28<>INDEX(CONST_MonitoringApproach,2),"", AND(COUNTA($E28,$G28,$K28)=3,COUNT($F28,$J28)=2,IF($K28=CONST_tCO2pTJ,ISNUMBER($H28),TRUE()))) | BU28: =IF($D28<>INDEX(CONST_MonitoringApproach,3),"",AND(COUNTA($E28,$G28)=2,COUNT($F28,$L28)=2)) | BW28: =AND(CNTR_HasEntriesA,D28="")
C29: 13 | I29: =IF(E29="","",IF(G29="","", IF(G29=CONST_kNm3,CONST_GJpkNm3,CONST_GJpt))) | M29: =IF(D29<>INDEX(CONST_MonitoringApproach,3),"", IF(G29="","", CONST_tC&"/"&IF(G29="",CONST_t,G29))) | O29: % | Q29: % | S29: % | U29: % | AU29: =IF($D29="","",IF(BR29=FALSE(),CONST_ERR_Inconsistent,IF(COUNTIF(BS29:BU29,FALSE())>0,CONST_ERR_Incomplete,SUM(BD29:BF29)))) | AV29: =IF(ISNUMBER(AU29),SUM(BH29:BJ29),"") | AX29: =IF($D29="","",$F29*$H29/1000*(1-$R29/100)) | AY29: =IF($D29="","",$F29*$H29/1000*($R29/100)) | BA29: =CONST_CNTR_SUM_CO2 | BD29: =IF($D29<>INDEX(CONST_MonitoringApproach,1),"",$F29*IF($K29=CONST_tCO2pTJ,$H29/1000,1)*$J29*IF($N29="",1,$N29/100)*(1-$R29/100)) | BE29: =IF($D29<>INDEX(CONST_MonitoringApproach,2),"",$F29*IF($K29=CONST_tCO2pTJ,$H29/1000,1)*$J29*IF($P29="",1,$P29/100)*(1-$R29/100)) | BF29: =IF($D29<>INDEX(CONST_MonitoringApproach,3),"",$F29*$L29*3.664*(1-$R29/100)) | BH29: =IF($D29<>INDEX(CONST_MonitoringApproach,1),"",$F29*IF($K29=CONST_tCO2pTJ,$H29/1000,1)*$J29*IF($N29="",1,$N29/100)*($R29/100)) | BI29: =IF($D29<>INDEX(CONST_MonitoringApproach,2),"",$F29*IF($K29=CONST_tCO2pTJ,$H29/1000,1)*$J29*IF($P29="",1,$P29/100)*($R29/100)) | BJ29: =IF($D29<>INDEX(CONST_MonitoringApproach,3),"",$F29*$L29*3.664*($R29/100)) | BL29: =IF($D29="","",MATCH($D29,CONST_MonitoringApproach,0)=3) | BM29: =IF($D29="","",MATCH($D29,CONST_MonitoringApproach,0)<>3) | BN29: =IF($D29="","",MATCH($D29,CONST_MonitoringApproach,0)<>1) | BO29: =IF($D29="","",MATCH($D29,CONST_MonitoringApproach,0)<>2) | BP29: =OR($K29<>CONST_tCO2pTJ,$D29=INDEX(CONST_MonitoringApproach,3)) | BR29: =IF($D29="","",OR(AND($G29 = INDEX(CONST_torkNm3,1), $K29=INDEX(CONST_tCO2pTJOrtCO2pt,2)),AND($G29 = INDEX(CONST_torkNm3,2),$K29=INDEX(CONST_tCO2pTJOrtCO2pt,3)),$K29=INDEX(CONST_tCO2pTJOrtCO2pt,1),$D29=INDEX(CONST_MonitoringApproach,3))) | BS29: =IF($D29<>INDEX(CONST_MonitoringApproach,1),"", AND(COUNTA($E29,$G29,$K29)=3,COUNT($F29,$J29)=2,IF($K29=CONST_tCO2pTJ,ISNUMBER($H29),TRUE()))) | BT29: =IF($D29<>INDEX(CONST_MonitoringApproach,2),"", AND(COUNTA($E29,$G29,$K29)=3,COUNT($F29,$J29)=2,IF($K29=CONST_tCO2pTJ,ISNUMBER($H29),TRUE()))) | BU29: =IF($D29<>INDEX(CONST_MonitoringApproach,3),"",AND(COUNTA($E29,$G29)=2,COUNT($F29,$L29)=2)) | BW29: =AND(CNTR_HasEntriesA,D29="")
C30: 14 | I30: =IF(E30="","",IF(G30="","", IF(G30=CONST_kNm3,CONST_GJpkNm3,CONST_GJpt))) | M30: =IF(D30<>INDEX(CONST_MonitoringApproach,3),"", IF(G30="","", CONST_tC&"/"&IF(G30="",CONST_t,G30))) | O30: % | Q30: % | S30: % | U30: % | AU30: =IF($D30="","",IF(BR30=FALSE(),CONST_ERR_Inconsistent,IF(COUNTIF(BS30:BU30,FALSE())>0,CONST_ERR_Incomplete,SUM(BD30:BF30)))) | AV30: =IF(ISNUMBER(AU30),SUM(BH30:BJ30),"") | AX30: =IF($D30="","",$F30*$H30/1000*(1-$R30/100)) | AY30: =IF($D30="","",$F30*$H30/1000*($R30/100)) | BA30: =CONST_CNTR_SUM_CO2 | BD30: =IF($D30<>INDEX(CONST_MonitoringApproach,1),"",$F30*IF($K30=CONST_tCO2pTJ,$H30/1000,1)*$J30*IF($N30="",1,$N30/100)*(1-$R30/100)) | BE30: =IF($D30<>INDEX(CONST_MonitoringApproach,2),"",$F30*IF($K30=CONST_tCO2pTJ,$H30/1000,1)*$J30*IF($P30="",1,$P30/100)*(1-$R30/100)) | BF30: =IF($D30<>INDEX(CONST_MonitoringApproach,3),"",$F30*$L30*3.664*(1-$R30/100)) | BH30: =IF($D30<>INDEX(CONST_MonitoringApproach,1),"",$F30*IF($K30=CONST_tCO2pTJ,$H30/1000,1)*$J30*IF($N30="",1,$N30/100)*($R30/100)) | BI30: =IF($D30<>INDEX(CONST_MonitoringApproach,2),"",$F30*IF($K30=CONST_tCO2pTJ,$H30/1000,1)*$J30*IF($P30="",1,$P30/100)*($R30/100)) | BJ30: =IF($D30<>INDEX(CONST_MonitoringApproach,3),"",$F30*$L30*3.664*($R30/100)) | BL30: =IF($D30="","",MATCH($D30,CONST_MonitoringApproach,0)=3) | BM30: =IF($D30="","",MATCH($D30,CONST_MonitoringApproach,0)<>3) | BN30: =IF($D30="","",MATCH($D30,CONST_MonitoringApproach,0)<>1) | BO30: =IF($D30="","",MATCH($D30,CONST_MonitoringApproach,0)<>2) | BP30: =OR($K30<>CONST_tCO2pTJ,$D30=INDEX(CONST_MonitoringApproach,3)) | BR30: =IF($D30="","",OR(AND($G30 = INDEX(CONST_torkNm3,1), $K30=INDEX(CONST_tCO2pTJOrtCO2pt,2)),AND($G30 = INDEX(CONST_torkNm3,2),$K30=INDEX(CONST_tCO2pTJOrtCO2pt,3)),$K30=INDEX(CONST_tCO2pTJOrtCO2pt,1),$D30=INDEX(CONST_MonitoringApproach,3))) | BS30: =IF($D30<>INDEX(CONST_MonitoringApproach,1),"", AND(COUNTA($E30,$G30,$K30)=3,COUNT($F30,$J30)=2,IF($K30=CONST_tCO2pTJ,ISNUMBER($H30),TRUE()))) | BT30: =IF($D30<>INDEX(CONST_MonitoringApproach,2),"", AND(COUNTA($E30,$G30,$K30)=3,COUNT($F30,$J30)=2,IF($K30=CONST_tCO2pTJ,ISNUMBER($H30),TRUE()))) | BU30: =IF($D30<>INDEX(CONST_MonitoringApproach,3),"",AND(COUNTA($E30,$G30)=2,COUNT($F30,$L30)=2)) | BW30: =AND(CNTR_HasEntriesA,D30="")
C31: 15 | I31: =IF(E31="","",IF(G31="","", IF(G31=CONST_kNm3,CONST_GJpkNm3,CONST_GJpt))) | M31: =IF(D31<>INDEX(CONST_MonitoringApproach,3),"", IF(G31="","", CONST_tC&"/"&IF(G31="",CONST_t,G31))) | O31: % | Q31: % | S31: % | U31: % | AU31: =IF($D31="","",IF(BR31=FALSE(),CONST_ERR_Inconsistent,IF(COUNTIF(BS31:BU31,FALSE())>0,CONST_ERR_Incomplete,SUM(BD31:BF31)))) | AV31: =IF(ISNUMBER(AU31),SUM(BH31:BJ31),"") | AX31: =IF($D31="","",$F31*$H31/1000*(1-$R31/100)) | AY31: =IF($D31="","",$F31*$H31/1000*($R31/100)) | BA31: =CONST_CNTR_SUM_CO2 | BD31: =IF($D31<>INDEX(CONST_MonitoringApproach,1),"",$F31*IF($K31=CONST_tCO2pTJ,$H31/1000,1)*$J31*IF($N31="",1,$N31/100)*(1-$R31/100)) | BE31: =IF($D31<>INDEX(CONST_MonitoringApproach,2),"",$F31*IF($K31=CONST_tCO2pTJ,$H31/1000,1)*$J31*IF($P31="",1,$P31/100)*(1-$R31/100)) | BF31: =IF($D31<>INDEX(CONST_MonitoringApproach,3),"",$F31*$L31*3.664*(1-$R31/100)) | BH31: =IF($D31<>INDEX(CONST_MonitoringApproach,1),"",$F31*IF($K31=CONST_tCO2pTJ,$H31/1000,1)*$J31*IF($N31="",1,$N31/100)*($R31/100)) | BI31: =IF($D31<>INDEX(CONST_MonitoringApproach,2),"",$F31*IF($K31=CONST_tCO2pTJ,$H31/1000,1)*$J31*IF($P31="",1,$P31/100)*($R31/100)) | BJ31: =IF($D31<>INDEX(CONST_MonitoringApproach,3),"",$F31*$L31*3.664*($R31/100)) | BL31: =IF($D31="","",MATCH($D31,CONST_MonitoringApproach,0)=3) | BM31: =IF($D31="","",MATCH($D31,CONST_MonitoringApproach,0)<>3) | BN31: =IF($D31="","",MATCH($D31,CONST_MonitoringApproach,0)<>1) | BO31: =IF($D31="","",MATCH($D31,CONST_MonitoringApproach,0)<>2) | BP31: =OR($K31<>CONST_tCO2pTJ,$D31=INDEX(CONST_MonitoringApproach,3)) | BR31: =IF($D31="","",OR(AND($G31 = INDEX(CONST_torkNm3,1), $K31=INDEX(CONST_tCO2pTJOrtCO2pt,2)),AND($G31 = INDEX(CONST_torkNm3,2),$K31=INDEX(CONST_tCO2pTJOrtCO2pt,3)),$K31=INDEX(CONST_tCO2pTJOrtCO2pt,1),$D31=INDEX(CONST_MonitoringApproach,3))) | BS31: =IF($D31<>INDEX(CONST_MonitoringApproach,1),"", AND(COUNTA($E31,$G31,$K31)=3,COUNT($F31,$J31)=2,IF($K31=CONST_tCO2pTJ,ISNUMBER($H31),TRUE()))) | BT31: =IF($D31<>INDEX(CONST_MonitoringApproach,2),"", AND(COUNTA($E31,$G31,$K31)=3,COUNT($F31,$J31)=2,IF($K31=CONST_tCO2pTJ,ISNUMBER($H31),TRUE()))) | BU31: =IF($D31<>INDEX(CONST_MonitoringApproach,3),"",AND(COUNTA($E31,$G31)=2,COUNT($F31,$L31)=2)) | BW31: =AND(CNTR_HasEntriesA,D31="")
C32: 16 | I32: =IF(E32="","",IF(G32="","", IF(G32=CONST_kNm3,CONST_GJpkNm3,CONST_GJpt))) | M32: =IF(D32<>INDEX(CONST_MonitoringApproach,3),"", IF(G32="","", CONST_tC&"/"&IF(G32="",CONST_t,G32))) | O32: % | Q32: % | S32: % | U32: % | AU32: =IF($D32="","",IF(BR32=FALSE(),CONST_ERR_Inconsistent,IF(COUNTIF(BS32:BU32,FALSE())>0,CONST_ERR_Incomplete,SUM(BD32:BF32)))) | AV32: =IF(ISNUMBER(AU32),SUM(BH32:BJ32),"") | AX32: =IF($D32="","",$F32*$H32/1000*(1-$R32/100)) | AY32: =IF($D32="","",$F32*$H32/1000*($R32/100)) | BA32: =CONST_CNTR_SUM_CO2 | BD32: =IF($D32<>INDEX(CONST_MonitoringApproach,1),"",$F32*IF($K32=CONST_tCO2pTJ,$H32/1000,1)*$J32*IF($N32="",1,$N32/100)*(1-$R32/100)) | BE32: =IF($D32<>INDEX(CONST_MonitoringApproach,2),"",$F32*IF($K32=CONST_tCO2pTJ,$H32/1000,1)*$J32*IF($P32="",1,$P32/100)*(1-$R32/100)) | BF32: =IF($D32<>INDEX(CONST_MonitoringApproach,3),"",$F32*$L32*3.664*(1-$R32/100)) | BH32: =IF($D32<>INDEX(CONST_MonitoringApproach,1),"",$F32*IF($K32=CONST_tCO2pTJ,$H32/1000,1)*$J32*IF($N32="",1,$N32/100)*($R32/100)) | BI32: =IF($D32<>INDEX(CONST_MonitoringApproach,2),"",$F32*IF($K32=CONST_tCO2pTJ,$H32/1000,1)*$J32*IF($P32="",1,$P32/100)*($R32/100)) | BJ32: =IF($D32<>INDEX(CONST_MonitoringApproach,3),"",$F32*$L32*3.664*($R32/100)) | BL32: =IF($D32="","",MATCH($D32,CONST_MonitoringApproach,0)=3) | BM32: =IF($D32="","",MATCH($D32,CONST_MonitoringApproach,0)<>3) | BN32: =IF($D32="","",MATCH($D32,CONST_MonitoringApproach,0)<>1) | BO32: =IF($D32="","",MATCH($D32,CONST_MonitoringApproach,0)<>2) | BP32: =OR($K32<>CONST_tCO2pTJ,$D32=INDEX(CONST_MonitoringApproach,3)) | BR32: =IF($D32="","",OR(AND($G32 = INDEX(CONST_torkNm3,1), $K32=INDEX(CONST_tCO2pTJOrtCO2pt,2)),AND($G32 = INDEX(CONST_torkNm3,2),$K32=INDEX(CONST_tCO2pTJOrtCO2pt,3)),$K32=INDEX(CONST_tCO2pTJOrtCO2pt,1),$D32=INDEX(CONST_MonitoringApproach,3))) | BS32: =IF($D32<>INDEX(CONST_MonitoringApproach,1),"", AND(COUNTA($E32,$G32,$K32)=3,COUNT($F32,$J32)=2,IF($K32=CONST_tCO2pTJ,ISNUMBER($H32),TRUE()))) | BT32: =IF($D32<>INDEX(CONST_MonitoringApproach,2),"", AND(COUNTA($E32,$G32,$K32)=3,COUNT($F32,$J32)=2,IF($K32=CONST_tCO2pTJ,ISNUMBER($H32),TRUE()))) | BU32: =IF($D32<>INDEX(CONST_MonitoringApproach,3),"",AND(COUNTA($E32,$G32)=2,COUNT($F32,$L32)=2)) | BW32: =AND(CNTR_HasEntriesA,D32="")
C33: 17 | I33: =IF(E33="","",IF(G33="","", IF(G33=CONST_kNm3,CONST_GJpkNm3,CONST_GJpt))) | M33: =IF(D33<>INDEX(CONST_MonitoringApproach,3),"", IF(G33="","", CONST_tC&"/"&IF(G33="",CONST_t,G33))) | O33: % | Q33: % | S33: % | U33: % | AU33: =IF($D33="","",IF(BR33=FALSE(),CONST_ERR_Inconsistent,IF(COUNTIF(BS33:BU33,FALSE())>0,CONST_ERR_Incomplete,SUM(BD33:BF33)))) | AV33: =IF(ISNUMBER(AU33),SUM(BH33:BJ33),"") | AX33: =IF($D33="","",$F33*$H33/1000*(1-$R33/100)) | AY33: =IF($D33="","",$F33*$H33/1000*($R33/100)) | BA33: =CONST_CNTR_SUM_CO2 | BD33: =IF($D33<>INDEX(CONST_MonitoringApproach,1),"",$F33*IF($K33=CONST_tCO2pTJ,$H33/1000,1)*$J33*IF($N33="",1,$N33/100)*(1-$R33/100)) | BE33: =IF($D33<>INDEX(CONST_MonitoringApproach,2),"",$F33*IF($K33=CONST_tCO2pTJ,$H33/1000,1)*$J33*IF($P33="",1,$P33/100)*(1-$R33/100)) | BF33: =IF($D33<>INDEX(CONST_MonitoringApproach,3),"",$F33*$L33*3.664*(1-$R33/100)) | BH33: =IF($D33<>INDEX(CONST_MonitoringApproach,1),"",$F33*IF($K33=CONST_tCO2pTJ,$H33/1000,1)*$J33*IF($N33="",1,$N33/100)*($R33/100)) | BI33: =IF($D33<>INDEX(CONST_MonitoringApproach,2),"",$F33*IF($K33=CONST_tCO2pTJ,$H33/1000,1)*$J33*IF($P33="",1,$P33/100)*($R33/100)) | BJ33: =IF($D33<>INDEX(CONST_MonitoringApproach,3),"",$F33*$L33*3.664*($R33/100)) | BL33: =IF($D33="","",MATCH($D33,CONST_MonitoringApproach,0)=3) | BM33: =IF($D33="","",MATCH($D33,CONST_MonitoringApproach,0)<>3) | BN33: =IF($D33="","",MATCH($D33,CONST_MonitoringApproach,0)<>1) | BO33: =IF($D33="","",MATCH($D33,CONST_MonitoringApproach,0)<>2) | BP33: =OR($K33<>CONST_tCO2pTJ,$D33=INDEX(CONST_MonitoringApproach,3)) | BR33: =IF($D33="","",OR(AND($G33 = INDEX(CONST_torkNm3,1), $K33=INDEX(CONST_tCO2pTJOrtCO2pt,2)),AND($G33 = INDEX(CONST_torkNm3,2),$K33=INDEX(CONST_tCO2pTJOrtCO2pt,3)),$K33=INDEX(CONST_tCO2pTJOrtCO2pt,1),$D33=INDEX(CONST_MonitoringApproach,3))) | BS33: =IF($D33<>INDEX(CONST_MonitoringApproach,1),"", AND(COUNTA($E33,$G33,$K33)=3,COUNT($F33,$J33)=2,IF($K33=CONST_tCO2pTJ,ISNUMBER($H33),TRUE()))) | BT33: =IF($D33<>INDEX(CONST_MonitoringApproach,2),"", AND(COUNTA($E33,$G33,$K33)=3,COUNT($F33,$J33)=2,IF($K33=CONST_tCO2pTJ,ISNUMBER($H33),TRUE()))) | BU33: =IF($D33<>INDEX(CONST_MonitoringApproach,3),"",AND(COUNTA($E33,$G33)=2,COUNT($F33,$L33)=2)) | BW33: =AND(CNTR_HasEntriesA,D33="")
C34: 18 | I34: =IF(E34="","",IF(G34="","", IF(G34=CONST_kNm3,CONST_GJpkNm3,CONST_GJpt))) | M34: =IF(D34<>INDEX(CONST_MonitoringApproach,3),"", IF(G34="","", CONST_tC&"/"&IF(G34="",CONST_t,G34))) | O34: % | Q34: % | S34: % | U34: % | AU34: =IF($D34="","",IF(BR34=FALSE(),CONST_ERR_Inconsistent,IF(COUNTIF(BS34:BU34,FALSE())>0,CONST_ERR_Incomplete,SUM(BD34:BF34)))) | AV34: =IF(ISNUMBER(AU34),SUM(BH34:BJ34),"") | AX34: =IF($D34="","",$F34*$H34/1000*(1-$R34/100)) | AY34: =IF($D34="","",$F34*$H34/1000*($R34/100)) | BA34: =CONST_CNTR_SUM_CO2 | BD34: =IF($D34<>INDEX(CONST_MonitoringApproach,1),"",$F34*IF($K34=CONST_tCO2pTJ,$H34/1000,1)*$J34*IF($N34="",1,$N34/100)*(1-$R34/100)) | BE34: =IF($D34<>INDEX(CONST_MonitoringApproach,2),"",$F34*IF($K34=CONST_tCO2pTJ,$H34/1000,1)*$J34*IF($P34="",1,$P34/100)*(1-$R34/100)) | BF34: =IF($D34<>INDEX(CONST_MonitoringApproach,3),"",$F34*$L34*3.664*(1-$R34/100)) | BH34: =IF($D34<>INDEX(CONST_MonitoringApproach,1),"",$F34*IF($K34=CONST_tCO2pTJ,$H34/1000,1)*$J34*IF($N34="",1,$N34/100)*($R34/100)) | BI34: =IF($D34<>INDEX(CONST_MonitoringApproach,2),"",$F34*IF($K34=CONST_tCO2pTJ,$H34/1000,1)*$J34*IF($P34="",1,$P34/100)*($R34/100)) | BJ34: =IF($D34<>INDEX(CONST_MonitoringApproach,3),"",$F34*$L34*3.664*($R34/100)) | BL34: =IF($D34="","",MATCH($D34,CONST_MonitoringApproach,0)=3) | BM34: =IF($D34="","",MATCH($D34,CONST_MonitoringApproach,0)<>3) | BN34: =IF($D34="","",MATCH($D34,CONST_MonitoringApproach,0)<>1) | BO34: =IF($D34="","",MATCH($D34,CONST_MonitoringApproach,0)<>2) | BP34: =OR($K34<>CONST_tCO2pTJ,$D34=INDEX(CONST_MonitoringApproach,3)) | BR34: =IF($D34="","",OR(AND($G34 = INDEX(CONST_torkNm3,1), $K34=INDEX(CONST_tCO2pTJOrtCO2pt,2)),AND($G34 = INDEX(CONST_torkNm3,2),$K34=INDEX(CONST_tCO2pTJOrtCO2pt,3)),$K34=INDEX(CONST_tCO2pTJOrtCO2pt,1),$D34=INDEX(CONST_MonitoringApproach,3))) | BS34: =IF($D34<>INDEX(CONST_MonitoringApproach,1),"", AND(COUNTA($E34,$G34,$K34)=3,COUNT($F34,$J34)=2,IF($K34=CONST_tCO2pTJ,ISNUMBER($H34),TRUE()))) | BT34: =IF($D34<>INDEX(CONST_MonitoringApproach,2),"", AND(COUNTA($E34,$G34,$K34)=3,COUNT($F34,$J34)=2,IF($K34=CONST_tCO2pTJ,ISNUMBER($H34),TRUE()))) | BU34: =IF($D34<>INDEX(CONST_MonitoringApproach,3),"",AND(COUNTA($E34,$G34)=2,COUNT($F34,$L34)=2)) | BW34: =AND(CNTR_HasEntriesA,D34="")
C35: 19 | I35: =IF(E35="","",IF(G35="","", IF(G35=CONST_kNm3,CONST_GJpkNm3,CONST_GJpt))) | M35: =IF(D35<>INDEX(CONST_MonitoringApproach,3),"", IF(G35="","", CONST_tC&"/"&IF(G35="",CONST_t,G35))) | O35: % | Q35: % | S35: % | U35: % | AU35: =IF($D35="","",IF(BR35=FALSE(),CONST_ERR_Inconsistent,IF(COUNTIF(BS35:BU35,FALSE())>0,CONST_ERR_Incomplete,SUM(BD35:BF35)))) | AV35: =IF(ISNUMBER(AU35),SUM(BH35:BJ35),"") | AX35: =IF($D35="","",$F35*$H35/1000*(1-$R35/100)) | AY35: =IF($D35="","",$F35*$H35/1000*($R35/100)) | BA35: =CONST_CNTR_SUM_CO2 | BD35: =IF($D35<>INDEX(CONST_MonitoringApproach,1),"",$F35*IF($K35=CONST_tCO2pTJ,$H35/1000,1)*$J35*IF($N35="",1,$N35/100)*(1-$R35/100)) | BE35: =IF($D35<>INDEX(CONST_MonitoringApproach,2),"",$F35*IF($K35=CONST_tCO2pTJ,$H35/1000,1)*$J35*IF($P35="",1,$P35/100)*(1-$R35/100)) | BF35: =IF($D35<>INDEX(CONST_MonitoringApproach,3),"",$F35*$L35*3.664*(1-$R35/100)) | BH35: =IF($D35<>INDEX(CONST_MonitoringApproach,1),"",$F35*IF($K35=CONST_tCO2pTJ,$H35/1000,1)*$J35*IF($N35="",1,$N35/100)*($R35/100)) | BI35: =IF($D35<>INDEX(CONST_MonitoringApproach,2),"",$F35*IF($K35=CONST_tCO2pTJ,$H35/1000,1)*$J35*IF($P35="",1,$P35/100)*($R35/100)) | BJ35: =IF($D35<>INDEX(CONST_MonitoringApproach,3),"",$F35*$L35*3.664*($R35/100)) | BL35: =IF($D35="","",MATCH($D35,CONST_MonitoringApproach,0)=3) | BM35: =IF($D35="","",MATCH($D35,CONST_MonitoringApproach,0)<>3) | BN35: =IF($D35="","",MATCH($D35,CONST_MonitoringApproach,0)<>1) | BO35: =IF($D35="","",MATCH($D35,CONST_MonitoringApproach,0)<>2) | BP35: =OR($K35<>CONST_tCO2pTJ,$D35=INDEX(CONST_MonitoringApproach,3)) | BR35: =IF($D35="","",OR(AND($G35 = INDEX(CONST_torkNm3,1), $K35=INDEX(CONST_tCO2pTJOrtCO2pt,2)),AND($G35 = INDEX(CONST_torkNm3,2),$K35=INDEX(CONST_tCO2pTJOrtCO2pt,3)),$K35=INDEX(CONST_tCO2pTJOrtCO2pt,1),$D35=INDEX(CONST_MonitoringApproach,3))) | BS35: =IF($D35<>INDEX(CONST_MonitoringApproach,1),"", AND(COUNTA($E35,$G35,$K35)=3,COUNT($F35,$J35)=2,IF($K35=CONST_tCO2pTJ,ISNUMBER($H35),TRUE()))) | BT35: =IF($D35<>INDEX(CONST_MonitoringApproach,2),"", AND(COUNTA($E35,$G35,$K35)=3,COUNT($F35,$J35)=2,IF($K35=CONST_tCO2pTJ,ISNUMBER($H35),TRUE()))) | BU35: =IF($D35<>INDEX(CONST_MonitoringApproach,3),"",AND(COUNTA($E35,$G35)=2,COUNT($F35,$L35)=2)) | BW35: =AND(CNTR_HasEntriesA,D35="")
C36: 20 | I36: =IF(E36="","",IF(G36="","", IF(G36=CONST_kNm3,CONST_GJpkNm3,CONST_GJpt))) | M36: =IF(D36<>INDEX(CONST_MonitoringApproach,3),"", IF(G36="","", CONST_tC&"/"&IF(G36="",CONST_t,G36))) | O36: % | Q36: % | S36: % | U36: % | AU36: =IF($D36="","",IF(BR36=FALSE(),CONST_ERR_Inconsistent,IF(COUNTIF(BS36:BU36,FALSE())>0,CONST_ERR_Incomplete,SUM(BD36:BF36)))) | AV36: =IF(ISNUMBER(AU36),SUM(BH36:BJ36),"") | AX36: =IF($D36="","",$F36*$H36/1000*(1-$R36/100)) | AY36: =IF($D36="","",$F36*$H36/1000*($R36/100)) | BA36: =CONST_CNTR_SUM_CO2 | BD36: =IF($D36<>INDEX(CONST_MonitoringApproach,1),"",$F36*IF($K36=CONST_tCO2pTJ,$H36/1000,1)*$J36*IF($N36="",1,$N36/100)*(1-$R36/100)) | BE36: =IF($D36<>INDEX(CONST_MonitoringApproach,2),"",$F36*IF($K36=CONST_tCO2pTJ,$H36/1000,1)*$J36*IF($P36="",1,$P36/100)*(1-$R36/100)) | BF36: =IF($D36<>INDEX(CONST_MonitoringApproach,3),"",$F36*$L36*3.664*(1-$R36/100)) | BH36: =IF($D36<>INDEX(CONST_MonitoringApproach,1),"",$F36*IF($K36=CONST_tCO2pTJ,$H36/1000,1)*$J36*IF($N36="",1,$N36/100)*($R36/100)) | BI36: =IF($D36<>INDEX(CONST_MonitoringApproach,2),"",$F36*IF($K36=CONST_tCO2pTJ,$H36/1000,1)*$J36*IF($P36="",1,$P36/100)*($R36/100)) | BJ36: =IF($D36<>INDEX(CONST_MonitoringApproach,3),"",$F36*$L36*3.664*($R36/100)) | BL36: =IF($D36="","",MATCH($D36,CONST_MonitoringApproach,0)=3) | BM36: =IF($D36="","",MATCH($D36,CONST_MonitoringApproach,0)<>3) | BN36: =IF($D36="","",MATCH($D36,CONST_MonitoringApproach,0)<>1) | BO36: =IF($D36="","",MATCH($D36,CONST_MonitoringApproach,0)<>2) | BP36: =OR($K36<>CONST_tCO2pTJ,$D36=INDEX(CONST_MonitoringApproach,3)) | BR36: =IF($D36="","",OR(AND($G36 = INDEX(CONST_torkNm3,1), $K36=INDEX(CONST_tCO2pTJOrtCO2pt,2)),AND($G36 = INDEX(CONST_torkNm3,2),$K36=INDEX(CONST_tCO2pTJOrtCO2pt,3)),$K36=INDEX(CONST_tCO2pTJOrtCO2pt,1),$D36=INDEX(CONST_MonitoringApproach,3))) | BS36: =IF($D36<>INDEX(CONST_MonitoringApproach,1),"", AND(COUNTA($E36,$G36,$K36)=3,COUNT($F36,$J36)=2,IF($K36=CONST_tCO2pTJ,ISNUMBER($H36),TRUE()))) | BT36: =IF($D36<>INDEX(CONST_MonitoringApproach,2),"", AND(COUNTA($E36,$G36,$K36)=3,COUNT($F36,$J36)=2,IF($K36=CONST_tCO2pTJ,ISNUMBER($H36),TRUE()))) | BU36: =IF($D36<>INDEX(CONST_MonitoringApproach,3),"",AND(COUNTA($E36,$G36)=2,COUNT($F36,$L36)=2)) | BW36: =AND(CNTR_HasEntriesA,D36="")
C37: 21 | I37: =IF(E37="","",IF(G37="","", IF(G37=CONST_kNm3,CONST_GJpkNm3,CONST_GJpt))) | M37: =IF(D37<>INDEX(CONST_MonitoringApproach,3),"", IF(G37="","", CONST_tC&"/"&IF(G37="",CONST_t,G37))) | O37: % | Q37: % | S37: % | U37: % | AU37: =IF($D37="","",IF(BR37=FALSE(),CONST_ERR_Inconsistent,IF(COUNTIF(BS37:BU37,FALSE())>0,CONST_ERR_Incomplete,SUM(BD37:BF37)))) | AV37: =IF(ISNUMBER(AU37),SUM(BH37:BJ37),"") | AX37: =IF($D37="","",$F37*$H37/1000*(1-$R37/100)) | AY37: =IF($D37="","",$F37*$H37/1000*($R37/100)) | BA37: =CONST_CNTR_SUM_CO2 | BD37: =IF($D37<>INDEX(CONST_MonitoringApproach,1),"",$F37*IF($K37=CONST_tCO2pTJ,$H37/1000,1)*$J37*IF($N37="",1,$N37/100)*(1-$R37/100)) | BE37: =IF($D37<>INDEX(CONST_MonitoringApproach,2),"",$F37*IF($K37=CONST_tCO2pTJ,$H37/1000,1)*$J37*IF($P37="",1,$P37/100)*(1-$R37/100)) | BF37: =IF($D37<>INDEX(CONST_MonitoringApproach,3),"",$F37*$L37*3.664*(1-$R37/100)) | BH37: =IF($D37<>INDEX(CONST_MonitoringApproach,1),"",$F37*IF($K37=CONST_tCO2pTJ,$H37/1000,1)*$J37*IF($N37="",1,$N37/100)*($R37/100)) | BI37: =IF($D37<>INDEX(CONST_MonitoringApproach,2),"",$F37*IF($K37=CONST_tCO2pTJ,$H37/1000,1)*$J37*IF($P37="",1,$P37/100)*($R37/100)) | BJ37: =IF($D37<>INDEX(CONST_MonitoringApproach,3),"",$F37*$L37*3.664*($R37/100)) | BL37: =IF($D37="","",MATCH($D37,CONST_MonitoringApproach,0)=3) | BM37: =IF($D37="","",MATCH($D37,CONST_MonitoringApproach,0)<>3) | BN37: =IF($D37="","",MATCH($D37,CONST_MonitoringApproach,0)<>1) | BO37: =IF($D37="","",MATCH($D37,CONST_MonitoringApproach,0)<>2) | BP37: =OR($K37<>CONST_tCO2pTJ,$D37=INDEX(CONST_MonitoringApproach,3)) | BR37: =IF($D37="","",OR(AND($G37 = INDEX(CONST_torkNm3,1), $K37=INDEX(CONST_tCO2pTJOrtCO2pt,2)),AND($G37 = INDEX(CONST_torkNm3,2),$K37=INDEX(CONST_tCO2pTJOrtCO2pt,3)),$K37=INDEX(CONST_tCO2pTJOrtCO2pt,1),$D37=INDEX(CONST_MonitoringApproach,3))) | BS37: =IF($D37<>INDEX(CONST_MonitoringApproach,1),"", AND(COUNTA($E37,$G37,$K37)=3,COUNT($F37,$J37)=2,IF($K37=CONST_tCO2pTJ,ISNUMBER($H37),TRUE()))) | BT37: =IF($D37<>INDEX(CONST_MonitoringApproach,2),"", AND(COUNTA($E37,$G37,$K37)=3,COUNT($F37,$J37)=2,IF($K37=CONST_tCO2pTJ,ISNUMBER($H37),TRUE()))) | BU37: =IF($D37<>INDEX(CONST_MonitoringApproach,3),"",AND(COUNTA($E37,$G37)=2,COUNT($F37,$L37)=2)) | BW37: =AND(CNTR_HasEntriesA,D37="")
C38: 22 | I38: =IF(E38="","",IF(G38="","", IF(G38=CONST_kNm3,CONST_GJpkNm3,CONST_GJpt))) | M38: =IF(D38<>INDEX(CONST_MonitoringApproach,3),"", IF(G38="","", CONST_tC&"/"&IF(G38="",CONST_t,G38))) | O38: % | Q38: % | S38: % | U38: % | AU38: =IF($D38="","",IF(BR38=FALSE(),CONST_ERR_Inconsistent,IF(COUNTIF(BS38:BU38,FALSE())>0,CONST_ERR_Incomplete,SUM(BD38:BF38)))) | AV38: =IF(ISNUMBER(AU38),SUM(BH38:BJ38),"") | AX38: =IF($D38="","",$F38*$H38/1000*(1-$R38/100)) | AY38: =IF($D38="","",$F38*$H38/1000*($R38/100)) | BA38: =CONST_CNTR_SUM_CO2 | BD38: =IF($D38<>INDEX(CONST_MonitoringApproach,1),"",$F38*IF($K38=CONST_tCO2pTJ,$H38/1000,1)*$J38*IF($N38="",1,$N38/100)*(1-$R38/100)) | BE38: =IF($D38<>INDEX(CONST_MonitoringApproach,2),"",$F38*IF($K38=CONST_tCO2pTJ,$H38/1000,1)*$J38*IF($P38="",1,$P38/100)*(1-$R38/100)) | BF38: =IF($D38<>INDEX(CONST_MonitoringApproach,3),"",$F38*$L38*3.664*(1-$R38/100)) | BH38: =IF($D38<>INDEX(CONST_MonitoringApproach,1),"",$F38*IF($K38=CONST_tCO2pTJ,$H38/1000,1)*$J38*IF($N38="",1,$N38/100)*($R38/100)) | BI38: =IF($D38<>INDEX(CONST_MonitoringApproach,2),"",$F38*IF($K38=CONST_tCO2pTJ,$H38/1000,1)*$J38*IF($P38="",1,$P38/100)*($R38/100)) | BJ38: =IF($D38<>INDEX(CONST_MonitoringApproach,3),"",$F38*$L38*3.664*($R38/100)) | BL38: =IF($D38="","",MATCH($D38,CONST_MonitoringApproach,0)=3) | BM38: =IF($D38="","",MATCH($D38,CONST_MonitoringApproach,0)<>3) | BN38: =IF($D38="","",MATCH($D38,CONST_MonitoringApproach,0)<>1) | BO38: =IF($D38="","",MATCH($D38,CONST_MonitoringApproach,0)<>2) | BP38: =OR($K38<>CONST_tCO2pTJ,$D38=INDEX(CONST_MonitoringApproach,3)) | BR38: =IF($D38="","",OR(AND($G38 = INDEX(CONST_torkNm3,1), $K38=INDEX(CONST_tCO2pTJOrtCO2pt,2)),AND($G38 = INDEX(CONST_torkNm3,2),$K38=INDEX(CONST_tCO2pTJOrtCO2pt,3)),$K38=INDEX(CONST_tCO2pTJOrtCO2pt,1),$D38=INDEX(CONST_MonitoringApproach,3))) | BS38: =IF($D38<>INDEX(CONST_MonitoringApproach,1),"", AND(COUNTA($E38,$G38,$K38)=3,COUNT($F38,$J38)=2,IF($K38=CONST_tCO2pTJ,ISNUMBER($H38),TRUE()))) | BT38: =IF($D38<>INDEX(CONST_MonitoringApproach,2),"", AND(COUNTA($E38,$G38,$K38)=3,COUNT($F38,$J38)=2,IF($K38=CONST_tCO2pTJ,ISNUMBER($H38),TRUE()))) | BU38: =IF($D38<>INDEX(CONST_MonitoringApproach,3),"",AND(COUNTA($E38,$G38)=2,COUNT($F38,$L38)=2)) | BW38: =AND(CNTR_HasEntriesA,D38="")
C39: 23 | I39: =IF(E39="","",IF(G39="","", IF(G39=CONST_kNm3,CONST_GJpkNm3,CONST_GJpt))) | M39: =IF(D39<>INDEX(CONST_MonitoringApproach,3),"", IF(G39="","", CONST_tC&"/"&IF(G39="",CONST_t,G39))) | O39: % | Q39: % | S39: % | U39: % | AU39: =IF($D39="","",IF(BR39=FALSE(),CONST_ERR_Inconsistent,IF(COUNTIF(BS39:BU39,FALSE())>0,CONST_ERR_Incomplete,SUM(BD39:BF39)))) | AV39: =IF(ISNUMBER(AU39),SUM(BH39:BJ39),"") | AX39: =IF($D39="","",$F39*$H39/1000*(1-$R39/100)) | AY39: =IF($D39="","",$F39*$H39/1000*($R39/100)) | BA39: =CONST_CNTR_SUM_CO2 | BD39: =IF($D39<>INDEX(CONST_MonitoringApproach,1),"",$F39*IF($K39=CONST_tCO2pTJ,$H39/1000,1)*$J39*IF($N39="",1,$N39/100)*(1-$R39/100)) | BE39: =IF($D39<>INDEX(CONST_MonitoringApproach,2),"",$F39*IF($K39=CONST_tCO2pTJ,$H39/1000,1)*$J39*IF($P39="",1,$P39/100)*(1-$R39/100)) | BF39: =IF($D39<>INDEX(CONST_MonitoringApproach,3),"",$F39*$L39*3.664*(1-$R39/100)) | BH39: =IF($D39<>INDEX(CONST_MonitoringApproach,1),"",$F39*IF($K39=CONST_tCO2pTJ,$H39/1000,1)*$J39*IF($N39="",1,$N39/100)*($R39/100)) | BI39: =IF($D39<>INDEX(CONST_MonitoringApproach,2),"",$F39*IF($K39=CONST_tCO2pTJ,$H39/1000,1)*$J39*IF($P39="",1,$P39/100)*($R39/100)) | BJ39: =IF($D39<>INDEX(CONST_MonitoringApproach,3),"",$F39*$L39*3.664*($R39/100)) | BL39: =IF($D39="","",MATCH($D39,CONST_MonitoringApproach,0)=3) | BM39: =IF($D39="","",MATCH($D39,CONST_MonitoringApproach,0)<>3) | BN39: =IF($D39="","",MATCH($D39,CONST_MonitoringApproach,0)<>1) | BO39: =IF($D39="","",MATCH($D39,CONST_MonitoringApproach,0)<>2) | BP39: =OR($K39<>CONST_tCO2pTJ,$D39=INDEX(CONST_MonitoringApproach,3)) | BR39: =IF($D39="","",OR(AND($G39 = INDEX(CONST_torkNm3,1), $K39=INDEX(CONST_tCO2pTJOrtCO2pt,2)),AND($G39 = INDEX(CONST_torkNm3,2),$K39=INDEX(CONST_tCO2pTJOrtCO2pt,3)),$K39=INDEX(CONST_tCO2pTJOrtCO2pt,1),$D39=INDEX(CONST_MonitoringApproach,3))) | BS39: =IF($D39<>INDEX(CONST_MonitoringApproach,1),"", AND(COUNTA($E39,$G39,$K39)=3,COUNT($F39,$J39)=2,IF($K39=CONST_tCO2pTJ,ISNUMBER($H39),TRUE()))) | BT39: =IF($D39<>INDEX(CONST_MonitoringApproach,2),"", AND(COUNTA($E39,$G39,$K39)=3,COUNT($F39,$J39)=2,IF($K39=CONST_tCO2pTJ,ISNUMBER($H39),TRUE()))) | BU39: =IF($D39<>INDEX(CONST_MonitoringApproach,3),"",AND(COUNTA($E39,$G39)=2,COUNT($F39,$L39)=2)) | BW39: =AND(CNTR_HasEntriesA,D39="")
... C91: 75 | I91: =IF(E91="","",IF(G91="","", IF(G91=CONST_kNm3,CONST_GJpkNm3,CONST_GJpt))) | M91: =IF(D91<>INDEX(CONST_MonitoringApproach,3),"", IF(G91="","", CONST_tC&"/"&IF(G91="",CONST_t,G91))) | O91: % | Q91: % | S91: % | U91: % | AU91: =IF($D91="","",IF(BR91=FALSE(),CONST_ERR_Inconsistent,IF(COUNTIF(BS91:BU91,FALSE())>0,CONST_ERR_Incomplete,SUM(BD91:BF91)))) | AV91: =IF(ISNUMBER(AU91),SUM(BH91:BJ91),"") | AX91: =IF($D91="","",$F91*$H91/1000*(1-$R91/100)) | AY91: =IF($D91="","",$F91*$H91/1000*($R91/100)) | BA91: =CONST_CNTR_SUM_CO2 | BD91: =IF($D91<>INDEX(CONST_MonitoringApproach,1),"",$F91*IF($K91=CONST_tCO2pTJ,$H91/1000,1)*$J91*IF($N91="",1,$N91/100)*(1-$R91/100)) | BE91: =IF($D91<>INDEX(CONST_MonitoringApproach,2),"",$F91*IF($K91=CONST_tCO2pTJ,$H91/1000,1)*$J91*IF($P91="",1,$P91/100)*(1-$R91/100)) | BF91: =IF($D91<>INDEX(CONST_MonitoringApproach,3),"",$F91*$L91*3.664*(1-$R91/100)) | BH91: =IF($D91<>INDEX(CONST_MonitoringApproach,1),"",$F91*IF($K91=CONST_tCO2pTJ,$H91/1000,1)*$J91*IF($N91="",1,$N91/100)*($R91/100)) | BI91: =IF($D91<>INDEX(CONST_MonitoringApproach,2),"",$F91*IF($K91=CONST_tCO2pTJ,$H91/1000,1)*$J91*IF($P91="",1,$P91/100)*($R91/100)) | BJ91: =IF($D91<>INDEX(CONST_MonitoringApproach,3),"",$F91*$L91*3.664*($R91/100)) | BL91: =IF($D91="","",MATCH($D91,CONST_MonitoringApproach,0)=3) | BM91: =IF($D91="","",MATCH($D91,CONST_MonitoringApproach,0)<>3) | BN91: =IF($D91="","",MATCH($D91,CONST_MonitoringApproach,0)<>1) | BO91: =IF($D91="","",MATCH($D91,CONST_MonitoringApproach,0)<>2) | BP91: =OR($K91<>CONST_tCO2pTJ,$D91=INDEX(CONST_MonitoringApproach,3)) | BR91: =IF($D91="","",OR(AND($G91 = INDEX(CONST_torkNm3,1), $K91=INDEX(CONST_tCO2pTJOrtCO2pt,2)),AND($G91 = INDEX(CONST_torkNm3,2),$K91=INDEX(CONST_tCO2pTJOrtCO2pt,3)),$K91=INDEX(CONST_tCO2pTJOrtCO2pt,1),$D91=INDEX(CONST_MonitoringApproach,3))) | BS91: =IF($D91<>INDEX(CONST_MonitoringApproach,1),"", AND(COUNTA($E91,$G91,$K91)=3,COUNT($F91,$J91)=2,IF($K91=CONST_tCO2pTJ,ISNUMBER($H91),TRUE()))) | BT91: =IF($D91<>INDEX(CONST_MonitoringApproach,2),"", AND(COUNTA($E91,$G91,$K91)=3,COUNT($F91,$J91)=2,IF($K91=CONST_tCO2pTJ,ISNUMBER($H91),TRUE()))) | BU91: =IF($D91<>INDEX(CONST_MonitoringApproach,3),"",AND(COUNTA($E91,$G91)=2,COUNT($F91,$L91)=2)) | BW91: =AND(CNTR_HasEntriesA,D91="")
A95: 2 | C95: (b) | D95: =Translations!$B$1962 | BA95: =D95 | BE95: Method A | BH95: Method B | BK95: Cond.format
C96: =Translations!$B$131 | D96: =Translations!$B$132 | E96: =Translations!$B$1963 | F96: =Translations!$B$134 | G96: =Translations!$B$135 | H96: =Translations!$B$136 | I96: =Translations!$B$137 | J96: =Translations!$B$138 | K96: =Translations!$B$139 | L96: =Translations!$B$140 | M96: =Translations!$B$141 | N96: =Translations!$B$142 | O96: =Translations!$B$143 | P96: =Translations!$B$144 | Q96: =Translations!$B$145 | R96: =Translations!$B$146 | S96: =Translations!$B$147 | T96: non-sust. BioC | U96: non-sust. BioC Unit | V96: =Translations!$B$150 | W96: =Translations!$B$151 | X96: =Translations!$B$152 | Y96: =Translations!$B$153 | Z96: =Translations!$B$1959 | AA96: =Translations!$B$1960 | AB96: Flue gas (total) | AC96: Flue gas (total), Unit | AD96: =Translations!$B$158 | AE96: =Translations!$B$159 | AF96: =Translations!$B$1961 | AG96: =Translations!$B$161 | AH96: =Translations!$B$162 | AI96: =Translations!$B$163 | AJ96: =Translations!$B$164 | AK96: =Translations!$B$165 | AL96: =Translations!$B$166 | AM96: =Translations!$B$167 | AN96: =Translations!$B$168 | AO96: =Translations!$B$169 | AP96: =Translations!$B$170 | AQ96: =Translations!$B$171 | AR96: =Translations!$B$172 | AS96: =Translations!$B$173 | AT96: =Translations!$B$174 | AU96: =Translations!$B$175 | AV96: =Translations!$B$176 | AW96: CO2e non-sust. bio (t) | AX96: =Translations!$B$178 | AY96: =Translations!$B$179 | BE96: CF4 | BF96: C2F6 | BH96: CF4 | BI96: C2F6 | BK96: CF4 | BL96: cond. Rows
C97: =Translations!$B$202 | D97: =Translations!$B$647 | E97: =Translations!$B$204 | F97: 500000 | G97: =CONST_t | AG97: 2.17 | AH97: 1.23 | AI97: 0.146 | AM97: 0.122 | AN97: =IF($D97="","",IF(MATCH($D97,CONST_PFCSlopeOrOvervoltage,0)=1,BE97,BH97)) | AO97: =IF(AN97="","",SUM(AN97)*AM97) | AP97: =IF($D97="","",CONST_GWP_CF4) | AQ97: =IF($D97="","",CONST_GWP_C2F6) | AR97: =IF($D97="","",SUM(AN97)*AP97) | AS97: =IF($D97="","",AO97*AQ97) | AT97: 0.98 | AU97: =IF($D97="","",SUM(AR97:AS97)/IF(AT97="",1,AT97)) | BE97: =F97*AG97*AH97*AI97/1000 | BF97: =IF(BE97="","",$AM97) | BH97: =IFERROR(F97*(AJ97/AK97)*AL97/1000,CONST_ERR_Incomplete) | BI97: =IF(BH97="","",$AM97)
C98: 1 | G98: =CONST_t | AN98: =IF($D98="","",IF(MATCH($D98,CONST_PFCSlopeOrOvervoltage,0)=1,BE98,BH98)) | AO98: =IF(AN98="","",SUM(AN98)*AM98) | AP98: =IF($D98="","",CONST_GWP_CF4) | AQ98: =IF($D98="","",CONST_GWP_C2F6) | AR98: =IF($D98="","",SUM(AN98)*AP98) | AS98: =IF($D98="","",AO98*AQ98) | AU98: =IF($D98="","",SUM(AR98:AS98)/IF(AT98="",1,AT98)) | BA98: =CONST_CNTR_SUM_PFC | BE98: =F98*AG98*AH98*AI98/1000 | BF98: =IF(BE98="","",$AM98) | BH98: =IFERROR(F98*(AJ98/AK98)*AL98/1000,CONST_ERR_Incomplete) | BI98: =IF(BH98="","",$AM98) | BK98: =IF(D98="","",MATCH(D98,CONST_PFCSlopeOrOvervoltage,0)) | BL98: =D98="" | BW98: =AND(CNTR_HasEntriesA,COUNTIF(A_InstData!$AH$62:$AH$71,TRUE())=0)
C99: 2 | G99: =CONST_t | AN99: =IF($D99="","",IF(MATCH($D99,CONST_PFCSlopeOrOvervoltage,0)=1,BE99,BH99)) | AO99: =IF(AN99="","",SUM(AN99)*AM99) | AP99: =IF($D99="","",CONST_GWP_CF4) | AQ99: =IF($D99="","",CONST_GWP_C2F6) | AR99: =IF($D99="","",SUM(AN99)*AP99) | AS99: =IF($D99="","",AO99*AQ99) | AU99: =IF($D99="","",SUM(AR99:AS99)/IF(AT99="",1,AT99)) | BA99: =CONST_CNTR_SUM_PFC | BE99: =F99*AG99*AH99*AI99/1000 | BF99: =IF(BE99="","",$AM99) | BH99: =IFERROR(F99*(AJ99/AK99)*AL99/1000,CONST_ERR_Incomplete) | BI99: =IF(BH99="","",$AM99) | BK99: =IF(D99="","",MATCH(D99,CONST_PFCSlopeOrOvervoltage,0)) | BL99: =D99="" | BW99: =AND(CNTR_HasEntriesA,COUNTIF(A_InstData!$AH$62:$AH$71,TRUE())=0)
C100: 3 | G100: =CONST_t | AN100: =IF($D100="","",IF(MATCH($D100,CONST_PFCSlopeOrOvervoltage,0)=1,BE100,BH100)) | AO100: =IF(AN100="","",SUM(AN100)*AM100) | AP100: =IF($D100="","",CONST_GWP_CF4) | AQ100: =IF($D100="","",CONST_GWP_C2F6) | AR100: =IF($D100="","",SUM(AN100)*AP100) | AS100: =IF($D100="","",AO100*AQ100) | AU100: =IF($D100="","",SUM(AR100:AS100)/IF(AT100="",1,AT100)) | BA100: =CONST_CNTR_SUM_PFC | BE100: =F100*AG100*AH100*AI100/1000 | BF100: =IF(BE100="","",$AM100) | BH100: =IFERROR(F100*(AJ100/AK100)*AL100/1000,CONST_ERR_Incomplete) | BI100: =IF(BH100="","",$AM100) | BK100: =IF(D100="","",MATCH(D100,CONST_PFCSlopeOrOvervoltage,0)) | BL100: =D100="" | BW100: =AND(CNTR_HasEntriesA,COUNTIF(A_InstData!$AH$62:$AH$71,TRUE())=0)
C101: 4 | G101: =CONST_t | AN101: =IF($D101="","",IF(MATCH($D101,CONST_PFCSlopeOrOvervoltage,0)=1,BE101,BH101)) | AO101: =IF(AN101="","",SUM(AN101)*AM101) | AP101: =IF($D101="","",CONST_GWP_CF4) | AQ101: =IF($D101="","",CONST_GWP_C2F6) | AR101: =IF($D101="","",SUM(AN101)*AP101) | AS101: =IF($D101="","",AO101*AQ101) | AU101: =IF($D101="","",SUM(AR101:AS101)/IF(AT101="",1,AT101)) | BA101: =CONST_CNTR_SUM_PFC | BE101: =F101*AG101*AH101*AI101/1000 | BF101: =IF(BE101="","",$AM101) | BH101: =IFERROR(F101*(AJ101/AK101)*AL101/1000,CONST_ERR_Incomplete) | BI101: =IF(BH101="","",$AM101) | BK101: =IF(D101="","",MATCH(D101,CONST_PFCSlopeOrOvervoltage,0)) | BL101: =D101="" | BW101: =AND(CNTR_HasEntriesA,COUNTIF(A_InstData!$AH$62:$AH$71,TRUE())=0)
C102: 5 | G102: =CONST_t | AN102: =IF($D102="","",IF(MATCH($D102,CONST_PFCSlopeOrOvervoltage,0)=1,BE102,BH102)) | AO102: =IF(AN102="","",SUM(AN102)*AM102) | AP102: =IF($D102="","",CONST_GWP_CF4) | AQ102: =IF($D102="","",CONST_GWP_C2F6) | AR102: =IF($D102="","",SUM(AN102)*AP102) | AS102: =IF($D102="","",AO102*AQ102) | AU102: =IF($D102="","",SUM(AR102:AS102)/IF(AT102="",1,AT102)) | BA102: =CONST_CNTR_SUM_PFC | BE102: =F102*AG102*AH102*AI102/1000 | BF102: =IF(BE102="","",$AM102) | BH102: =IFERROR(F102*(AJ102/AK102)*AL102/1000,CONST_ERR_Incomplete) | BI102: =IF(BH102="","",$AM102) | BK102: =IF(D102="","",MATCH(D102,CONST_PFCSlopeOrOvervoltage,0)) | BL102: =D102="" | BW102: =AND(CNTR_HasEntriesA,COUNTIF(A_InstData!$AH$62:$AH$71,TRUE())=0)
C103: 6 | G103: =CONST_t | AN103: =IF($D103="","",IF(MATCH($D103,CONST_PFCSlopeOrOvervoltage,0)=1,BE103,BH103)) | AO103: =IF(AN103="","",SUM(AN103)*AM103) | AP103: =IF($D103="","",CONST_GWP_CF4) | AQ103: =IF($D103="","",CONST_GWP_C2F6) | AR103: =IF($D103="","",SUM(AN103)*AP103) | AS103: =IF($D103="","",AO103*AQ103) | AU103: =IF($D103="","",SUM(AR103:AS103)/IF(AT103="",1,AT103)) | BA103: =CONST_CNTR_SUM_PFC | BE103: =F103*AG103*AH103*AI103/1000 | BF103: =IF(BE103="","",$AM103) | BH103: =IFERROR(F103*(AJ103/AK103)*AL103/1000,CONST_ERR_Incomplete) | BI103: =IF(BH103="","",$AM103) | BK103: =IF(D103="","",MATCH(D103,CONST_PFCSlopeOrOvervoltage,0)) | BL103: =D103="" | BW103: =AND(CNTR_HasEntriesA,COUNTIF(A_InstData!$AH$62:$AH$71,TRUE())=0)
C104: 7 | G104: =CONST_t | AN104: =IF($D104="","",IF(MATCH($D104,CONST_PFCSlopeOrOvervoltage,0)=1,BE104,BH104)) | AO104: =IF(AN104="","",SUM(AN104)*AM104) | AP104: =IF($D104="","",CONST_GWP_CF4) | AQ104: =IF($D104="","",CONST_GWP_C2F6) | AR104: =IF($D104="","",SUM(AN104)*AP104) | AS104: =IF($D104="","",AO104*AQ104) | AU104: =IF($D104="","",SUM(AR104:AS104)/IF(AT104="",1,AT104)) | BA104: =CONST_CNTR_SUM_PFC | BE104: =F104*AG104*AH104*AI104/1000 | BF104: =IF(BE104="","",$AM104) | BH104: =IFERROR(F104*(AJ104/AK104)*AL104/1000,CONST_ERR_Incomplete) | BI104: =IF(BH104="","",$AM104) | BK104: =IF(D104="","",MATCH(D104,CONST_PFCSlopeOrOvervoltage,0)) | BL104: =D104="" | BW104: =AND(CNTR_HasEntriesA,COUNTIF(A_InstData!$AH$62:$AH$71,TRUE())=0)
C105: 8 | G105: =CONST_t | AN105: =IF($D105="","",IF(MATCH($D105,CONST_PFCSlopeOrOvervoltage,0)=1,BE105,BH105)) | AO105: =IF(AN105="","",SUM(AN105)*AM105) | AP105: =IF($D105="","",CONST_GWP_CF4) | AQ105: =IF($D105="","",CONST_GWP_C2F6) | AR105: =IF($D105="","",SUM(AN105)*AP105) | AS105: =IF($D105="","",AO105*AQ105) | AU105: =IF($D105="","",SUM(AR105:AS105)/IF(AT105="",1,AT105)) | BA105: =CONST_CNTR_SUM_PFC | BE105: =F105*AG105*AH105*AI105/1000 | BF105: =IF(BE105="","",$AM105) | BH105: =IFERROR(F105*(AJ105/AK105)*AL105/1000,CONST_ERR_Incomplete) | BI105: =IF(BH105="","",$AM105) | BK105: =IF(D105="","",MATCH(D105,CONST_PFCSlopeOrOvervoltage,0)) | BL105: =D105="" | BW105: =AND(CNTR_HasEntriesA,COUNTIF(A_InstData!$AH$62:$AH$71,TRUE())=0)
C106: 9 | G106: =CONST_t | AN106: =IF($D106="","",IF(MATCH($D106,CONST_PFCSlopeOrOvervoltage,0)=1,BE106,BH106)) | AO106: =IF(AN106="","",SUM(AN106)*AM106) | AP106: =IF($D106="","",CONST_GWP_CF4) | AQ106: =IF($D106="","",CONST_GWP_C2F6) | AR106: =IF($D106="","",SUM(AN106)*AP106) | AS106: =IF($D106="","",AO106*AQ106) | AU106: =IF($D106="","",SUM(AR106:AS106)/IF(AT106="",1,AT106)) | BA106: =CONST_CNTR_SUM_PFC | BE106: =F106*AG106*AH106*AI106/1000 | BF106: =IF(BE106="","",$AM106) | BH106: =IFERROR(F106*(AJ106/AK106)*AL106/1000,CONST_ERR_Incomplete) | BI106: =IF(BH106="","",$AM106) | BK106: =IF(D106="","",MATCH(D106,CONST_PFCSlopeOrOvervoltage,0)) | BL106: =D106="" | BW106: =AND(CNTR_HasEntriesA,COUNTIF(A_InstData!$AH$62:$AH$71,TRUE())=0)
C107: 10 | G107: =CONST_t | AN107: =IF($D107="","",IF(MATCH($D107,CONST_PFCSlopeOrOvervoltage,0)=1,BE107,BH107)) | AO107: =IF(AN107="","",SUM(AN107)*AM107) | AP107: =IF($D107="","",CONST_GWP_CF4) | AQ107: =IF($D107="","",CONST_GWP_C2F6) | AR107: =IF($D107="","",SUM(AN107)*AP107) | AS107: =IF($D107="","",AO107*AQ107) | AU107: =IF($D107="","",SUM(AR107:AS107)/IF(AT107="",1,AT107)) | BA107: =CONST_CNTR_SUM_PFC | BE107: =F107*AG107*AH107*AI107/1000 | BF107: =IF(BE107="","",$AM107) | BH107: =IFERROR(F107*(AJ107/AK107)*AL107/1000,CONST_ERR_Incomplete) | BI107: =IF(BH107="","",$AM107) | BK107: =IF(D107="","",MATCH(D107,CONST_PFCSlopeOrOvervoltage,0)) | BL107: =D107="" | BW107: =AND(CNTR_HasEntriesA,COUNTIF(A_InstData!$AH$62:$AH$71,TRUE())=0)
A109: 3 | C109: (c) | D109: =Translations!$B$1964 | BA109: Emission sources
C110: =Translations!$B$131 | D110: =Translations!$B$122 | E110: =Translations!$B$209 | F110: =Translations!$B$134 | G110: =Translations!$B$135 | H110: =Translations!$B$136 | I110: =Translations!$B$137 | J110: =Translations!$B$138 | K110: =Translations!$B$139 | L110: =Translations!$B$140 | M110: =Translations!$B$141 | N110: =Translations!$B$142 | O110: =Translations!$B$143 | P110: =Translations!$B$144 | Q110: =Translations!$B$145 | R110: =Translations!$B$210 | S110: =Translations!$B$147 | T110: non-sust. BioC | U110: non-sust. BioC Unit | V110: =Translations!$B$150 | W110: =Translations!$B$151 | X110: =Translations!$B$152 | Y110: =Translations!$B$153 | Z110: =Translations!$B$1959 | AA110: =Translations!$B$1960 | AB110: Flue gas (total) | AC110: Flue gas (total), Unit | AD110: =Translations!$B$158 | AE110: =Translations!$B$159 | AF110: =Translations!$B$1961 | AG110: =Translations!$B$161 | AH110: =Translations!$B$162 | AI110: =Translations!$B$163 | AJ110: =Translations!$B$164 | AK110: =Translations!$B$165 | AL110: =Translations!$B$166 | AM110: =Translations!$B$167 | AN110: =Translations!$B$168 | AO110: =Translations!$B$169 | AP110: =Translations!$B$170 | AQ110: =Translations!$B$171 | AR110: =Translations!$B$172 | AS110: =Translations!$B$173 | AT110: =Translations!$B$174 | AU110: =Translations!$B$175 | AV110: =Translations!$B$176 | AW110: CO2e non-sust. bio (t) | AX110: =Translations!$B$178 | AY110: =Translations!$B$179
C111: =Translations!$B$180 | D111: N2O | E111: N2O | R111: 0 | S111: % | V111: 64.2925 | W111: =CONST_gpNm3 | X111: 4 | Y111: =CONST_hpa | Z111: 265 | AA111: =CONST_Nm3ph | AD111: =IF(E111="","",V111*X111*Z111/1000*(1-R111/100)) | AE111: =CONST_t | AF111: =IF(E111="","",IF(E111=INDEX(CONST_CEMSType,2),CONST_GWP_N2O,1)) | AU111: =IF(E111="","",V111*X111*Z111/1000*(1-R111/100)*AF111) | AV111: =IF(E111="","",V111*X111*Z111/1000*(R111/100)*AF111) | AW111: 0 | AX111: 0 | AY111: 0
C112: =Translations!$B$185 | D112: =Translations!$B$211 | E112: CO2 | R112: 15 | S112: % | V112: 1820 | W112: =CONST_gpNm3 | X112: 5000 | Y112: =CONST_hpa | Z112: 50 | AA112: =CONST_Nm3ph | AD112: =IF(E112="","",V112*X112*Z112/1000*(1-R112/100)) | AE112: =CONST_t | AF112: =IF(E112="","",IF(E112=INDEX(CONST_CEMSType,2),CONST_GWP_N2O,1)) | AU112: =IF(E112="","",V112*X112*Z112/1000*(1-R112/100)*AF112) | AV112: =IF(E112="","",V112*X112*Z112/1000*(R112/100)*AF112) | AW112: 0 | AX112: 0 | AY112: 0
C113: 1 | S113: % | W113: =CONST_gpNm3 | Y113: =CONST_hpa | AA113: =CONST_Nm3ph | AD113: =IF(E113="","",V113*X113*Z113/1000*(1-R113/100)) | AE113: =CONST_t | AF113: =IF(E113="","",IF(E113=INDEX(CONST_CEMSType,2),CONST_GWP_N2O,1)) | AU113: =IF(E113="","",V113*X113*Z113/1000*(1-R113/100)*AF113) | AV113: =IF(E113="","",V113*X113*Z113/1000*(R113/100)*AF113) | BA113: =IF(E113=INDEX(CONST_CEMSType,2),CONST_CNTR_SUM_N2O,CONST_CNTR_SUM_CO2) | BW113: =AND(CNTR_HasEntriesA,D113="")
C114: 2 | S114: % | W114: =CONST_gpNm3 | Y114: =CONST_hpa | AA114: =CONST_Nm3ph | AD114: =IF(E114="","",V114*X114*Z114/1000*(1-R114/100)) | AE114: =CONST_t | AF114: =IF(E114="","",IF(E114=INDEX(CONST_CEMSType,2),CONST_GWP_N2O,1)) | AU114: =IF(E114="","",V114*X114*Z114/1000*(1-R114/100)*AF114) | AV114: =IF(E114="","",V114*X114*Z114/1000*(R114/100)*AF114) | BA114: =IF(E114=INDEX(CONST_CEMSType,2),CONST_CNTR_SUM_N2O,CONST_CNTR_SUM_CO2) | BW114: =AND(CNTR_HasEntriesA,D114="")
C115: 3 | S115: % | W115: =CONST_gpNm3 | Y115: =CONST_hpa | AA115: =CONST_Nm3ph | AD115: =IF(E115="","",V115*X115*Z115/1000*(1-R115/100)) | AE115: =CONST_t | AF115: =IF(E115="","",IF(E115=INDEX(CONST_CEMSType,2),CONST_GWP_N2O,1)) | AU115: =IF(E115="","",V115*X115*Z115/1000*(1-R115/100)*AF115) | AV115: =IF(E115="","",V115*X115*Z115/1000*(R115/100)*AF115) | BA115: =IF(E115=INDEX(CONST_CEMSType,2),CONST_CNTR_SUM_N2O,CONST_CNTR_SUM_CO2) | BW115: =AND(CNTR_HasEntriesA,D115="")
C116: 4 | S116: % | W116: =CONST_gpNm3 | Y116: =CONST_hpa | AA116: =CONST_Nm3ph | AD116: =IF(E116="","",V116*X116*Z116/1000*(1-R116/100)) | AE116: =CONST_t | AF116: =IF(E116="","",IF(E116=INDEX(CONST_CEMSType,2),CONST_GWP_N2O,1)) | AU116: =IF(E116="","",V116*X116*Z116/1000*(1-R116/100)*AF116) | AV116: =IF(E116="","",V116*X116*Z116/1000*(R116/100)*AF116) | BA116: =IF(E116=INDEX(CONST_CEMSType,2),CONST_CNTR_SUM_N2O,CONST_CNTR_SUM_CO2) | BW116: =AND(CNTR_HasEntriesA,D116="")
C117: 5 | S117: % | W117: =CONST_gpNm3 | Y117: =CONST_hpa | AA117: =CONST_Nm3ph | AD117: =IF(E117="","",V117*X117*Z117/1000*(1-R117/100)) | AE117: =CONST_t | AF117: =IF(E117="","",IF(E117=INDEX(CONST_CEMSType,2),CONST_GWP_N2O,1)) | AU117: =IF(E117="","",V117*X117*Z117/1000*(1-R117/100)*AF117) | AV117: =IF(E117="","",V117*X117*Z117/1000*(R117/100)*AF117) | BA117: =IF(E117=INDEX(CONST_CEMSType,2),CONST_CNTR_SUM_N2O,CONST_CNTR_SUM_CO2) | BW117: =AND(CNTR_HasEntriesA,D117="")
C118: 6 | S118: % | W118: =CONST_gpNm3 | Y118: =CONST_hpa | AA118: =CONST_Nm3ph | AD118: =IF(E118="","",V118*X118*Z118/1000*(1-R118/100)) | AE118: =CONST_t | AF118: =IF(E118="","",IF(E118=INDEX(CONST_CEMSType,2),CONST_GWP_N2O,1)) | AU118: =IF(E118="","",V118*X118*Z118/1000*(1-R118/100)*AF118) | AV118: =IF(E118="","",V118*X118*Z118/1000*(R118/100)*AF118) | BA118: =IF(E118=INDEX(CONST_CEMSType,2),CONST_CNTR_SUM_N2O,CONST_CNTR_SUM_CO2) | BW118: =AND(CNTR_HasEntriesA,D118="")
C119: 7 | S119: % | W119: =CONST_gpNm3 | Y119: =CONST_hpa | AA119: =CONST_Nm3ph | AD119: =IF(E119="","",V119*X119*Z119/1000*(1-R119/100)) | AE119: =CONST_t | AF119: =IF(E119="","",IF(E119=INDEX(CONST_CEMSType,2),CONST_GWP_N2O,1)) | AU119: =IF(E119="","",V119*X119*Z119/1000*(1-R119/100)*AF119) | AV119: =IF(E119="","",V119*X119*Z119/1000*(R119/100)*AF119) | BA119: =IF(E119=INDEX(CONST_CEMSType,2),CONST_CNTR_SUM_N2O,CONST_CNTR_SUM_CO2) | BW119: =AND(CNTR_HasEntriesA,D119="")
C120: 8 | S120: % | W120: =CONST_gpNm3 | Y120: =CONST_hpa | AA120: =CONST_Nm3ph | AD120: =IF(E120="","",V120*X120*Z120/1000*(1-R120/100)) | AE120: =CONST_t | AF120: =IF(E120="","",IF(E120=INDEX(CONST_CEMSType,2),CONST_GWP_N2O,1)) | AU120: =IF(E120="","",V120*X120*Z120/1000*(1-R120/100)*AF120) | AV120: =IF(E120="","",V120*X120*Z120/1000*(R120/100)*AF120) | BA120: =IF(E120=INDEX(CONST_CEMSType,2),CONST_CNTR_SUM_N2O,CONST_CNTR_SUM_CO2) | BW120: =AND(CNTR_HasEntriesA,D120="")
C121: 9 | S121: % | W121: =CONST_gpNm3 | Y121: =CONST_hpa | AA121: =CONST_Nm3ph | AD121: =IF(E121="","",V121*X121*Z121/1000*(1-R121/100)) | AE121: =CONST_t | AF121: =IF(E121="","",IF(E121=INDEX(CONST_CEMSType,2),CONST_GWP_N2O,1)) | AU121: =IF(E121="","",V121*X121*Z121/1000*(1-R121/100)*AF121) | AV121: =IF(E121="","",V121*X121*Z121/1000*(R121/100)*AF121) | BA121: =IF(E121=INDEX(CONST_CEMSType,2),CONST_CNTR_SUM_N2O,CONST_CNTR_SUM_CO2) | BW121: =AND(CNTR_HasEntriesA,D121="")
C122: 10 | S122: % | W122: =CONST_gpNm3 | Y122: =CONST_hpa | AA122: =CONST_Nm3ph | AD122: =IF(E122="","",V122*X122*Z122/1000*(1-R122/100)) | AE122: =CONST_t | AF122: =IF(E122="","",IF(E122=INDEX(CONST_CEMSType,2),CONST_GWP_N2O,1)) | AU122: =IF(E122="","",V122*X122*Z122/1000*(1-R122/100)*AF122) | AV122: =IF(E122="","",V122*X122*Z122/1000*(R122/100)*AF122) | BA122: =IF(E122=INDEX(CONST_CEMSType,2),CONST_CNTR_SUM_N2O,CONST_CNTR_SUM_CO2) | BW122: =AND(CNTR_HasEntriesA,D122="")
A124: ausblenden | AZ124: PRINT

Sheet C_Emissions&Energy
A1: ausblenden | P1: ausblenden | Q1: ausblenden | R1: ausblenden | S1: ausblenden | T1: ausblenden | U1: ausblenden | V1: ausblenden | W1: ausblenden | X1: ausblenden
B2: =Translations!$B$212 | E2: =Translations!$B$11 | G2: =HYPERLINK("#"&ADDRESS(2,3,,,a_Contents!$U$2),a_Contents!$B$2) | I2: =HYPERLINK("#"&ADDRESS(2,3,,,G_FurtherGuidance!$U$2),G_FurtherGuidance!$B$2) | K2: =HYPERLINK("#"&ADDRESS(2,3,,,Summary_Processes!$Y$2),Summary_Processes!$Y$2) | M2: =HYPERLINK("#"&ADDRESS(2,3,,,Summary_Products!$BF$2),Summary_Products!$BF$2) | R2: Print area: | S2: =ADDRESS(ROW($B$2),COLUMN($B$2)) & ":" & ADDRESS(MATCH("PRINT",$P:$P,0),COLUMN($O$19)) | T2: Name of this sheet | U2: =IF(ISERROR(CELL("filename",V2)),"C_Emissions&Energy",MID(CELL("filename",V2),FIND("]",CELL("filename",V2))+1,1024))
G3: =IFERROR(HYPERLINK("#"&ADDRESS(ROW($A$1)+MATCH(R3,$A:$A,0)-1,3),INDEX($R:$R,MATCH(R3,$A:$A,0))),"") | I3: =IFERROR(HYPERLINK("#"&ADDRESS(ROW($A$1)+MATCH(T3,$A:$A,0)-1,3),INDEX($R:$R,MATCH(T3,$A:$A,0))),"") | R3: 1 | T3: 2
C6: C. | E6: =Translations!$B$213 | R6: Values | S6: EmbedEm | V6: Errors | X6: Cond. form.
A8: =C8 | C8: 1 | D8: =Translations!$B$215 | R8: =D8
D10: =Translations!$B$216
D11: - | E11: =Translations!$B$217
D12: - | E12: =Translations!$B$218
D13: - | E13: =Translations!$B$219
E14: =Translations!$B$220 | G14: =Translations!$B$221 | H14: =Translations!$B$222 | I14: =Translations!$B$223 | J14: =Translations!$B$224 | K14: =Translations!$B$225 | L14: =Translations!$B$226
D15: i. | E15: =Translations!$B$227 | G15: =CONST_TJ | H15: =IF(CNTR_HasEntriesA,SUMIFS(B_EmInst!$AX:$AX,B_EmInst!$BA:$BA,CONST_CNTR_SUM_CO2)+SUMIFS(B_EmInst!$AY:$AY,B_EmInst!$BA:$BA,CONST_CNTR_SUM_CO2),"")
D16: ii. | E16: =Translations!$B$228 | G16: =CONST_TJ | I16: 61470 | J16: 12800
D17: iii. | E17: =Translations!$B$229 | G17: =CONST_TJ | H17: =IF(H16="",H15,H16) | I17: =IF(I16="","",I16) | J17: =IF(J16="","",J16) | K17: =IF(K16="","",K16) | L17: =IF(COUNT(H17:K17)>0,SUM(H17)-SUM(I17:K17),"")
A19: =C19 | C19: 2 | D19: =Translations!$B$230 | R19: GHG balance & data quality
D21: (a) | E21: =Translations!$B$1850
E22: =Translations!$B$231
E23: =Translations!$B$1965
E24: =Translations!$B$232 | G24: =Translations!$B$221 | H24: =Translations!$B$233 | I24: =Translations!$B$234 | J24: =Translations!$B$235 | K24: =Translations!$B$236 | L24: =Translations!$B$237 | M24: =Translations!$B$238 | N24: =Translations!$B$239
D25: i. | E25: =Translations!$B$227 | G25: =CONST_tCO2eq | H25: =IF(CNTR_HasEntriesA,SUMIFS(B_EmInst!$AU:$AU,B_EmInst!$BA:$BA,CONST_CNTR_SUM_CO2),"") | I25: =IF(CNTR_HasEntriesA,SUMIFS(B_EmInst!AV:AV,B_EmInst!$BA:$BA,CONST_CNTR_SUM_CO2),"") | J25: =IF(CNTR_HasEntriesA,SUMIFS(B_EmInst!$AU:$AU,B_EmInst!$BA:$BA,CONST_CNTR_SUM_N2O),"") | K25: =IF(CNTR_HasEntriesA,SUMIFS(B_EmInst!$AU:$AU,B_EmInst!$BA:$BA,CONST_CNTR_SUM_PFC),"") | L25: =IF(COUNT(H25:K25)>0,SUM(H25,J25:K25),"")
D26: ii. | E26: =Translations!$B$228 | G26: =CONST_tCO2eq | M26: 976918.88
D27: iii. | E27: =Translations!$B$229 | G27: =CONST_tCO2eq | H27: =IF(CNTR_HasEntriesA,IF(H26="",H25,H26),"") | I27: =IF(CNTR_HasEntriesA,IF(I26="",I25,I26),"") | J27: =IF(CNTR_HasEntriesA,IF(J26="",J25,J26),"") | K27: =IF(CNTR_HasEntriesA,IF(K26="",K25,K26),"") | L27: =IF(CNTR_HasEntriesA,SUM(H27,J27:K27),"") | M27: =IF(M26="","",M26) | N27: =IF(COUNT(L27:M27)>0,SUM(L27:M27),"")
D29: (b) | E29: =Translations!$B$1851
E30: =Translations!$B$1852
G31: =Translations!$B$221 | H31: =Translations!$B$1853 | I31: =Translations!$B$236 | J31: =Translations!$B$1854 | K31: =Translations!$B$638
E32: =Translations!$B$561 | G32: =CONST_tCO2eq | H32: =IF(CNTR_HasEntriesA,SUM(B_EmInst!AU17:AU91),"") | I32: =IF(CNTR_HasEntriesA,K27,"") | J32: =IF(CNTR_HasEntriesA,SUM(B_EmInst!AU113:AU122),"") | K32: =IF(CNTR_HasEntriesA,SUM(L27)-SUM(H32:J32),"")
D34: (c) | E34: =Translations!$B$1855
E36: =Translations!$B$1856 | F36: =Translations!$B$1857
E37: =Translations!$B$1858 | F37: =Translations!$B$1859
E38: =Translations!$B$1860 | F38: =Translations!$B$1886
D40: i. | E40: =Translations!$B$1856 | H40: Mostly measurements & national standard factors for e.g. the emission factor | R40: =IF(H40="","",MATCH(H40,CONST_DataQuality,0))
D41: ii. | E41: =Translations!$B$1858 | R41: =IF(H41="","",MATCH(H41,CONST_DataQualityJustification,0)) | X41: =IF(H40="",FALSE(),H40<>INDEX(CONST_DataQuality,5))
D42: iii. | E42: =Translations!$B$1860 | H42: Four eyes principle | R42: =IF(H42="","",MATCH(H42,CONST_DataVerification,0))
A45: ausblenden | P45: PRINT
A46: ausblenden
A47: ausblenden

Sheet D_Processes
A1: ausblenden | P1: ausblenden | Q1: ausblenden | R1: ausblenden | S1: ausblenden | T1: ausblenden | U1: ausblenden | V1: ausblenden | W1: ausblenden | X1: ausblenden
B2: =Translations!$B$240 | E2: =Translations!$B$11 | G2: =HYPERLINK("#"&ADDRESS(2,3,,,a_Contents!$U$2),a_Contents!$B$2) | I2: =HYPERLINK("#"&ADDRESS(MATCH($S13,G_FurtherGuidance!$S:$S,0),3,,,G_FurtherGuidance!$U$2),G_FurtherGuidance!$B$2) | K2: =HYPERLINK("#"&ADDRESS(2,3,,,Summary_Processes!$Y$2),Summary_Processes!$Y$2) | M2: =HYPERLINK("#"&ADDRESS(2,3,,,Summary_Products!$BF$2),Summary_Products!$BF$2) | R2: Print area: | S2: =ADDRESS(ROW($B$2),COLUMN($B$50)) & ":" & ADDRESS(MATCH("PRINT",$P:$P,0),COLUMN($O$50)) | T2: Name of this sheet | U2: =IF(ISERROR(CELL("filename",V2)),"D_Processes",MID(CELL("filename",V2),FIND("]",CELL("filename",V2))+1,1024))
G3: =IF(INDEX(CNTR_List_ExistProdProcNames,R3)=CONST_NA,"",HYPERLINK("#"&ADDRESS(ROW($C$11)+MATCH(R3,$C$11:$C$662,0)-1,COLUMN($C$11)),INDEX(CNTR_List_ExistProdProcNames,R3))) | I3: =IF(INDEX(CNTR_List_ExistProdProcNames,T3)=CONST_NA,"",HYPERLINK("#"&ADDRESS(ROW($C$11)+MATCH(T3,$C$11:$C$662,0)-1,COLUMN($C$11)),INDEX(CNTR_List_ExistProdProcNames,T3))) | K3: =IF(INDEX(CNTR_List_ExistProdProcNames,V3)=CONST_NA,"",HYPERLINK("#"&ADDRESS(ROW($C$11)+MATCH(V3,$C$11:$C$662,0)-1,COLUMN($C$11)),INDEX(CNTR_List_ExistProdProcNames,V3))) | M3: =IF(INDEX(CNTR_List_ExistProdProcNames,X3)=CONST_NA,"",HYPERLINK("#"&ADDRESS(ROW($C$11)+MATCH(X3,$C$11:$C$662,0)-1,COLUMN($C$11)),INDEX(CNTR_List_ExistProdProcNames,X3))) | R3: 1 | T3: 2 | V3: 3 | X3: 4
G4: =IF(INDEX(CNTR_List_ExistProdProcNames,R4)=CONST_NA,"",HYPERLINK("#"&ADDRESS(ROW($C$11)+MATCH(R4,$C$11:$C$662,0)-1,COLUMN($C$11)),INDEX(CNTR_List_ExistProdProcNames,R4))) | I4: =IF(INDEX(CNTR_List_ExistProdProcNames,T4)=CONST_NA,"",HYPERLINK("#"&ADDRESS(ROW($C$11)+MATCH(T4,$C$11:$C$662,0)-1,COLUMN($C$11)),INDEX(CNTR_List_ExistProdProcNames,T4))) | K4: =IF(INDEX(CNTR_List_ExistProdProcNames,V4)=CONST_NA,"",HYPERLINK("#"&ADDRESS(ROW($C$11)+MATCH(V4,$C$11:$C$662,0)-1,COLUMN($C$11)),INDEX(CNTR_List_ExistProdProcNames,V4))) | M4: =IF(INDEX(CNTR_List_ExistProdProcNames,X4)=CONST_NA,"",HYPERLINK("#"&ADDRESS(ROW($C$11)+MATCH(X4,$C$11:$C$662,0)-1,COLUMN($C$11)),INDEX(CNTR_List_ExistProdProcNames,X4))) | R4: 5 | T4: 6 | V4: 7 | X4: 8
G5: =IF(INDEX(CNTR_List_ExistProdProcNames,R5)=CONST_NA,"",HYPERLINK("#"&ADDRESS(ROW($C$11)+MATCH(R5,$C$11:$C$662,0)-1,COLUMN($C$11)),INDEX(CNTR_List_ExistProdProcNames,R5))) | I5: =IF(INDEX(CNTR_List_ExistProdProcNames,T5)=CONST_NA,"",HYPERLINK("#"&ADDRESS(ROW($C$11)+MATCH(T5,$C$11:$C$662,0)-1,COLUMN($C$11)),INDEX(CNTR_List_ExistProdProcNames,T5))) | R5: 9 | T5: 10
C7: D. | E7: =Translations!$B$241 | R7: Marker | S7: EmbedEm | V7: Errors | X7: Cond. form.
A9: 1 | D9: =Translations!$B$242
C11: 1 | D11: =CONST_ProductionProcess & " " & C11 & ":" | G11: =IF(INDEX(CNTR_List_ExistProdProcNames,R11)=CONST_NA,"",INDEX(CNTR_List_ExistProdProcNames,R11)) | L11: =IF(INDEX(CNTR_List_ExistProdProc,R11)=CONST_NA,"",INDEX(CNTR_List_ExistProdProc,R11)) | R11: =C11 | W11: Not relevant: | X11: =AND(CNTR_HasEntriesA,G11="")
E13: =HYPERLINK("#"&ADDRESS(MATCH($S13,G_FurtherGuidance!$S:$S,0),3,,,G_FurtherGuidance!$U$2),CONST_LinkToGuidanceSheet) | R13: Link to guidance: | S13: 3
D15: (a) | E15: =Translations!$B$243 | H15: =Translations!$B$244 | K15: =Translations!$B$221 | L15: =Translations!$B$245
D16: 1 | E16: =IF(G11="","",G11) & IF(L11="",""," | " & L11) | H16: =IF(L11="","",INDEX(CONST_MATRIX_ProductionRoute,MATCH(L11,CONST_LIST_Goods,0),D16)) | K16: =IF(L11="","",INDEX(CONST_LIST_GoodsUnit,MATCH(L11,CONST_LIST_Goods,0))) | L16: 4800000 | S16: 1 | V16: =IF(AND(G11<>"",E16<>"",L16<>""),TRUE(),IF(AND(G11<>"",OR(AND(E16<>"",L16=""),AND(E16="",L16<>""))),CONST_ErrorOrMissing&C11,CONST_NA))
D17: 2 | E17: =IF(H17=CONST_NA,"",E16) | H17: =IF(L11="","",INDEX(CONST_MATRIX_ProductionRoute,MATCH(L11,CONST_LIST_Goods,0),D17)) | K17: =IF(H17=CONST_NA,"",K16) | S17: 2 | V17: =IF(AND(G11<>"",E17<>"",L17<>""),TRUE(),IF(AND(G11<>"",OR(AND(E17<>"",L17=""),AND(E17="",L17<>""))),CONST_ErrorOrMissing&C11,CONST_NA))
D18: 3 | E18: =IF(H18=CONST_NA,"",E17) | H18: =IF(L11="","",INDEX(CONST_MATRIX_ProductionRoute,MATCH(L11,CONST_LIST_Goods,0),D18)) | K18: =IF(H18=CONST_NA,"",K17) | S18: 3 | V18: =IF(AND(G11<>"",E18<>"",L18<>""),TRUE(),IF(AND(G11<>"",OR(AND(E18<>"",L18=""),AND(E18="",L18<>""))),CONST_ErrorOrMissing&C11,CONST_NA))
D19: 4 | E19: =IF(H19=CONST_NA,"",E18) | H19: =IF(L11="","",INDEX(CONST_MATRIX_ProductionRoute,MATCH(L11,CONST_LIST_Goods,0),D19)) | K19: =IF(H19=CONST_NA,"",K18) | S19: 4 | V19: =IF(AND(G11<>"",E19<>"",L19<>""),TRUE(),IF(AND(G11<>"",OR(AND(E19<>"",L19=""),AND(E19="",L19<>""))),CONST_ErrorOrMissing&C11,CONST_NA))
D20: 5 | E20: =IF(H20=CONST_NA,"",E19) | H20: =IF(L11="","",INDEX(CONST_MATRIX_ProductionRoute,MATCH(L11,CONST_LIST_Goods,0),D20)) | K20: =IF(H20=CONST_NA,"",K19) | S20: 5 | V20: =IF(AND(G11<>"",E20<>"",L20<>""),TRUE(),IF(AND(G11<>"",OR(AND(E20<>"",L20=""),AND(E20="",L20<>""))),CONST_ErrorOrMissing&C11,CONST_NA))
D21: 6 | E21: =IF(H21=CONST_NA,"",E20) | H21: =IF(L11="","",INDEX(CONST_MATRIX_ProductionRoute,MATCH(L11,CONST_LIST_Goods,0),D21)) | K21: =IF(H21=CONST_NA,"",K20) | S21: 6 | V21: =IF(AND(G11<>"",E21<>"",L21<>""),TRUE(),IF(AND(G11<>"",OR(AND(E21<>"",L21=""),AND(E21="",L21<>""))),CONST_ErrorOrMissing&C11,CONST_NA))
D22: 7 | E22: =IF(H22=CONST_NA,"",E21) | H22: =IF(L11="","",INDEX(CONST_MATRIX_ProductionRoute,MATCH(L11,CONST_LIST_Goods,0),D22)) | K22: =IF(H22=CONST_NA,"",K21) | S22: 7 | V22: =IF(AND(G11<>"",E22<>"",L22<>""),TRUE(),IF(AND(G11<>"",OR(AND(E22<>"",L22=""),AND(E22="",L22<>""))),CONST_ErrorOrMissing&C11,CONST_NA))
D23: 8 | E23: =IF(H23=CONST_NA,"",E22) | H23: =IF(L11="","",INDEX(CONST_MATRIX_ProductionRoute,MATCH(L11,CONST_LIST_Goods,0),D23)) | K23: =IF(H23=CONST_NA,"",K22) | S23: 8 | V23: =IF(AND(G11<>"",E23<>"",L23<>""),TRUE(),IF(AND(G11<>"",OR(AND(E23<>"",L23=""),AND(E23="",L23<>""))),CONST_ErrorOrMissing&C11,CONST_NA))
E24: =Translations!$B$246 | K24: =K16 | L24: =IF(G11="","",SUM(L16:L23)) | R24: =CONST_CNTR_TotProd&G11 | T24: =IF(G11="","",L24)
D26: (b) | E26: =Translations!$B$247 | K26: =Translations!$B$221 | L26: =Translations!$B$245
D27: i. | E27: =Translations!$B$248 | K27: =K16 | L27: =L16 | R27: =CONST_GoodToMarket&G11 | T27: =IF($G$11="","",L27) | V27: =IF(AND(G11<>"",L27<>""),TRUE(),IF(AND(G11<>"",OR(L27="",L16<>"")),CONST_ErrorOrMissing&C11,CONST_NA))
D28: ii. | E28: =Translations!$B$249 | L28: =IF(AND(COUNT(L24,L27)=2,SUM(L24>0)),SUM(L27)/SUM(L24),"")
D29: iii. | E29: =Translations!$B$250 | L29: =IF(G11="","",AND(SUM(L24)>0,SUM(L24)=SUM(L27)))
D31: (c) | E31: =Translations!$B$251 | K31: =Translations!$B$221 | L31: =Translations!$B$245 | S31: Numbering | W31: cond.form. | X31: =IF(G11="",FALSE(),L29)
D32: 1 | E32: =IF(INDEX(CNTR_List_ExistProdProcNames,S32)=CONST_NA,"",INDEX(CNTR_List_ExistProdProcNames,S32)) | K32: =K16 | R32: =CONST_PrecursorToGoodInput&G11 &"_"&E32 | S32: =MAX(S31:S31)+IF(D32=C11,2,1) | T32: =IF(G11="","",L32) | V32: =IF(AND(G11<>"",E32<>"",L32<>""),TRUE(),IF(AND(G11<>"",E32<>"",L32="",X32=FALSE()),CONST_ErrorOrMissing&C11,CONST_NA)) | W32: cond.form. | X32: =IF(G11="",FALSE(),OR(L29,E32=""))
D33: 2 | E33: =IF(INDEX(CNTR_List_ExistProdProcNames,S33)=CONST_NA,"",INDEX(CNTR_List_ExistProdProcNames,S33)) | K33: =K32 | R33: =CONST_PrecursorToGoodInput&G11 &"_"&E33 | S33: =MAX(S31:S32)+IF(D33=C11,2,1) | T33: =IF(G11="","",L33) | V33: =IF(AND(G11<>"",E33<>"",L33<>""),TRUE(),IF(AND(G11<>"",E33<>"",L33="",X33=FALSE()),CONST_ErrorOrMissing&C11,CONST_NA)) | X33: =IF(G11="",FALSE(),OR(L29,E33=""))
D34: 3 | E34: =IF(INDEX(CNTR_List_ExistProdProcNames,S34)=CONST_NA,"",INDEX(CNTR_List_ExistProdProcNames,S34)) | K34: =K33 | R34: =CONST_PrecursorToGoodInput&G11 &"_"&E34 | S34: =MAX(S31:S33)+IF(D34=C11,2,1) | T34: =IF(G11="","",L34) | V34: =IF(AND(G11<>"",E34<>"",L34<>""),TRUE(),IF(AND(G11<>"",E34<>"",L34="",X34=FALSE()),CONST_ErrorOrMissing&C11,CONST_NA)) | X34: =IF(G11="",FALSE(),OR(L29,E34=""))
D35: 4 | E35: =IF(INDEX(CNTR_List_ExistProdProcNames,S35)=CONST_NA,"",INDEX(CNTR_List_ExistProdProcNames,S35)) | K35: =K34 | R35: =CONST_PrecursorToGoodInput&G11 &"_"&E35 | S35: =MAX(S31:S34)+IF(D35=C11,2,1) | T35: =IF(G11="","",L35) | V35: =IF(AND(G11<>"",E35<>"",L35<>""),TRUE(),IF(AND(G11<>"",E35<>"",L35="",X35=FALSE()),CONST_ErrorOrMissing&C11,CONST_NA)) | X35: =IF(G11="",FALSE(),OR(L29,E35=""))
D36: 5 | E36: =IF(INDEX(CNTR_List_ExistProdProcNames,S36)=CONST_NA,"",INDEX(CNTR_List_ExistProdProcNames,S36)) | K36: =K35 | R36: =CONST_PrecursorToGoodInput&G11 &"_"&E36 | S36: =MAX(S31:S35)+IF(D36=C11,2,1) | T36: =IF(G11="","",L36) | V36: =IF(AND(G11<>"",E36<>"",L36<>""),TRUE(),IF(AND(G11<>"",E36<>"",L36="",X36=FALSE()),CONST_ErrorOrMissing&C11,CONST_NA)) | X36: =IF(G11="",FALSE(),OR(L29,E36=""))
D37: 6 | E37: =IF(INDEX(CNTR_List_ExistProdProcNames,S37)=CONST_NA,"",INDEX(CNTR_List_ExistProdProcNames,S37)) | K37: =K36 | R37: =CONST_PrecursorToGoodInput&G11 &"_"&E37 | S37: =MAX(S31:S36)+IF(D37=C11,2,1) | T37: =IF(G11="","",L37) | V37: =IF(AND(G11<>"",E37<>"",L37<>""),TRUE(),IF(AND(G11<>"",E37<>"",L37="",X37=FALSE()),CONST_ErrorOrMissing&C11,CONST_NA)) | X37: =IF(G11="",FALSE(),OR(L29,E37=""))
D38: 7 | E38: =IF(INDEX(CNTR_List_ExistProdProcNames,S38)=CONST_NA,"",INDEX(CNTR_List_ExistProdProcNames,S38)) | K38: =K37 | R38: =CONST_PrecursorToGoodInput&G11 &"_"&E38 | S38: =MAX(S31:S37)+IF(D38=C11,2,1) | T38: =IF(G11="","",L38) | V38: =IF(AND(G11<>"",E38<>"",L38<>""),TRUE(),IF(AND(G11<>"",E38<>"",L38="",X38=FALSE()),CONST_ErrorOrMissing&C11,CONST_NA)) | X38: =IF(G11="",FALSE(),OR(L29,E38=""))
D39: 8 | E39: =IF(INDEX(CNTR_List_ExistProdProcNames,S39)=CONST_NA,"",INDEX(CNTR_List_ExistProdProcNames,S39)) | K39: =K38 | R39: =CONST_PrecursorToGoodInput&G11 &"_"&E39 | S39: =MAX(S31:S38)+IF(D39=C11,2,1) | T39: =IF(G11="","",L39) | V39: =IF(AND(G11<>"",E39<>"",L39<>""),TRUE(),IF(AND(G11<>"",E39<>"",L39="",X39=FALSE()),CONST_ErrorOrMissing&C11,CONST_NA)) | X39: =IF(G11="",FALSE(),OR(L29,E39=""))
D40: 9 | E40: =IF(INDEX(CNTR_List_ExistProdProcNames,S40)=CONST_NA,"",INDEX(CNTR_List_ExistProdProcNames,S40)) | K40: =K39 | R40: =CONST_PrecursorToGoodInput&G11 &"_"&E40 | S40: =MAX(S31:S39)+IF(D40=C11,2,1) | T40: =IF(G11="","",L40) | V40: =IF(AND(G11<>"",E40<>"",L40<>""),TRUE(),IF(AND(G11<>"",E40<>"",L40="",X40=FALSE()),CONST_ErrorOrMissing&C11,CONST_NA)) | X40: =IF(G11="",FALSE(),OR(L29,E40=""))
D41: (d) | E41: =Translations!$B$252 | K41: =K40 | V41: =IF(AND(G11<>"",L41<>""),TRUE(),IF(AND(G11<>"",L41="",X41=FALSE()),CONST_ErrorOrMissing&C11,CONST_NA)) | W41: cond.form. | X41: =IF(G11="",FALSE(),L29)
D42: (e) | E42: =Translations!$B$253 | K42: =K41 | L42: =IF(G11="","",SUM(L24)-SUM(L27,L32:L41)) | V42: =IF(AND(G11<>"",L42=0),TRUE(),IF(AND(G11<>"",L42<>0,X42=FALSE()),CONST_ErrorOrMissing&C11,CONST_NA)) | X42: =IF(G11="",FALSE(),L29)
D45: =Translations!$B$254 | J45: =IF(G11="","",G11)
E47: =HYPERLINK("#"&ADDRESS(MATCH($S47,G_FurtherGuidance!$S:$S,0),3,,,G_FurtherGuidance!$U$2),CONST_LinkToGuidanceSheet) | R47: Link to guidance: | S47: 3
K49: =Translations!$B$255 | L49: =Translations!$B$256 | M49: =Translations!$B$257
D50: (f) | E50: =Translations!$B$258 | K50: =FALSE() | L50: =TRUE() | M50: =IF(L11="","",INDEX(CONST_LIST_GoodsIndRel,MATCH(L11,CONST_LIST_Goods,0))) | V50: =IF(AND(L11<>"",X50=FALSE()),IF(COUNTA(K50:L50)=2,TRUE(),CONST_ErrorOrMissing&C11),CONST_NA)
E51: =Translations!$B$259
K53: =Translations!$B$221 | L53: =Translations!$B$260
D54: (g) | E54: =Translations!$B$261 | K54: =CONST_tCO2eq | L54: ='C_Emissions&Energy'!H32 | R54: =CONST_EmDir&G11 | S54: =CONST_CNTR_EmbedEmDir&G11 | T54: =IF(G11="","",L54) | V54: =IF(L11<>"",IF(L54<>"",TRUE(),CONST_ErrorOrMissing&C11),CONST_NA)
D56: (h) | E56: =Translations!$B$262 | K56: =Translations!$B$221 | L56: =Translations!$B$263 | M56: =Translations!$B$264 | W56: cond.form. | X56: =AND(K50<>"",K50=FALSE())
D57: i. | E57: =Translations!$B$265 | K57: TJ | V57: =IF(AND(L11<>"",X57=FALSE()),IF(COUNTA(L57:M57)=2,TRUE(),CONST_ErrorOrMissing&C11),CONST_NA) | X57: =X56
D58: ii. | E58: =Translations!$B$266 | K58: =CONST_tCO2pTJ | R58: =CONST_EmDirHeat&G11 | S58: =CONST_CNTR_EmbedEmDir&G11 | T58: =IF(G11="","",SUM(L57*L58-M57*M58)) | V58: =IF(AND(L11<>"",X58=FALSE()),IF(COUNTA(L58:M58)=2,TRUE(),CONST_ErrorOrMissing&C11),CONST_NA) | X58: =X57
D60: (i) | E60: =Translations!$B$256 | K60: =Translations!$B$221 | L60: =Translations!$B$263 | M60: =Translations!$B$264 | W60: cond.form. | X60: =AND(L50<>"",L50=FALSE())
D61: i. | E61: =Translations!$B$267 | K61: =CONST_TJ | L61: 0 | M61: 12800 | V61: =IF(AND(L11<>"",X61=FALSE()),IF(COUNTA(L61:M61)=2,TRUE(),CONST_ErrorOrMissing&C11),CONST_NA) | X61: =X60
D62: ii. | E62: =Translations!$B$268 | K62: =CONST_tCO2pTJ | R62: =CONST_EmDirWasteGases&G11 | S62: =CONST_CNTR_EmbedEmDir&G11 | T62: =IF(G11="","",SUM(L61*CONST_EFNatGas-M61*CONST_EFNatGas*0.667)) | X62: =X61
D64: (j) | E64: =Translations!$B$269 | K64: =Translations!$B$221 | L64: =Translations!$B$260 | W64: cond.form. | X64: =M50=FALSE()
D65: i. | E65: =Translations!$B$270 | K65: =CONST_MWh | L65: 1658844 | R65: =CONST_ElecConsumption&G11 | T65: =IF(G11="","",L65) | V65: =IF(AND(L11<>"",X65=FALSE()),IF(L65<>"",TRUE(),CONST_ErrorOrMissing&C11),CONST_NA) | X65: =X64
D66: ii. | E66: =Translations!$B$271 | K66: =CONST_tCO2&"/"&CONST_MWh | L66: 0.589 | S66: =CONST_CNTR_EmbedEmInDir&G11 | T66: =IF(G11="","",SUM(L65)*SUM(L66)) | V66: =IF(AND(L11<>"",X66=FALSE()),IF(L66<>"",TRUE(),CONST_ErrorOrMissing&C11),CONST_NA) | X66: =X65
D67: iii. | E67: =Translations!$B$272 | K67: - | L67: Mix | R67: =CONST_CNTR_ElecEFMethod&G11 | T67: =IF(L67="","",L67) | V67: =IF(AND(L11<>"",X67=FALSE()),IF(L67<>"",TRUE(),CONST_ErrorOrMissing&C11),CONST_NA) | X67: =X66
D70: (k) | E70: =Translations!$B$273 | K70: =Translations!$B$221 | L70: =Translations!$B$260
D71: i. | E71: =Translations!$B$274 | K71: MWh | L71: 0 | V71: =IF(L11<>"",IF(L71<>"",TRUE(),CONST_ErrorOrMissing&C11),CONST_NA)
D72: ii. | E72: =Translations!$B$271 | K72: =CONST_tCO2&"/"&CONST_MWh | S72: =CONST_CNTR_EmbedEmDir&G11 | T72: =IF(G11="","",-SUM(L71)*SUM(L72)) | V72: =IF(AND(L11<>"",SUM(L71)>0),IF(L72<>"",TRUE(),CONST_ErrorOrMissing&C11),CONST_NA)
C76: =C11+1 | D76: =CONST_ProductionProcess & " " & C76 & ":" | G76: =IF(INDEX(CNTR_List_ExistProdProcNames,R76)=CONST_NA,"",INDEX(CNTR_List_ExistProdProcNames,R76)) | L76: =IF(INDEX(CNTR_List_ExistProdProc,R76)=CONST_NA,"",INDEX(CNTR_List_ExistProdProc,R76)) | R76: =C76 | W76: Not relevant: | X76: =AND(CNTR_HasEntriesA,G76="")
E78: =HYPERLINK("#"&ADDRESS(MATCH($S78,G_FurtherGuidance!$S:$S,0),3,,,G_FurtherGuidance!$U$2),CONST_LinkToGuidanceSheet) | R78: Link to guidance: | S78: 3
D80: (a) | E80: =Translations!$B$243 | H80: =Translations!$B$244 | K80: =Translations!$B$221 | L80: =Translations!$B$245
D81: 1 | E81: =IF(G76="","",G76) & IF(L76="",""," | " & L76) | H81: =IF(L76="","",INDEX(CONST_MATRIX_ProductionRoute,MATCH(L76,CONST_LIST_Goods,0),D81)) | K81: =IF(L76="","",INDEX(CONST_LIST_GoodsUnit,MATCH(L76,CONST_LIST_Goods,0))) | L81: 1500000 | S81: 1 | V81: =IF(AND(G76<>"",E81<>"",L81<>""),TRUE(),IF(AND(G76<>"",OR(AND(E81<>"",L81=""),AND(E81="",L81<>""))),CONST_ErrorOrMissing&C76,CONST_NA))
D82: 2 | E82: =IF(H82=CONST_NA,"",E81) | H82: =IF(L76="","",INDEX(CONST_MATRIX_ProductionRoute,MATCH(L76,CONST_LIST_Goods,0),D82)) | K82: =IF(H82=CONST_NA,"",K81) | L82: 1500000 | S82: 2 | V82: =IF(AND(G76<>"",E82<>"",L82<>""),TRUE(),IF(AND(G76<>"",OR(AND(E82<>"",L82=""),AND(E82="",L82<>""))),CONST_ErrorOrMissing&C76,CONST_NA))
D83: 3 | E83: =IF(H83=CONST_NA,"",E82) | H83: =IF(L76="","",INDEX(CONST_MATRIX_ProductionRoute,MATCH(L76,CONST_LIST_Goods,0),D83)) | K83: =IF(H83=CONST_NA,"",K82) | L83: 1500000 | S83: 3 | V83: =IF(AND(G76<>"",E83<>"",L83<>""),TRUE(),IF(AND(G76<>"",OR(AND(E83<>"",L83=""),AND(E83="",L83<>""))),CONST_ErrorOrMissing&C76,CONST_NA))
D84: 4 | E84: =IF(H84=CONST_NA,"",E83) | H84: =IF(L76="","",INDEX(CONST_MATRIX_ProductionRoute,MATCH(L76,CONST_LIST_Goods,0),D84)) | K84: =IF(H84=CONST_NA,"",K83) | L84: 1500000 | S84: 4 | V84: =IF(AND(G76<>"",E84<>"",L84<>""),TRUE(),IF(AND(G76<>"",OR(AND(E84<>"",L84=""),AND(E84="",L84<>""))),CONST_ErrorOrMissing&C76,CONST_NA))
D85: 5 | E85: =IF(H85=CONST_NA,"",E84) | H85: =IF(L76="","",INDEX(CONST_MATRIX_ProductionRoute,MATCH(L76,CONST_LIST_Goods,0),D85)) | K85: =IF(H85=CONST_NA,"",K84) | S85: 5 | V85: =IF(AND(G76<>"",E85<>"",L85<>""),TRUE(),IF(AND(G76<>"",OR(AND(E85<>"",L85=""),AND(E85="",L85<>""))),CONST_ErrorOrMissing&C76,CONST_NA))
D86: 6 | E86: =IF(H86=CONST_NA,"",E85) | H86: =IF(L76="","",INDEX(CONST_MATRIX_ProductionRoute,MATCH(L76,CONST_LIST_Goods,0),D86)) | K86: =IF(H86=CONST_NA,"",K85) | S86: 6 | V86: =IF(AND(G76<>"",E86<>"",L86<>""),TRUE(),IF(AND(G76<>"",OR(AND(E86<>"",L86=""),AND(E86="",L86<>""))),CONST_ErrorOrMissing&C76,CONST_NA))
D87: 7 | E87: =IF(H87=CONST_NA,"",E86) | H87: =IF(L76="","",INDEX(CONST_MATRIX_ProductionRoute,MATCH(L76,CONST_LIST_Goods,0),D87)) | K87: =IF(H87=CONST_NA,"",K86) | S87: 7 | V87: =IF(AND(G76<>"",E87<>"",L87<>""),TRUE(),IF(AND(G76<>"",OR(AND(E87<>"",L87=""),AND(E87="",L87<>""))),CONST_ErrorOrMissing&C76,CONST_NA))
D88: 8 | E88: =IF(H88=CONST_NA,"",E87) | H88: =IF(L76="","",INDEX(CONST_MATRIX_ProductionRoute,MATCH(L76,CONST_LIST_Goods,0),D88)) | K88: =IF(H88=CONST_NA,"",K87) | S88: 8 | V88: =IF(AND(G76<>"",E88<>"",L88<>""),TRUE(),IF(AND(G76<>"",OR(AND(E88<>"",L88=""),AND(E88="",L88<>""))),CONST_ErrorOrMissing&C76,CONST_NA))
E89: =Translations!$B$246 | K89: =K81 | L89: =IF(G76="","",SUM(L81:L88)) | R89: =CONST_CNTR_TotProd&G76 | T89: =IF(G76="","",L89)
D91: (b) | E91: =Translations!$B$247 | K91: =Translations!$B$221 | L91: =Translations!$B$245
D92: i. | E92: =Translations!$B$248 | K92: =K81 | L92: 6000000 | R92: =CONST_GoodToMarket&G76 | T92: =IF($G$11="","",L92) | V92: =IF(AND(G76<>"",L92<>""),TRUE(),IF(AND(G76<>"",OR(L92="",L81<>"")),CONST_ErrorOrMissing&C76,CONST_NA))
D93: ii. | E93: =Translations!$B$249 | L93: =IF(AND(COUNT(L89,L92)=2,SUM(L89>0)),SUM(L92)/SUM(L89),"")
D94: iii. | E94: =Translations!$B$250 | L94: =IF(G76="","",AND(SUM(L89)>0,SUM(L89)=SUM(L92)))
D96: (c) | E96: =Translations!$B$251 | K96: =Translations!$B$221 | L96: =Translations!$B$245 | S96: Numbering | W96: cond.form. | X96: =IF(G76="",FALSE(),L94)
D97: 1 | E97: =IF(INDEX(CNTR_List_ExistProdProcNames,S97)=CONST_NA,"",INDEX(CNTR_List_ExistProdProcNames,S97)) | K97: =K81 | R97: =CONST_PrecursorToGoodInput&G76 &"_"&E97 | S97: =MAX(S96:S96)+IF(D97=C76,2,1) | T97: =IF(G76="","",L97) | V97: =IF(AND(G76<>"",E97<>"",L97<>""),TRUE(),IF(AND(G76<>"",E97<>"",L97="",X97=FALSE()),CONST_ErrorOrMissing&C76,CONST_NA)) | W97: cond.form. | X97: =IF(G76="",FALSE(),OR(L94,E97=""))
D98: 2 | E98: =IF(INDEX(CNTR_List_ExistProdProcNames,S98)=CONST_NA,"",INDEX(CNTR_List_ExistProdProcNames,S98)) | K98: =K97 | R98: =CONST_PrecursorToGoodInput&G76 &"_"&E98 | S98: =MAX(S96:S97)+IF(D98=C76,2,1) | T98: =IF(G76="","",L98) | V98: =IF(AND(G76<>"",E98<>"",L98<>""),TRUE(),IF(AND(G76<>"",E98<>"",L98="",X98=FALSE()),CONST_ErrorOrMissing&C76,CONST_NA)) | X98: =IF(G76="",FALSE(),OR(L94,E98=""))
D99: 3 | E99: =IF(INDEX(CNTR_List_ExistProdProcNames,S99)=CONST_NA,"",INDEX(CNTR_List_ExistProdProcNames,S99)) | K99: =K98 | R99: =CONST_PrecursorToGoodInput&G76 &"_"&E99 | S99: =MAX(S96:S98)+IF(D99=C76,2,1) | T99: =IF(G76="","",L99) | V99: =IF(AND(G76<>"",E99<>"",L99<>""),TRUE(),IF(AND(G76<>"",E99<>"",L99="",X99=FALSE()),CONST_ErrorOrMissing&C76,CONST_NA)) | X99: =IF(G76="",FALSE(),OR(L94,E99=""))
D100: 4 | E100: =IF(INDEX(CNTR_List_ExistProdProcNames,S100)=CONST_NA,"",INDEX(CNTR_List_ExistProdProcNames,S100)) | K100: =K99 | R100: =CONST_PrecursorToGoodInput&G76 &"_"&E100 | S100: =MAX(S96:S99)+IF(D100=C76,2,1) | T100: =IF(G76="","",L100) | V100: =IF(AND(G76<>"",E100<>"",L100<>""),TRUE(),IF(AND(G76<>"",E100<>"",L100="",X100=FALSE()),CONST_ErrorOrMissing&C76,CONST_NA)) | X100: =IF(G76="",FALSE(),OR(L94,E100=""))
D101: 5 | E101: =IF(INDEX(CNTR_List_ExistProdProcNames,S101)=CONST_NA,"",INDEX(CNTR_List_ExistProdProcNames,S101)) | K101: =K100 | R101: =CONST_PrecursorToGoodInput&G76 &"_"&E101 | S101: =MAX(S96:S100)+IF(D101=C76,2,1) | T101: =IF(G76="","",L101) | V101: =IF(AND(G76<>"",E101<>"",L101<>""),TRUE(),IF(AND(G76<>"",E101<>"",L101="",X101=FALSE()),CONST_ErrorOrMissing&C76,CONST_NA)) | X101: =IF(G76="",FALSE(),OR(L94,E101=""))
D102: 6 | E102: =IF(INDEX(CNTR_List_ExistProdProcNames,S102)=CONST_NA,"",INDEX(CNTR_List_ExistProdProcNames,S102)) | K102: =K101 | R102: =CONST_PrecursorToGoodInput&G76 &"_"&E102 | S102: =MAX(S96:S101)+IF(D102=C76,2,1) | T102: =IF(G76="","",L102) | V102: =IF(AND(G76<>"",E102<>"",L102<>""),TRUE(),IF(AND(G76<>"",E102<>"",L102="",X102=FALSE()),CONST_ErrorOrMissing&C76,CONST_NA)) | X102: =IF(G76="",FALSE(),OR(L94,E102=""))
D103: 7 | E103: =IF(INDEX(CNTR_List_ExistProdProcNames,S103)=CONST_NA,"",INDEX(CNTR_List_ExistProdProcNames,S103)) | K103: =K102 | R103: =CONST_PrecursorToGoodInput&G76 &"_"&E103 | S103: =MAX(S96:S102)+IF(D103=C76,2,1) | T103: =IF(G76="","",L103) | V103: =IF(AND(G76<>"",E103<>"",L103<>""),TRUE(),IF(AND(G76<>"",E103<>"",L103="",X103=FALSE()),CONST_ErrorOrMissing&C76,CONST_NA)) | X103: =IF(G76="",FALSE(),OR(L94,E103=""))
D104: 8 | E104: =IF(INDEX(CNTR_List_ExistProdProcNames,S104)=CONST_NA,"",INDEX(CNTR_List_ExistProdProcNames,S104)) | K104: =K103 | R104: =CONST_PrecursorToGoodInput&G76 &"_"&E104 | S104: =MAX(S96:S103)+IF(D104=C76,2,1) | T104: =IF(G76="","",L104) | V104: =IF(AND(G76<>"",E104<>"",L104<>""),TRUE(),IF(AND(G76<>"",E104<>"",L104="",X104=FALSE()),CONST_ErrorOrMissing&C76,CONST_NA)) | X104: =IF(G76="",FALSE(),OR(L94,E104=""))
D105: 9 | E105: =IF(INDEX(CNTR_List_ExistProdProcNames,S105)=CONST_NA,"",INDEX(CNTR_List_ExistProdProcNames,S105)) | K105: =K104 | R105: =CONST_PrecursorToGoodInput&G76 &"_"&E105 | S105: =MAX(S96:S104)+IF(D105=C76,2,1) | T105: =IF(G76="","",L105) | V105: =IF(AND(G76<>"",E105<>"",L105<>""),TRUE(),IF(AND(G76<>"",E105<>"",L105="",X105=FALSE()),CONST_ErrorOrMissing&C76,CONST_NA)) | X105: =IF(G76="",FALSE(),OR(L94,E105=""))
D106: (d) | E106: =Translations!$B$252 | K106: =K105 | V106: =IF(AND(G76<>"",L106<>""),TRUE(),IF(AND(G76<>"",L106="",X106=FALSE()),CONST_ErrorOrMissing&C76,CONST_NA)) | W106: cond.form. | X106: =IF(G76="",FALSE(),L94)
D107: (e) | E107: =Translations!$B$253 | K107: =K106 | L107: =IF(G76="","",SUM(L89)-SUM(L92,L97:L106)) | V107: =IF(AND(G76<>"",L107=0),TRUE(),IF(AND(G76<>"",L107<>0,X107=FALSE()),CONST_ErrorOrMissing&C76,CONST_NA)) | X107: =IF(G76="",FALSE(),L94)
D110: =Translations!$B$254 | J110: =IF(G76="","",G76)
E112: =HYPERLINK("#"&ADDRESS(MATCH($S112,G_FurtherGuidance!$S:$S,0),3,,,G_FurtherGuidance!$U$2),CONST_LinkToGuidanceSheet) | R112: Link to guidance: | S112: 3
K114: =Translations!$B$255 | L114: =Translations!$B$256 | M114: =Translations!$B$257
D115: (f) | E115: =Translations!$B$258 | K115: FALSE | L115: FALSE | M115: =IF(L76="","",INDEX(CONST_LIST_GoodsIndRel,MATCH(L76,CONST_LIST_Goods,0))) | V115: =IF(AND(L76<>"",X115=FALSE()),IF(COUNTA(K115:L115)=2,TRUE(),CONST_ErrorOrMissing&C76),CONST_NA)
E116: =Translations!$B$259
K118: =Translations!$B$221 | L118: =Translations!$B$260
D119: (g) | E119: =Translations!$B$261 | K119: =CONST_tCO2eq | L119: 7000000 | R119: =CONST_EmDir&G76 | S119: =CONST_CNTR_EmbedEmDir&G76 | T119: =IF(G76="","",L119) | V119: =IF(L76<>"",IF(L119<>"",TRUE(),CONST_ErrorOrMissing&C76),CONST_NA)
D121: (h) | E121: =Translations!$B$262 | K121: =Translations!$B$221 | L121: =Translations!$B$263 | M121: =Translations!$B$264 | W121: cond.form. | X121: =AND(K115<>"",K115=FALSE())
D122: i. | E122: =Translations!$B$265 | K122: TJ | V122: =IF(AND(L76<>"",X122=FALSE()),IF(COUNTA(L122:M122)=2,TRUE(),CONST_ErrorOrMissing&C76),CONST_NA) | X122: =X121
D123: ii. | E123: =Translations!$B$266 | K123: =CONST_tCO2pTJ | R123: =CONST_EmDirHeat&G76 | S123: =CONST_CNTR_EmbedEmDir&G76 | T123: =IF(G76="","",SUM(L122*L123-M122*M123)) | V123: =IF(AND(L76<>"",X123=FALSE()),IF(COUNTA(L123:M123)=2,TRUE(),CONST_ErrorOrMissing&C76),CONST_NA) | X123: =X122
D125: (i) | E125: =Translations!$B$256 | K125: =Translations!$B$221 | L125: =Translations!$B$263 | M125: =Translations!$B$264 | W125: cond.form. | X125: =AND(L115<>"",L115=FALSE())
D126: i. | E126: =Translations!$B$267 | K126: =CONST_TJ | V126: =IF(AND(L76<>"",X126=FALSE()),IF(COUNTA(L126:M126)=2,TRUE(),CONST_ErrorOrMissing&C76),CONST_NA) | X126: =X125
D127: ii. | E127: =Translations!$B$268 | K127: =CONST_tCO2pTJ | R127: =CONST_EmDirWasteGases&G76 | S127: =CONST_CNTR_EmbedEmDir&G76 | T127: =IF(G76="","",SUM(L126*CONST_EFNatGas-M126*CONST_EFNatGas*0.667)) | X127: =X126
D129: (j) | E129: =Translations!$B$269 | K129: =Translations!$B$221 | L129: =Translations!$B$260 | W129: cond.form. | X129: =M115=FALSE()
D130: i. | E130: =Translations!$B$270 | K130: =CONST_MWh | L130: 1658844 | R130: =CONST_ElecConsumption&G76 | T130: =IF(G76="","",L130) | V130: =IF(AND(L76<>"",X130=FALSE()),IF(L130<>"",TRUE(),CONST_ErrorOrMissing&C76),CONST_NA) | X130: =X129
D131: ii. | E131: =Translations!$B$271 | K131: =CONST_tCO2&"/"&CONST_MWh | L131: 0.589 | S131: =CONST_CNTR_EmbedEmInDir&G76 | T131: =IF(G76="","",SUM(L130)*SUM(L131)) | V131: =IF(AND(L76<>"",X131=FALSE()),IF(L131<>"",TRUE(),CONST_ErrorOrMissing&C76),CONST_NA) | X131: =X130
D132: iii. | E132: =Translations!$B$272 | K132: - | L132: Mix | R132: =CONST_CNTR_ElecEFMethod&G76 | T132: =IF(L132="","",L132) | V132: =IF(AND(L76<>"",X132=FALSE()),IF(L132<>"",TRUE(),CONST_ErrorOrMissing&C76),CONST_NA) | X132: =X131
...

Sheet E_PurchPrec
A1: ausblenden | P1: ausblenden | Q1: ausblenden | R1: ausblenden | S1: ausblenden | T1: ausblenden | U1: ausblenden | V1: ausblenden | W1: ausblenden | X1: ausblenden | Y1: ausblenden | Z1: ausblenden
B2: =Translations!$B$124 | E2: =Translations!$B$11 | G2: =HYPERLINK("#"&ADDRESS(2,3,,,a_Contents!$U$2),a_Contents!$B$2) | I2: =HYPERLINK("#"&ADDRESS(MATCH($S10,G_FurtherGuidance!$S:$S,0),3,,,G_FurtherGuidance!$U$2),G_FurtherGuidance!$B$2) | K2: =HYPERLINK("#"&ADDRESS(2,3,,,Summary_Processes!$Y$2),Summary_Processes!$Y$2) | M2: =HYPERLINK("#"&ADDRESS(2,3,,,Summary_Products!$BF$2),Summary_Products!$BF$2) | R2: Print area: | S2: =ADDRESS(ROW($B$12),COLUMN($B$12)) & ":" & ADDRESS(MATCH("PRINT",$P:$P,0),COLUMN($O$12)) | T2: Name of this sheet | U2: =IF(ISERROR(CELL("filename",V2)),"E_PurchPrec",MID(CELL("filename",V2),FIND("]",CELL("filename",V2))+1,1024))
E3: =IF(INDEX(CNTR_List_ExistPurchPrecNames,R3)=CONST_NA,"",HYPERLINK("#"&ADDRESS(ROW($C$14)+MATCH(R3,$C$14:$C$1032,0)-1,COLUMN($C$14)),INDEX(CNTR_List_ExistPurchPrecNames,R3))) | G3: =IF(INDEX(CNTR_List_ExistPurchPrecNames,T3)=CONST_NA,"",HYPERLINK("#"&ADDRESS(ROW($C$14)+MATCH(T3,$C$14:$C$1032,0)-1,COLUMN($C$14)),INDEX(CNTR_List_ExistPurchPrecNames,T3))) | I3: =IF(INDEX(CNTR_List_ExistPurchPrecNames,V3)=CONST_NA,"",HYPERLINK("#"&ADDRESS(ROW($C$14)+MATCH(V3,$C$14:$C$1032,0)-1,COLUMN($C$14)),INDEX(CNTR_List_ExistPurchPrecNames,V3))) | K3: =IF(INDEX(CNTR_List_ExistPurchPrecNames,X3)=CONST_NA,"",HYPERLINK("#"&ADDRESS(ROW($C$14)+MATCH(X3,$C$14:$C$1032,0)-1,COLUMN($C$14)),INDEX(CNTR_List_ExistPurchPrecNames,X3))) | M3: =IF(INDEX(CNTR_List_ExistPurchPrecNames,Z3)=CONST_NA,"",HYPERLINK("#"&ADDRESS(ROW($C$14)+MATCH(Z3,$C$14:$C$1032,0)-1,COLUMN($C$14)),INDEX(CNTR_List_ExistPurchPrecNames,Z3))) | R3: 1 | T3: =R3+1 | V3: =T3+1 | X3: =V3+1 | Z3: =X3+1
E4: =IF(INDEX(CNTR_List_ExistPurchPrecNames,R4)=CONST_NA,"",HYPERLINK("#"&ADDRESS(ROW($C$14)+MATCH(R4,$C$14:$C$1032,0)-1,COLUMN($C$14)),INDEX(CNTR_List_ExistPurchPrecNames,R4))) | G4: =IF(INDEX(CNTR_List_ExistPurchPrecNames,T4)=CONST_NA,"",HYPERLINK("#"&ADDRESS(ROW($C$14)+MATCH(T4,$C$14:$C$1032,0)-1,COLUMN($C$14)),INDEX(CNTR_List_ExistPurchPrecNames,T4))) | I4: =IF(INDEX(CNTR_List_ExistPurchPrecNames,V4)=CONST_NA,"",HYPERLINK("#"&ADDRESS(ROW($C$14)+MATCH(V4,$C$14:$C$1032,0)-1,COLUMN($C$14)),INDEX(CNTR_List_ExistPurchPrecNames,V4))) | K4: =IF(INDEX(CNTR_List_ExistPurchPrecNames,X4)=CONST_NA,"",HYPERLINK("#"&ADDRESS(ROW($C$14)+MATCH(X4,$C$14:$C$1032,0)-1,COLUMN($C$14)),INDEX(CNTR_List_ExistPurchPrecNames,X4))) | M4: =IF(INDEX(CNTR_List_ExistPurchPrecNames,Z4)=CONST_NA,"",HYPERLINK("#"&ADDRESS(ROW($C$14)+MATCH(Z4,$C$14:$C$1032,0)-1,COLUMN($C$14)),INDEX(CNTR_List_ExistPurchPrecNames,Z4))) | R4: =Z3+1 | T4: =R4+1 | V4: =T4+1 | X4: =V4+1 | Z4: =X4+1
E5: =IF(INDEX(CNTR_List_ExistPurchPrecNames,R5)=CONST_NA,"",HYPERLINK("#"&ADDRESS(ROW($C$14)+MATCH(R5,$C$14:$C$1032,0)-1,COLUMN($C$14)),INDEX(CNTR_List_ExistPurchPrecNames,R5))) | G5: =IF(INDEX(CNTR_List_ExistPurchPrecNames,T5)=CONST_NA,"",HYPERLINK("#"&ADDRESS(ROW($C$14)+MATCH(T5,$C$14:$C$1032,0)-1,COLUMN($C$14)),INDEX(CNTR_List_ExistPurchPrecNames,T5))) | I5: =IF(INDEX(CNTR_List_ExistPurchPrecNames,V5)=CONST_NA,"",HYPERLINK("#"&ADDRESS(ROW($C$14)+MATCH(V5,$C$14:$C$1032,0)-1,COLUMN($C$14)),INDEX(CNTR_List_ExistPurchPrecNames,V5))) | K5: =IF(INDEX(CNTR_List_ExistPurchPrecNames,X5)=CONST_NA,"",HYPERLINK("#"&ADDRESS(ROW($C$14)+MATCH(X5,$C$14:$C$1032,0)-1,COLUMN($C$14)),INDEX(CNTR_List_ExistPurchPrecNames,X5))) | M5: =IF(INDEX(CNTR_List_ExistPurchPrecNames,Z5)=CONST_NA,"",HYPERLINK("#"&ADDRESS(ROW($C$14)+MATCH(Z5,$C$14:$C$1032,0)-1,COLUMN($C$14)),INDEX(CNTR_List_ExistPurchPrecNames,Z5))) | R5: =Z4+1 | T5: =R5+1 | V5: =T5+1 | X5: =V5+1 | Z5: =X5+1
E6: =IF(INDEX(CNTR_List_ExistPurchPrecNames,R6)=CONST_NA,"",HYPERLINK("#"&ADDRESS(ROW($C$14)+MATCH(R6,$C$14:$C$1032,0)-1,COLUMN($C$14)),INDEX(CNTR_List_ExistPurchPrecNames,R6))) | G6: =IF(INDEX(CNTR_List_ExistPurchPrecNames,T6)=CONST_NA,"",HYPERLINK("#"&ADDRESS(ROW($C$14)+MATCH(T6,$C$14:$C$1032,0)-1,COLUMN($C$14)),INDEX(CNTR_List_ExistPurchPrecNames,T6))) | I6: =IF(INDEX(CNTR_List_ExistPurchPrecNames,V6)=CONST_NA,"",HYPERLINK("#"&ADDRESS(ROW($C$14)+MATCH(V6,$C$14:$C$1032,0)-1,COLUMN($C$14)),INDEX(CNTR_List_ExistPurchPrecNames,V6))) | K6: =IF(INDEX(CNTR_List_ExistPurchPrecNames,X6)=CONST_NA,"",HYPERLINK("#"&ADDRESS(ROW($C$14)+MATCH(X6,$C$14:$C$1032,0)-1,COLUMN($C$14)),INDEX(CNTR_List_ExistPurchPrecNames,X6))) | M6: =IF(INDEX(CNTR_List_ExistPurchPrecNames,Z6)=CONST_NA,"",HYPERLINK("#"&ADDRESS(ROW($C$14)+MATCH(Z6,$C$14:$C$1032,0)-1,COLUMN($C$14)),INDEX(CNTR_List_ExistPurchPrecNames,Z6))) | R6: =Z5+1 | T6: =R6+1 | V6: =T6+1 | X6: =V6+1 | Z6: =X6+1
C8: E. | E8: =Translations!$B$275 | R8: Marker | S8: EmbedEm | V8: Errors | Z8: Cond. form.
E10: =HYPERLINK("#"&ADDRESS(MATCH($S10,G_FurtherGuidance!$S:$S,0),3,,,G_FurtherGuidance!$U$2),CONST_LinkToGuidanceSheet) | R10: Link to guidance: | S10: 4
A12: 1 | D12: =Translations!$B$242
V13: TRUE = green, n.a. = white
C14: 1 | D14: =CONST_PurchPrecursor & " " & C14 & ":" | G14: =IF(INDEX(CNTR_List_ExistPurchPrecNames,MATCH(R14,CNTR_ListPurchPrecID,0))=CONST_NA,"",INDEX(CNTR_List_ExistPurchPrecNames,MATCH(R14,CNTR_ListPurchPrecID,0))) | L14: =IF(INDEX(CNTR_List_ExistPurchPrec,MATCH(R14,CNTR_ListPurchPrecID,0))=CONST_NA,"",INDEX(CNTR_List_ExistPurchPrec,MATCH(R14,CNTR_ListPurchPrecID,0))) | R14: =INDEX(CNTR_ListPurchPrecID,C14) | Y14: Not relevant: | Z14: =AND(CNTR_HasEntriesA,G14="")
E15: =HYPERLINK("#"&ADDRESS(MATCH($S15,G_FurtherGuidance!$S:$S,0),3,,,G_FurtherGuidance!$U$2),CONST_LinkToGuidanceSheet) | R15: Link to guidance: | S15: 4
D16: (a) | E16: =Translations!$B$276 | H16: =Translations!$B$244 | K16: =Translations!$B$221 | L16: =Translations!$B$245 | Y16: cond.format
D17: 1 | E17: =IF(G14="","",G14) & IF(L14="",""," | " & L14) | H17: =IF(L14="","",INDEX(CONST_MATRIX_ProductionRoute,MATCH(L14,CONST_LIST_Goods,0),D17)) | K17: =IF(L14="","",INDEX(CONST_LIST_GoodsUnit,MATCH(L14,CONST_LIST_Goods,0))) | S17: 1 | V17: =IF(AND(Y17=FALSE(),ISNUMBER(L17)),TRUE(),IF(Y17=FALSE(),CONST_ErrorOrMissing&C14,CONST_NA)) | Y17: =IF(OR(H17="",H17=CONST_NA),"",IF(H17=CONST_AllProdRoutes,FALSE(), COUNTIF(INDEX(CNTR_MatrixPurchPrecRoutes,C14,),S17)=0))
D18: 2 | E18: =IF(H18=CONST_NA,"",E17) | H18: =IF(L14="","",INDEX(CONST_MATRIX_ProductionRoute,MATCH(L14,CONST_LIST_Goods,0),D18)) | K18: =IF(H18=CONST_NA,"",K17) | S18: 2 | V18: =IF(AND(Y18=FALSE(),ISNUMBER(L18)),TRUE(),IF(Y18=FALSE(),CONST_ErrorOrMissing&C14,CONST_NA)) | Y18: =IF(OR(H18="",H18=CONST_NA),"",IF(H18=CONST_AllProdRoutes,FALSE(), COUNTIF(INDEX(CNTR_MatrixPurchPrecRoutes,C14,),S18)=0))
D19: 3 | E19: =IF(H19=CONST_NA,"",E18) | H19: =IF(L14="","",INDEX(CONST_MATRIX_ProductionRoute,MATCH(L14,CONST_LIST_Goods,0),D19)) | K19: =IF(H19=CONST_NA,"",K18) | S19: 3 | V19: =IF(AND(Y19=FALSE(),ISNUMBER(L19)),TRUE(),IF(Y19=FALSE(),CONST_ErrorOrMissing&C14,CONST_NA)) | Y19: =IF(OR(H19="",H19=CONST_NA),"",IF(H19=CONST_AllProdRoutes,FALSE(), COUNTIF(INDEX(CNTR_MatrixPurchPrecRoutes,C14,),S19)=0))
D20: 4 | E20: =IF(H20=CONST_NA,"",E19) | H20: =IF(L14="","",INDEX(CONST_MATRIX_ProductionRoute,MATCH(L14,CONST_LIST_Goods,0),D20)) | K20: =IF(H20=CONST_NA,"",K19) | S20: 4 | V20: =IF(AND(Y20=FALSE(),ISNUMBER(L20)),TRUE(),IF(Y20=FALSE(),CONST_ErrorOrMissing&C14,CONST_NA)) | Y20: =IF(OR(H20="",H20=CONST_NA),"",IF(H20=CONST_AllProdRoutes,FALSE(), COUNTIF(INDEX(CNTR_MatrixPurchPrecRoutes,C14,),S20)=0))
D21: 5 | E21: =IF(H21=CONST_NA,"",E20) | H21: =IF(L14="","",INDEX(CONST_MATRIX_ProductionRoute,MATCH(L14,CONST_LIST_Goods,0),D21)) | K21: =IF(H21=CONST_NA,"",K20) | S21: 5 | V21: =IF(AND(Y21=FALSE(),ISNUMBER(L21)),TRUE(),IF(Y21=FALSE(),CONST_ErrorOrMissing&C14,CONST_NA)) | Y21: =IF(OR(H21="",H21=CONST_NA),"",IF(H21=CONST_AllProdRoutes,FALSE(), COUNTIF(INDEX(CNTR_MatrixPurchPrecRoutes,C14,),S21)=0))
D22: 6 | E22: =IF(H22=CONST_NA,"",E21) | H22: =IF(L14="","",INDEX(CONST_MATRIX_ProductionRoute,MATCH(L14,CONST_LIST_Goods,0),D22)) | K22: =IF(H22=CONST_NA,"",K21) | S22: 6 | V22: =IF(AND(Y22=FALSE(),ISNUMBER(L22)),TRUE(),IF(Y22=FALSE(),CONST_ErrorOrMissing&C14,CONST_NA)) | Y22: =IF(OR(H22="",H22=CONST_NA),"",IF(H22=CONST_AllProdRoutes,FALSE(), COUNTIF(INDEX(CNTR_MatrixPurchPrecRoutes,C14,),S22)=0))
D23: 7 | E23: =IF(H23=CONST_NA,"",E22) | H23: =IF(L14="","",INDEX(CONST_MATRIX_ProductionRoute,MATCH(L14,CONST_LIST_Goods,0),D23)) | K23: =IF(H23=CONST_NA,"",K22) | S23: 7 | V23: =IF(AND(Y23=FALSE(),ISNUMBER(L23)),TRUE(),IF(Y23=FALSE(),CONST_ErrorOrMissing&C14,CONST_NA)) | Y23: =IF(OR(H23="",H23=CONST_NA),"",IF(H23=CONST_AllProdRoutes,FALSE(), COUNTIF(INDEX(CNTR_MatrixPurchPrecRoutes,C14,),S23)=0))
D24: 8 | E24: =IF(H24=CONST_NA,"",E23) | H24: =IF(L14="","",INDEX(CONST_MATRIX_ProductionRoute,MATCH(L14,CONST_LIST_Goods,0),D24)) | K24: =IF(H24=CONST_NA,"",K23) | S24: 8 | V24: =IF(AND(Y24=FALSE(),ISNUMBER(L24)),TRUE(),IF(Y24=FALSE(),CONST_ErrorOrMissing&C14,CONST_NA)) | Y24: =IF(OR(H24="",H24=CONST_NA),"",IF(H24=CONST_AllProdRoutes,FALSE(), COUNTIF(INDEX(CNTR_MatrixPurchPrecRoutes,C14,),S24)=0))
E25: =Translations!$B$1966 | K25: =K17 | L25: =IF(G14="","",SUM(L17:L24)) | R25: =CONST_CNTR_TotProd&G14 | T25: =IF(G14="","",IF(SUM(L25)=0,100,L25))
D27: (b) | E27: =Translations!$B$1967 | K27: =Translations!$B$221 | L27: =Translations!$B$245 | S27: Numbering
D28: 1 | E28: =IF(INDEX(CNTR_List_ExistProdProcNames,S28)=CONST_NA,"",INDEX(CNTR_List_ExistProdProcNames,S28)) | K28: =IF(E28="","",K25) | R28: =CONST_PrecursorToGoodInput&G14 &"_"&E28 | S28: =D28 | T28: =IF(G14="","",L28) | V28: =IF(AND(G14<>"",E28<>"",L28<>""),TRUE(),IF(AND(G14<>"",E28<>"",L28="",Z28=FALSE()),CONST_ErrorOrMissing&C14,CONST_NA)) | Y28: cond.form. | Z28: =IF(G14="",FALSE(),E28="")
D29: 2 | E29: =IF(INDEX(CNTR_List_ExistProdProcNames,S29)=CONST_NA,"",INDEX(CNTR_List_ExistProdProcNames,S29)) | K29: =IF(E29="","",K28) | R29: =CONST_PrecursorToGoodInput&G14 &"_"&E29 | S29: =D29 | T29: =IF(G14="","",L29) | V29: =IF(AND(G14<>"",E29<>"",L29<>""),TRUE(),IF(AND(G14<>"",E29<>"",L29="",Z29=FALSE()),CONST_ErrorOrMissing&C14,CONST_NA)) | Z29: =IF(G14="",FALSE(),E29="")
D30: 3 | E30: =IF(INDEX(CNTR_List_ExistProdProcNames,S30)=CONST_NA,"",INDEX(CNTR_List_ExistProdProcNames,S30)) | K30: =IF(E30="","",K29) | R30: =CONST_PrecursorToGoodInput&G14 &"_"&E30 | S30: =D30 | T30: =IF(G14="","",L30) | V30: =IF(AND(G14<>"",E30<>"",L30<>""),TRUE(),IF(AND(G14<>"",E30<>"",L30="",Z30=FALSE()),CONST_ErrorOrMissing&C14,CONST_NA)) | Z30: =IF(G14="",FALSE(),E30="")
D31: 4 | E31: =IF(INDEX(CNTR_List_ExistProdProcNames,S31)=CONST_NA,"",INDEX(CNTR_List_ExistProdProcNames,S31)) | K31: =IF(E31="","",K30) | R31: =CONST_PrecursorToGoodInput&G14 &"_"&E31 | S31: =D31 | T31: =IF(G14="","",L31) | V31: =IF(AND(G14<>"",E31<>"",L31<>""),TRUE(),IF(AND(G14<>"",E31<>"",L31="",Z31=FALSE()),CONST_ErrorOrMissing&C14,CONST_NA)) | Z31: =IF(G14="",FALSE(),E31="")
D32: 5 | E32: =IF(INDEX(CNTR_List_ExistProdProcNames,S32)=CONST_NA,"",INDEX(CNTR_List_ExistProdProcNames,S32)) | K32: =IF(E32="","",K31) | R32: =CONST_PrecursorToGoodInput&G14 &"_"&E32 | S32: =D32 | T32: =IF(G14="","",L32) | V32: =IF(AND(G14<>"",E32<>"",L32<>""),TRUE(),IF(AND(G14<>"",E32<>"",L32="",Z32=FALSE()),CONST_ErrorOrMissing&C14,CONST_NA)) | Z32: =IF(G14="",FALSE(),E32="")
D33: 6 | E33: =IF(INDEX(CNTR_List_ExistProdProcNames,S33)=CONST_NA,"",INDEX(CNTR_List_ExistProdProcNames,S33)) | K33: =IF(E33="","",K32) | R33: =CONST_PrecursorToGoodInput&G14 &"_"&E33 | S33: =D33 | T33: =IF(G14="","",L33) | V33: =IF(AND(G14<>"",E33<>"",L33<>""),TRUE(),IF(AND(G14<>"",E33<>"",L33="",Z33=FALSE()),CONST_ErrorOrMissing&C14,CONST_NA)) | Z33: =IF(G14="",FALSE(),E33="")
D34: 7 | E34: =IF(INDEX(CNTR_List_ExistProdProcNames,S34)=CONST_NA,"",INDEX(CNTR_List_ExistProdProcNames,S34)) | K34: =IF(E34="","",K33) | R34: =CONST_PrecursorToGoodInput&G14 &"_"&E34 | S34: =D34 | T34: =IF(G14="","",L34) | V34: =IF(AND(G14<>"",E34<>"",L34<>""),TRUE(),IF(AND(G14<>"",E34<>"",L34="",Z34=FALSE()),CONST_ErrorOrMissing&C14,CONST_NA)) | Z34: =IF(G14="",FALSE(),E34="")
D35: 8 | E35: =IF(INDEX(CNTR_List_ExistProdProcNames,S35)=CONST_NA,"",INDEX(CNTR_List_ExistProdProcNames,S35)) | K35: =IF(E35="","",K34) | R35: =CONST_PrecursorToGoodInput&G14 &"_"&E35 | S35: =D35 | T35: =IF(G14="","",L35) | V35: =IF(AND(G14<>"",E35<>"",L35<>""),TRUE(),IF(AND(G14<>"",E35<>"",L35="",Z35=FALSE()),CONST_ErrorOrMissing&C14,CONST_NA)) | Z35: =IF(G14="",FALSE(),E35="")
D36: 9 | E36: =IF(INDEX(CNTR_List_ExistProdProcNames,S36)=CONST_NA,"",INDEX(CNTR_List_ExistProdProcNames,S36)) | K36: =IF(E36="","",K35) | R36: =CONST_PrecursorToGoodInput&G14 &"_"&E36 | S36: =D36 | T36: =IF(G14="","",L36) | V36: =IF(AND(G14<>"",E36<>"",L36<>""),TRUE(),IF(AND(G14<>"",E36<>"",L36="",Z36=FALSE()),CONST_ErrorOrMissing&C14,CONST_NA)) | Z36: =IF(G14="",FALSE(),E36="")
D37: 10 | E37: =IF(INDEX(CNTR_List_ExistProdProcNames,S37)=CONST_NA,"",INDEX(CNTR_List_ExistProdProcNames,S37)) | K37: =IF(E37="","",K36) | R37: =CONST_PrecursorToGoodInput&G14 &"_"&E37 | S37: =D37 | T37: =IF(G14="","",L37) | V37: =IF(AND(G14<>"",E37<>"",L37<>""),TRUE(),IF(AND(G14<>"",E37<>"",L37="",Z37=FALSE()),CONST_ErrorOrMissing&C14,CONST_NA)) | Z37: =IF(G14="",FALSE(),E37="")
D38: (c) | E38: =Translations!$B$1968 | K38: =K25 | V38: =IF(G14="",CONST_NA,IF(ISNUMBER(L38),TRUE(),CONST_ErrorOrMissing&C14))
D39: (d) | E39: =Translations!$B$253 | K39: =K38 | L39: =IF(G14="","",SUM(L25)-SUM(L28:L38)) | V39: =IF(G14="",CONST_NA,IF(L39=0,TRUE(),CONST_ErrorOrMissing&C14))
D42: =Translations!$B$279 | J42: =IF(G14="","",G14)
D44: (e) | E44: =Translations!$B$280
E46: =HYPERLINK("#"&ADDRESS(MATCH($S46,G_FurtherGuidance!$S:$S,0),3,,,G_FurtherGuidance!$U$2),CONST_LinkToGuidanceSheet) | R46: Link to guidance: | S46: 4
E48: =Translations!$B$284 | K48: =Translations!$B$221 | L48: =Translations!$B$260 | M48: =Translations!$B$285 | T48: Value | U48: Incomplete? | V48: Error?
D49: i. | E49: =Translations!$B$1969 | K49: =IF(L14="","",CONST_tCO2eq & "/" & K25) | R49: =CONST_PurchPrecDefaultUsed&G14 | S49: =CONST_CNTR_EmbedEmDir&G14 | T49: =IF(G14="","",SUM(T25)*SUM(L49)) | U49: =IF(G14="","",IF(M49="",CONST_ERR_Incomplete,MATCH(M49,CONST_MeasDefaultUnknown,0)=2)) | V49: =IF(AND(G14<>"",COUNTA(L49:M49)=2),TRUE(),IF(AND(G14<>"",COUNTA(L49:M49)<2),CONST_ErrorOrMissing&C14,CONST_NA))
D50: ii. | E50: =Translations!$B$1970 | K50: =IF(K49="","",CONST_MWh&"/"&K25) | R50: =CONST_ElecConsumption&G14 | T50: =IF(G14="","",SUM(T25)*SUM(L50)) | U50: =IF(G14="","",IF(M50="",CONST_ERR_Incomplete,MATCH(M50,CONST_MeasDefaultUnknown,0)=2)) | V50: =IF(AND(G14<>"",COUNTA(L50:M50)=2),TRUE(),IF(AND(G14<>"",COUNTA(L50:M50)<2),CONST_ErrorOrMissing&C14,CONST_NA))
D51: iii. | E51: =Translations!$B$1971 | K51: =IF(K49="","",CONST_tCO2eq&"/"&CONST_MWh) | R51: =CONST_CNTR_ElecEFMethod&G14 | U51: =IF(G14="","",M51) | V51: =IF(AND(G14<>"",COUNTA(L51:M51)=2),TRUE(),IF(AND(G14<>"",COUNTA(L51:M51)<2),CONST_ErrorOrMissing&C14,CONST_NA))
D52: iv. | E52: =Translations!$B$1972 | K52: =K49 | L52: =IF(COUNT(L50:L51)=0,"",L50*L51) | S52: =CONST_CNTR_EmbedEmInDir&G14 | T52: =IF(G14="","",SUM(T25)*SUM(L52))
D54: v. | E54: =Translations!$B$1858 | V54: =IF(OR(G14="",Z54=TRUE()),CONST_NA,IF(K54<>"",TRUE(),CONST_ErrorOrMissing&C14)) | Z54: =AND(M49<>"",M49<>INDEX(CONST_MeasDefaultUnknown,2),M50<>"",M50<>INDEX(CONST_MeasDefaultUnknown,2))
C58: =C14+1 | D58: =CONST_PurchPrecursor & " " & C58 & ":" | G58: =IF(INDEX(CNTR_List_ExistPurchPrecNames,MATCH(R58,CNTR_ListPurchPrecID,0))=CONST_NA,"",INDEX(CNTR_List_ExistPurchPrecNames,MATCH(R58,CNTR_ListPurchPrecID,0))) | L58: =IF(INDEX(CNTR_List_ExistPurchPrec,MATCH(R58,CNTR_ListPurchPrecID,0))=CONST_NA,"",INDEX(CNTR_List_ExistPurchPrec,MATCH(R58,CNTR_ListPurchPrecID,0))) | R58: =INDEX(CNTR_ListPurchPrecID,C58) | Y58: Not relevant: | Z58: =AND(CNTR_HasEntriesA,G58="")
E59: =HYPERLINK("#"&ADDRESS(MATCH($S59,G_FurtherGuidance!$S:$S,0),3,,,G_FurtherGuidance!$U$2),CONST_LinkToGuidanceSheet) | R59: Link to guidance: | S59: 4
D60: (a) | E60: =Translations!$B$276 | H60: =Translations!$B$244 | K60: =Translations!$B$221 | L60: =Translations!$B$245 | Y60: cond.format
D61: 1 | E61: =IF(G58="","",G58) & IF(L58="",""," | " & L58) | H61: =IF(L58="","",INDEX(CONST_MATRIX_ProductionRoute,MATCH(L58,CONST_LIST_Goods,0),D61)) | K61: =IF(L58="","",INDEX(CONST_LIST_GoodsUnit,MATCH(L58,CONST_LIST_Goods,0))) | S61: 1 | V61: =IF(AND(Y61=FALSE(),ISNUMBER(L61)),TRUE(),IF(Y61=FALSE(),CONST_ErrorOrMissing&C58,CONST_NA)) | Y61: =IF(OR(H61="",H61=CONST_NA),"",IF(H61=CONST_AllProdRoutes,FALSE(), COUNTIF(INDEX(CNTR_MatrixPurchPrecRoutes,C58,),S61)=0))
D62: 2 | E62: =IF(H62=CONST_NA,"",E61) | H62: =IF(L58="","",INDEX(CONST_MATRIX_ProductionRoute,MATCH(L58,CONST_LIST_Goods,0),D62)) | K62: =IF(H62=CONST_NA,"",K61) | S62: 2 | V62: =IF(AND(Y62=FALSE(),ISNUMBER(L62)),TRUE(),IF(Y62=FALSE(),CONST_ErrorOrMissing&C58,CONST_NA)) | Y62: =IF(OR(H62="",H62=CONST_NA),"",IF(H62=CONST_AllProdRoutes,FALSE(), COUNTIF(INDEX(CNTR_MatrixPurchPrecRoutes,C58,),S62)=0))
D63: 3 | E63: =IF(H63=CONST_NA,"",E62) | H63: =IF(L58="","",INDEX(CONST_MATRIX_ProductionRoute,MATCH(L58,CONST_LIST_Goods,0),D63)) | K63: =IF(H63=CONST_NA,"",K62) | S63: 3 | V63: =IF(AND(Y63=FALSE(),ISNUMBER(L63)),TRUE(),IF(Y63=FALSE(),CONST_ErrorOrMissing&C58,CONST_NA)) | Y63: =IF(OR(H63="",H63=CONST_NA),"",IF(H63=CONST_AllProdRoutes,FALSE(), COUNTIF(INDEX(CNTR_MatrixPurchPrecRoutes,C58,),S63)=0))
D64: 4 | E64: =IF(H64=CONST_NA,"",E63) | H64: =IF(L58="","",INDEX(CONST_MATRIX_ProductionRoute,MATCH(L58,CONST_LIST_Goods,0),D64)) | K64: =IF(H64=CONST_NA,"",K63) | S64: 4 | V64: =IF(AND(Y64=FALSE(),ISNUMBER(L64)),TRUE(),IF(Y64=FALSE(),CONST_ErrorOrMissing&C58,CONST_NA)) | Y64: =IF(OR(H64="",H64=CONST_NA),"",IF(H64=CONST_AllProdRoutes,FALSE(), COUNTIF(INDEX(CNTR_MatrixPurchPrecRoutes,C58,),S64)=0))
D65: 5 | E65: =IF(H65=CONST_NA,"",E64) | H65: =IF(L58="","",INDEX(CONST_MATRIX_ProductionRoute,MATCH(L58,CONST_LIST_Goods,0),D65)) | K65: =IF(H65=CONST_NA,"",K64) | S65: 5 | V65: =IF(AND(Y65=FALSE(),ISNUMBER(L65)),TRUE(),IF(Y65=FALSE(),CONST_ErrorOrMissing&C58,CONST_NA)) | Y65: =IF(OR(H65="",H65=CONST_NA),"",IF(H65=CONST_AllProdRoutes,FALSE(), COUNTIF(INDEX(CNTR_MatrixPurchPrecRoutes,C58,),S65)=0))
